Workbook
Name ExternalData_8: '3 customers'!$A$1:$J$92

Sheet 1 orders
A1: orderID | B1: customerID | C1: orderDate | D1: requiredDate | E1: shippedDate | F1: arrivedDate | G1: productID | H1: orderPrice | I1: orderQuantity | J1: discountApllied | K1: freightCost | L1: shipVia
A2: 10248 | B2: VINET | C2: 44746 | D2: 44774 | E2: 44758 | F2: 44766 | G2: 11 | H2: 14 | I2: 12 | J2: 0 | K2: 32.38 | L2: Federal Shipping
A3: 10248 | B3: VINET | C3: 44746 | D3: 44774 | E3: 44758 | F3: 44766 | G3: 42 | H3: 9.8 | I3: 10 | J3: 0 | K3: 32.38 | L3: Federal Shipping
A4: 10248 | B4: VINET | C4: 44746 | D4: 44774 | E4: 44758 | F4: 44766 | G4: 72 | H4: 34.8 | I4: 5 | J4: 0 | K4: 32.38 | L4: Federal Shipping
A5: 10249 | B5: TOMSP | C5: 44747 | D5: 44789 | E5: 44752 | F5: 44756 | G5: 14 | H5: 18.6 | I5: 9 | J5: 0 | K5: 11.61 | L5: Speedy Express
A6: 10249 | B6: TOMSP | C6: 44747 | D6: 44789 | E6: 44752 | F6: 44756 | G6: 51 | H6: 42.4 | I6: 40 | J6: 0 | K6: 11.61 | L6: Speedy Express
A7: 10250 | B7: HANAR | C7: 44750 | D7: 44778 | E7: 44754 | F7: 44771 | G7: 41 | H7: 7.7 | I7: 10 | J7: 0 | K7: 65.83 | L7: United Package
A8: 10250 | B8: HANAR | C8: 44750 | D8: 44778 | E8: 44754 | F8: 44771 | G8: 51 | H8: 42.4 | I8: 35 | J8: 0.15 | K8: 65.83 | L8: United Package
A9: 10250 | B9: HANAR | C9: 44750 | D9: 44778 | E9: 44754 | F9: 44771 | G9: 65 | H9: 16.8 | I9: 15 | J9: 0.15 | K9: 65.83 | L9: United Package
A10: 10251 | B10: VICTE | C10: 44750 | D10: 44778 | E10: 44757 | F10: 44761 | G10: 22 | H10: 16.8 | I10: 6 | J10: 0.05 | K10: 41.34 | L10: Speedy Express
A11: 10251 | B11: VICTE | C11: 44750 | D11: 44778 | E11: 44757 | F11: 44761 | G11: 57 | H11: 15.6 | I11: 15 | J11: 0.05 | K11: 41.34 | L11: Speedy Express
A12: 10251 | B12: VICTE | C12: 44750 | D12: 44778 | E12: 44757 | F12: 44761 | G12: 65 | H12: 16.8 | I12: 20 | J12: 0 | K12: 41.34 | L12: Speedy Express
A13: 10252 | B13: SUPRD | C13: 44751 | D13: 44779 | E13: 44753 | F13: 44766 | G13: 20 | H13: 64.8 | I13: 40 | J13: 0.05 | K13: 51.3 | L13: United Package
... A1964: 11007 | B1964: PRINI | C1964: 45390 | D1964: 45418 | E1964: 45395 | F1964: 45407 | G1964: 42 | H1964: 14 | I1964: 14 | J1964: 0 | K1964: 202.24 | L1964: United Package
A1965: 11008 | B1965: ERNSH | C1965: 45390 | D1965: 45418 | G1965: 28 | H1965: 45.6 | I1965: 70 | J1965: 0.05 | K1965: 79.46 | L1965: Federal Shipping
A1966: 11008 | B1966: ERNSH | C1966: 45390 | D1966: 45418 | G1966: 34 | H1966: 14 | I1966: 90 | J1966: 0.05 | K1966: 79.46 | L1966: Federal Shipping
A1967: 11008 | B1967: ERNSH | C1967: 45390 | D1967: 45418 | G1967: 71 | H1967: 21.5 | I1967: 21 | J1967: 0 | K1967: 79.46 | L1967: Federal Shipping
A1968: 11009 | B1968: GODOS | C1968: 45390 | D1968: 45418 | E1968: 45392 | F1968: 45400 | G1968: 24 | H1968: 4.5 | I1968: 12 | J1968: 0 | K1968: 59.11 | L1968: Speedy Express
A1969: 11009 | B1969: GODOS | C1969: 45390 | D1969: 45418 | E1969: 45392 | F1969: 45400 | G1969: 36 | H1969: 19 | I1969: 18 | J1969: 0.25 | K1969: 59.11 | L1969: Speedy Express
A1970: 11009 | B1970: GODOS | C1970: 45390 | D1970: 45418 | E1970: 45392 | F1970: 45400 | G1970: 60 | H1970: 34 | I1970: 9 | J1970: 0 | K1970: 59.11 | L1970: Speedy Express
A1971: 11010 | B1971: REGGC | C1971: 45391 | D1971: 45419 | E1971: 45403 | F1971: 45414 | G1971: 7 | H1971: 30 | I1971: 20 | J1971: 0 | K1971: 28.71 | L1971: United Package
A1972: 11010 | B1972: REGGC | C1972: 45391 | D1972: 45419 | E1972: 45403 | F1972: 45414 | G1972: 24 | H1972: 4.5 | I1972: 10 | J1972: 0 | K1972: 28.71 | L1972: United Package
A1973: 11011 | B1973: ALFKI | C1973: 45391 | D1973: 45419 | E1973: 45395 | F1973: 45398 | G1973: 58 | H1973: 13.25 | I1973: 40 | J1973: 0.05 | K1973: 1.21 | L1973: Speedy Express
A1974: 11011 | B1974: ALFKI | C1974: 45391 | D1974: 45419 | E1974: 45395 | F1974: 45398 | G1974: 71 | H1974: 21.5 | I1974: 20 | J1974: 0 | K1974: 1.21 | L1974: Speedy Express
A1975: 11012 | B1975: FRANK | C1975: 45391 | D1975: 45405 | E1975: 45399 | F1975: 45406 | G1975: 19 | H1975: 9.2 | I1975: 50 | J1975: 0.05 | K1975: 242.95 | L1975: Federal Shipping
A1976: 11012 | B1976: FRANK | C1976: 45391 | D1976: 45405 | E1976: 45399 | F1976: 45406 | G1976: 60 | H1976: 34 | I1976: 36 | J1976: 0.05 | K1976: 242.95 | L1976: Federal Shipping
A1977: 11012 | B1977: FRANK | C1977: 45391 | D1977: 45405 | E1977: 45399 | F1977: 45406 | G1977: 71 | H1977: 21.5 | I1977: 60 | J1977: 0.05 | K1977: 242.95 | L1977: Federal Shipping
A1978: 11013 | B1978: ROMEY | C1978: 45391 | D1978: 45419 | E1978: 45392 | F1978: 45400 | G1978: 23 | H1978: 9 | I1978: 10 | J1978: 0 | K1978: 32.99 | L1978: Speedy Express
A1979: 11013 | B1979: ROMEY | C1979: 45391 | D1979: 45419 | E1979: 45392 | F1979: 45400 | G1979: 42 | H1979: 14 | I1979: 4 | J1979: 0 | K1979: 32.99 | L1979: Speedy Express
... A1992: 11018 | B1992: LONEP | C1992: 45395 | D1992: 45423 | E1992: 45398 | F1992: 45417 | G1992: 56 | H1992: 38 | I1992: 5 | J1992: 0 | K1992: 11.65 | L1992: United Package
A1993: 11019 | B1993: RANCH | C1993: 45395 | D1993: 45423 | G1993: 46 | H1993: 12 | I1993: 3 | J1993: 0 | K1993: 3.17 | L1993: Federal Shipping
A1994: 11019 | B1994: RANCH | C1994: 45395 | D1994: 45423 | G1994: 49 | H1994: 20 | I1994: 2 | J1994: 0 | K1994: 3.17 | L1994: Federal Shipping
A1995: 11020 | B1995: OTTIK | C1995: 45396 | D1995: 45424 | E1995: 45398 | F1995: 45407 | G1995: 10 | H1995: 31 | I1995: 24 | J1995: 0.15 | K1995: 43.3 | L1995: United Package
A1996: 11021 | B1996: QUICK | C1996: 45396 | D1996: 45424 | E1996: 45403 | F1996: 45405 | G1996: 2 | H1996: 19 | I1996: 11 | J1996: 0.25 | K1996: 297.18 | L1996: Speedy Express
A1997: 11021 | B1997: QUICK | C1997: 45396 | D1997: 45424 | E1997: 45403 | F1997: 45405 | G1997: 20 | H1997: 81 | I1997: 15 | J1997: 0 | K1997: 297.18 | L1997: Speedy Express
A1998: 11021 | B1998: QUICK | C1998: 45396 | D1998: 45424 | E1998: 45403 | F1998: 45405 | G1998: 26 | H1998: 31.23 | I1998: 63 | J1998: 0 | K1998: 297.18 | L1998: Speedy Express
A1999: 11021 | B1999: QUICK | C1999: 45396 | D1999: 45424 | E1999: 45403 | F1999: 45405 | G1999: 51 | H1999: 53 | I1999: 44 | J1999: 0.25 | K1999: 297.18 | L1999: Speedy Express
A2000: 11021 | B2000: QUICK | C2000: 45396 | D2000: 45424 | E2000: 45403 | F2000: 45405 | G2000: 72 | H2000: 34.8 | I2000: 35 | J2000: 0 | K2000: 297.18 | L2000: Speedy Express
A2001: 11022 | B2001: HANAR | C2001: 45396 | D2001: 45424 | E2001: 45416 | F2001: 45437 | G2001: 19 | H2001: 9.2 | I2001: 35 | J2001: 0 | K2001: 6.27 | L2001: United Package
A2002: 11022 | B2002: HANAR | C2002: 45396 | D2002: 45424 | E2002: 45416 | F2002: 45437 | G2002: 69 | H2002: 36 | I2002: 30 | J2002: 0 | K2002: 6.27 | L2002: United Package
A2003: 11023 | B2003: BSBEV | C2003: 45396 | D2003: 45410 | E2003: 45406 | F2003: 45415 | G2003: 7 | H2003: 30 | I2003: 4 | J2003: 0 | K2003: 123.83 | L2003: United Package
A2004: 11023 | B2004: BSBEV | C2004: 45396 | D2004: 45410 | E2004: 45406 | F2004: 45415 | G2004: 43 | H2004: 46 | I2004: 30 | J2004: 0 | K2004: 123.83 | L2004: United Package
A2005: 11024 | B2005: EASTC | C2005: 45397 | D2005: 45425 | E2005: 45402 | F2005: 45409 | G2005: 26 | H2005: 31.23 | I2005: 12 | J2005: 0 | K2005: 74.36 | L2005: Speedy Express
A2006: 11024 | B2006: EASTC | C2006: 45397 | D2006: 45425 | E2006: 45402 | F2006: 45409 | G2006: 33 | H2006: 2.5 | I2006: 30 | J2006: 0 | K2006: 74.36 | L2006: Speedy Express
... A2045: 11038 | B2045: SUPRD | C2045: 45403 | D2045: 45431 | E2045: 45412 | F2045: 45424 | G2045: 71 | H2045: 21.5 | I2045: 30 | J2045: 0 | K2045: 29.59 | L2045: United Package
A2046: 11039 | B2046: LINOD | C2046: 45403 | D2046: 45431 | G2046: 28 | H2046: 45.6 | I2046: 20 | J2046: 0 | K2046: 65 | L2046: United Package
A2047: 11039 | B2047: LINOD | C2047: 45403 | D2047: 45431 | G2047: 35 | H2047: 18 | I2047: 24 | J2047: 0 | K2047: 65 | L2047: United Package
A2048: 11039 | B2048: LINOD | C2048: 45403 | D2048: 45431 | G2048: 49 | H2048: 20 | I2048: 60 | J2048: 0 | K2048: 65 | L2048: United Package
A2049: 11039 | B2049: LINOD | C2049: 45403 | D2049: 45431 | G2049: 57 | H2049: 19.5 | I2049: 28 | J2049: 0 | K2049: 65 | L2049: United Package
A2050: 11040 | B2050: GREAL | C2050: 45404 | D2050: 45432 | G2050: 21 | H2050: 10 | I2050: 20 | J2050: 0 | K2050: 18.84 | L2050: Federal Shipping
A2051: 11041 | B2051: CHOPS | C2051: 45404 | D2051: 45432 | E2051: 45410 | F2051: 45425 | G2051: 2 | H2051: 19 | I2051: 30 | J2051: 0.2 | K2051: 48.22 | L2051: United Package
A2052: 11041 | B2052: CHOPS | C2052: 45404 | D2052: 45432 | E2052: 45410 | F2052: 45425 | G2052: 63 | H2052: 43.9 | I2052: 30 | J2052: 0 | K2052: 48.22 | L2052: United Package
A2053: 11042 | B2053: COMMI | C2053: 45404 | D2053: 45418 | E2053: 45413 | F2053: 45429 | G2053: 44 | H2053: 19.45 | I2053: 15 | J2053: 0 | K2053: 29.99 | L2053: Speedy Express
A2054: 11042 | B2054: COMMI | C2054: 45404 | D2054: 45418 | E2054: 45413 | F2054: 45429 | G2054: 61 | H2054: 28.5 | I2054: 4 | J2054: 0 | K2054: 29.99 | L2054: Speedy Express
A2055: 11043 | B2055: SPECD | C2055: 45404 | D2055: 45432 | E2055: 45411 | F2055: 45419 | G2055: 11 | H2055: 21 | I2055: 10 | J2055: 0 | K2055: 8.8 | L2055: United Package
A2056: 11044 | B2056: WOLZA | C2056: 45405 | D2056: 45433 | E2056: 45413 | F2056: 45423 | G2056: 62 | H2056: 49.3 | I2056: 12 | J2056: 0 | K2056: 8.72 | L2056: Speedy Express
A2057: 11045 | B2057: BOTTM | C2057: 45405 | D2057: 45433 | G2057: 33 | H2057: 2.5 | I2057: 15 | J2057: 0 | K2057: 70.58 | L2057: United Package
A2058: 11045 | B2058: BOTTM | C2058: 45405 | D2058: 45433 | G2058: 51 | H2058: 53 | I2058: 24 | J2058: 0 | K2058: 70.58 | L2058: United Package
A2059: 11046 | B2059: WANDK | C2059: 45405 | D2059: 45433 | E2059: 45406 | F2059: 45415 | G2059: 12 | H2059: 38 | I2059: 20 | J2059: 0.05 | K2059: 71.64 | L2059: United Package
A2060: 11046 | B2060: WANDK | C2060: 45405 | D2060: 45433 | E2060: 45406 | F2060: 45415 | G2060: 32 | H2060: 32 | I2060: 15 | J2060: 0.05 | K2060: 71.64 | L2060: United Package
A2061: 11046 | B2061: WANDK | C2061: 45405 | D2061: 45433 | E2061: 45406 | F2061: 45415 | G2061: 35 | H2061: 18 | I2061: 18 | J2061: 0.05 | K2061: 71.64 | L2061: United Package
A2062: 11047 | B2062: EASTC | C2062: 45406 | D2062: 45434 | E2062: 45413 | F2062: 45421 | G2062: 1 | H2062: 18 | I2062: 25 | J2062: 0.25 | K2062: 46.62 | L2062: Federal Shipping
A2063: 11047 | B2063: EASTC | C2063: 45406 | D2063: 45434 | E2063: 45413 | F2063: 45421 | G2063: 5 | H2063: 21.35 | I2063: 30 | J2063: 0.25 | K2063: 46.62 | L2063: Federal Shipping
A2064: 11048 | B2064: BOTTM | C2064: 45406 | D2064: 45434 | E2064: 45412 | F2064: 45423 | G2064: 68 | H2064: 12.5 | I2064: 42 | J2064: 0 | K2064: 24.12 | L2064: Federal Shipping
A2065: 11049 | B2065: GOURL | C2065: 45406 | D2065: 45434 | E2065: 45416 | F2065: 45432 | G2065: 2 | H2065: 19 | I2065: 10 | J2065: 0.2 | K2065: 8.34 | L2065: Speedy Express
A2066: 11049 | B2066: GOURL | C2066: 45406 | D2066: 45434 | E2066: 45416 | F2066: 45432 | G2066: 12 | H2066: 38 | I2066: 4 | J2066: 0.2 | K2066: 8.34 | L2066: Speedy Express
A2067: 11050 | B2067: FOLKO | C2067: 45409 | D2067: 45437 | E2067: 45417 | F2067: 45427 | G2067: 76 | H2067: 18 | I2067: 50 | J2067: 0.1 | K2067: 59.41 | L2067: United Package
A2068: 11051 | B2068: LAMAI | C2068: 45409 | D2068: 45437 | G2068: 24 | H2068: 4.5 | I2068: 10 | J2068: 0.2 | K2068: 2.79 | L2068: Federal Shipping
A2069: 11052 | B2069: HANAR | C2069: 45409 | D2069: 45437 | E2069: 45413 | F2069: 45428 | G2069: 43 | H2069: 46 | I2069: 30 | J2069: 0.2 | K2069: 67.26 | L2069: Speedy Express
A2070: 11052 | B2070: HANAR | C2070: 45409 | D2070: 45437 | E2070: 45413 | F2070: 45428 | G2070: 61 | H2070: 28.5 | I2070: 10 | J2070: 0.2 | K2070: 67.26 | L2070: Speedy Express
A2071: 11053 | B2071: PICCO | C2071: 45409 | D2071: 45437 | E2071: 45411 | F2071: 45424 | G2071: 18 | H2071: 62.5 | I2071: 35 | J2071: 0.2 | K2071: 53.05 | L2071: United Package
A2072: 11053 | B2072: PICCO | C2072: 45409 | D2072: 45437 | E2072: 45411 | F2072: 45424 | G2072: 32 | H2072: 32 | I2072: 20 | J2072: 0 | K2072: 53.05 | L2072: United Package
A2073: 11053 | B2073: PICCO | C2073: 45409 | D2073: 45437 | E2073: 45411 | F2073: 45424 | G2073: 64 | H2073: 33.25 | I2073: 25 | J2073: 0.2 | K2073: 53.05 | L2073: United Package
A2074: 11054 | B2074: CACTU | C2074: 45410 | D2074: 45438 | G2074: 33 | H2074: 2.5 | I2074: 10 | J2074: 0 | K2074: 0.33 | L2074: Speedy Express
A2075: 11054 | B2075: CACTU | C2075: 45410 | D2075: 45438 | G2075: 67 | H2075: 14 | I2075: 20 | J2075: 0 | K2075: 0.33 | L2075: Speedy Express
A2076: 11055 | B2076: HILAA | C2076: 45410 | D2076: 45438 | E2076: 45417 | F2076: 45432 | G2076: 24 | H2076: 4.5 | I2076: 15 | J2076: 0 | K2076: 120.92 | L2076: United Package
A2077: 11055 | B2077: HILAA | C2077: 45410 | D2077: 45438 | E2077: 45417 | F2077: 45432 | G2077: 25 | H2077: 14 | I2077: 15 | J2077: 0 | K2077: 120.92 | L2077: United Package
A2078: 11055 | B2078: HILAA | C2078: 45410 | D2078: 45438 | E2078: 45417 | F2078: 45432 | G2078: 51 | H2078: 53 | I2078: 20 | J2078: 0 | K2078: 120.92 | L2078: United Package
A2079: 11055 | B2079: HILAA | C2079: 45410 | D2079: 45438 | E2079: 45417 | F2079: 45432 | G2079: 57 | H2079: 19.5 | I2079: 20 | J2079: 0 | K2079: 120.92 | L2079: United Package
A2080: 11056 | B2080: EASTC | C2080: 45410 | D2080: 45424 | E2080: 45413 | F2080: 45422 | G2080: 7 | H2080: 30 | I2080: 40 | J2080: 0 | K2080: 278.96 | L2080: United Package
A2081: 11056 | B2081: EASTC | C2081: 45410 | D2081: 45424 | E2081: 45413 | F2081: 45422 | G2081: 55 | H2081: 24 | I2081: 35 | J2081: 0 | K2081: 278.96 | L2081: United Package
A2082: 11056 | B2082: EASTC | C2082: 45410 | D2082: 45424 | E2082: 45413 | F2082: 45422 | G2082: 60 | H2082: 34 | I2082: 50 | J2082: 0 | K2082: 278.96 | L2082: United Package
A2083: 11057 | B2083: NORTS | C2083: 45411 | D2083: 45439 | E2083: 45413 | F2083: 45422 | G2083: 70 | H2083: 15 | I2083: 3 | J2083: 0 | K2083: 4.13 | L2083: Federal Shipping
A2084: 11058 | B2084: BLAUS | C2084: 45411 | D2084: 45439 | G2084: 21 | H2084: 10 | I2084: 3 | J2084: 0 | K2084: 31.14 | L2084: Federal Shipping
A2085: 11058 | B2085: BLAUS | C2085: 45411 | D2085: 45439 | G2085: 60 | H2085: 34 | I2085: 21 | J2085: 0 | K2085: 31.14 | L2085: Federal Shipping
A2086: 11058 | B2086: BLAUS | C2086: 45411 | D2086: 45439 | G2086: 61 | H2086: 28.5 | I2086: 4 | J2086: 0 | K2086: 31.14 | L2086: Federal Shipping
A2087: 11059 | B2087: RICAR | C2087: 45411 | D2087: 45453 | G2087: 13 | H2087: 6 | I2087: 30 | J2087: 0 | K2087: 85.8 | L2087: United Package
A2088: 11059 | B2088: RICAR | C2088: 45411 | D2088: 45453 | G2088: 17 | H2088: 39 | I2088: 12 | J2088: 0 | K2088: 85.8 | L2088: United Package
A2089: 11059 | B2089: RICAR | C2089: 45411 | D2089: 45453 | G2089: 60 | H2089: 34 | I2089: 35 | J2089: 0 | K2089: 85.8 | L2089: United Package
A2090: 11060 | B2090: FRANS | C2090: 45412 | D2090: 45440 | E2090: 45416 | F2090: 45427 | G2090: 60 | H2090: 34 | I2090: 4 | J2090: 0 | K2090: 10.98 | L2090: United Package
A2091: 11060 | B2091: FRANS | C2091: 45412 | D2091: 45440 | E2091: 45416 | F2091: 45427 | G2091: 77 | H2091: 13 | I2091: 10 | J2091: 0 | K2091: 10.98 | L2091: United Package
A2092: 11061 | B2092: GREAL | C2092: 45412 | D2092: 45454 | G2092: 60 | H2092: 34 | I2092: 15 | J2092: 0 | K2092: 14.01 | L2092: Federal Shipping
A2093: 11062 | B2093: REGGC | C2093: 45412 | D2093: 45440 | G2093: 53 | H2093: 32.8 | I2093: 10 | J2093: 0.2 | K2093: 29.93 | L2093: United Package
A2094: 11062 | B2094: REGGC | C2094: 45412 | D2094: 45440 | G2094: 70 | H2094: 15 | I2094: 12 | J2094: 0.2 | K2094: 29.93 | L2094: United Package
A2095: 11063 | B2095: HUNGO | C2095: 45412 | D2095: 45440 | E2095: 45418 | F2095: 45430 | G2095: 34 | H2095: 14 | I2095: 30 | J2095: 0 | K2095: 81.73 | L2095: United Package
A2096: 11063 | B2096: HUNGO | C2096: 45412 | D2096: 45440 | E2096: 45418 | F2096: 45430 | G2096: 40 | H2096: 18.4 | I2096: 40 | J2096: 0.1 | K2096: 81.73 | L2096: United Package
A2097: 11063 | B2097: HUNGO | C2097: 45412 | D2097: 45440 | E2097: 45418 | F2097: 45430 | G2097: 41 | H2097: 9.65 | I2097: 30 | J2097: 0.1 | K2097: 81.73 | L2097: United Package
A2098: 11064 | B2098: SAVEA | C2098: 45413 | D2098: 45441 | E2098: 45416 | F2098: 45427 | G2098: 17 | H2098: 39 | I2098: 77 | J2098: 0.1 | K2098: 30.09 | L2098: Speedy Express
A2099: 11064 | B2099: SAVEA | C2099: 45413 | D2099: 45441 | E2099: 45416 | F2099: 45427 | G2099: 41 | H2099: 9.65 | I2099: 12 | J2099: 0 | K2099: 30.09 | L2099: Speedy Express
A2100: 11064 | B2100: SAVEA | C2100: 45413 | D2100: 45441 | E2100: 45416 | F2100: 45427 | G2100: 53 | H2100: 32.8 | I2100: 25 | J2100: 0.1 | K2100: 30.09 | L2100: Speedy Express
...

Sheet 2 products
A1: productID | B1: productName | C1: quantityPerUnit | D1: unitsInStock | E1: unitsOnOrder | F1: reorderLevel | G1: discontinued | H1: purchasePrice_2022 | I1: purchasePrice_2023 | J1: purchasePrice_2024 | K1: productRating | L1: categoryName | M1: categoryDescription | N1: supplierName | O1: supplierCity | P1: supplierCountry
A2: 1 | B2: Chai | C2: 10 boxes x 20 bags | D2: 39 | E2: 0 | F2: 10 | G2: 0 | H2: 9.5742072 | I2: 12.158476 | J2: 12.177575 | K2: 4.5 | L2: Beverages | M2: Soft drinks coffees teas beers and ales | N2: Exotic Liquids | O2: London | P2: UK
A3: 2 | B3: Chang | C3: 24 - 12 oz bottles | D3: 17 | E3: 40 | F3: 25 | G3: 0 | H3: 9.7687469 | I3: 12.146269 | J3: 11.938437 | K3: 4.5 | L3: Beverages | M3: Soft drinks coffees teas beers and ales | N3: Exotic Liquids | O3: London | P3: UK
A4: 3 | B4: Aniseed Syrup | C4: 12 - 550 ml bottles | D4: 13 | E4: 70 | F4: 25 | G4: 0 | H4: 5.6218196 | I4: 6.3998026 | J4: 7.2059177 | K4: 5 | L4: Condiments | M4: Sweet and savory sauces relishes spreads and seasonings | N4: Exotic Liquids | O4: London | P4: UK
A5: 4 | B5: Chef Anton's Cajun Seasoning | C5: 48 - 6 oz jars | D5: 53 | E5: 0 | F5: 0 | G5: 0 | H5: 12.120073 | I5: 13.810471 | J5: 14.372802 | K5: 5 | L5: Condiments | M5: Sweet and savory sauces relishes spreads and seasonings | N5: New Orleans Cajun Delights | O5: New Orleans | P5: USA
A6: 5 | B6: Chef Anton's Gumbo Mix | C6: 36 boxes | D6: 0 | E6: 0 | F6: 0 | G6: 1 | H6: 10.905906 | I6: 14.652583 | J6: 13.963374 | K6: 4.5 | L6: Condiments | M6: Sweet and savory sauces relishes spreads and seasonings | N6: New Orleans Cajun Delights | O6: New Orleans | P6: USA
A7: 6 | B7: Grandma's Boysenberry Spread | C7: 12 - 8 oz jars | D7: 120 | E7: 0 | F7: 25 | G7: 0 | H7: 13.640303 | I7: 17.851104 | J7: 17.241659 | K7: 5 | L7: Condiments | M7: Sweet and savory sauces relishes spreads and seasonings | N7: Grandma Kelly's Homestead | O7: Ann Arbor | P7: USA
A8: 8 | B8: Northwoods Cranberry Sauce | C8: 12 - 12 oz jars | D8: 6 | E8: 0 | F8: 0 | G8: 0 | H8: 19.171769 | I8: 26.106205 | J8: 27.417709 | K8: 5 | L8: Condiments | M8: Sweet and savory sauces relishes spreads and seasonings | N8: Grandma Kelly's Homestead | O8: Ann Arbor | P8: USA
A9: 9 | B9: Mishi Kobe Niku | C9: 18 - 500 g pkgs. | D9: 29 | E9: 0 | F9: 0 | G9: 1 | I9: 59.95981 | J9: 72.668633 | K9: 4 | L9: Meat/Poultry | M9: Prepared meats | N9: Tokyo Traders | O9: Tokyo | P9: Japan
A10: 7 | B10: Uncle Bob's Organic Dried Pears | C10: 12 - 1 lb pkgs. | D10: 15 | E10: 0 | F10: 10 | G10: 0 | H10: 16.429974 | I10: 21.392446 | J10: 23.522222 | K10: 4.5 | L10: Produce | M10: Dried fruit and bean curd | N10: Grandma Kelly's Homestead | O10: Ann Arbor | P10: USA
A11: 10 | B11: Ikura | C11: 12 - 200 ml jars | D11: 31 | E11: 0 | F11: 0 | G11: 0 | H11: 16.076307 | I11: 20.727219 | J11: 20.903946 | K11: 3.5 | L11: Seafood | M11: Seaweed and fish | N11: Tokyo Traders | O11: Tokyo | P11: Japan
A12: 11 | B12: Queso Cabrales | C12: 1 kg pkg. | D12: 22 | E12: 30 | F12: 30 | G12: 0 | H12: 10.582311 | I12: 12.901881 | J12: 13.868363 | K12: 5 | L12: Dairy Products | M12: Cheeses | N12: Cooperativa de Quesos 'Las Cabras' | O12: Oviedo | P12: Spain
A13: 12 | B13: Queso Manchego La Pastora | C13: 10 - 500 g pkgs. | D13: 86 | E13: 0 | F13: 0 | G13: 0 | H13: 20.012451 | I13: 23.792166 | J13: 25.02511 | K13: 5 | L13: Dairy Products | M13: Cheeses | N13: Cooperativa de Quesos 'Las Cabras' | O13: Oviedo | P13: Spain
A14: 13 | B14: Konbu | C14: 2 kg box | D14: 24 | E14: 0 | F14: 5 | G14: 0 | H14: 3.2367274 | I14: 3.8657749 | J14: 3.966387 | K14: 4 | L14: Seafood | M14: Seaweed and fish | N14: Mayumi's | O14: Osaka | P14: Japan
A15: 14 | B15: Tofu | C15: 40 - 100 g pkgs. | D15: 35 | E15: 0 | F15: 0 | G15: 0 | H15: 13.952541 | I15: 15.380554 | J15: 15.347726 | K15: 4.5 | L15: Produce | M15: Dried fruit and bean curd | N15: Mayumi's | O15: Osaka | P15: Japan
A16: 15 | B16: Genen Shouyu | C16: 24 - 250 ml bottles | D16: 39 | E16: 0 | F16: 5 | G16: 0 | H16: 8.7559169 | I16: 10.783947 | J16: 11 | K16: 4.5 | L16: Condiments | M16: Sweet and savory sauces relishes spreads and seasonings | N16: Mayumi's | O16: Osaka | P16: Japan
A17: 16 | B17: Pavlova | C17: 32 - 500 g boxes | D17: 29 | E17: 0 | F17: 10 | G17: 0 | H17: 9.8065801 | I17: 11.985048 | J17: 12.68284 | K17: 4 | L17: Confections | M17: Desserts candies and sweet breads | N17: Pavlova Ltd. | O17: Melbourne | P17: Australia
A18: 17 | B18: Alice Mutton | C18: 20 - 1 kg tins | D18: 0 | E18: 0 | F18: 0 | G18: 1 | H18: 21.253774 | I18: 24.831305 | J18: 28.519163 | K18: 5 | L18: Meat/Poultry | M18: Prepared meats | N18: Pavlova Ltd. | O18: Melbourne | P18: Australia
A19: 18 | B19: Carnarvon Tigers | C19: 16 kg pkg. | D19: 42 | E19: 0 | F19: 0 | G19: 0 | H19: 32.463798 | I19: 39.519667 | J19: 41.27005 | K19: 4.5 | L19: Seafood | M19: Seaweed and fish | N19: Pavlova Ltd. | O19: Melbourne | P19: Australia
A20: 19 | B20: Teatime Chocolate Biscuits | C20: 10 boxes x 12 pieces | D20: 25 | E20: 0 | F20: 5 | G20: 0 | H20: 5.5812009 | I20: 5.9018837 | J20: 6.769657 | K20: 4 | L20: Confections | M20: Desserts candies and sweet breads | N20: Specialty Biscuits Ltd. | O20: Manchester | P20: UK
A21: 20 | B21: Sir Rodney's Marmalade | C21: 30 gift boxes | D21: 40 | E21: 0 | F21: 0 | G21: 0 | H21: 45.942474 | I21: 57.293421 | J21: 62.825376 | K21: 4.5 | L21: Confections | M21: Desserts candies and sweet breads | N21: Specialty Biscuits Ltd. | O21: Manchester | P21: UK
... A48: 47 | B48: Zaanse koeken | C48: 10 - 4 oz boxes | D48: 36 | E48: 0 | F48: 0 | G48: 0 | H48: 4.7389004 | I48: 6.5770883 | J48: 6.6351308 | K48: 3.5 | L48: Confections | M48: Desserts candies and sweet breads | N48: Zaanse Snoepfabriek | O48: Zaandam | P48: Netherlands
A49: 48 | B49: Chocolade | C49: 10 pkgs. | D49: 15 | E49: 70 | F49: 25 | G49: 0 | I49: 8.0796717 | J49: 8.207116 | K49: 4 | L49: Confections | M49: Desserts candies and sweet breads | N49: Zaanse Snoepfabriek | O49: Zaandam | P49: Netherlands
A50: 49 | B50: Maxilaku | C50: 24 - 50 g pkgs. | D50: 10 | E50: 60 | F50: 15 | G50: 0 | H50: 12.566636 | I50: 13.041123 | J50: 15.074599 | K50: 4.5 | L50: Confections | M50: Desserts candies and sweet breads | N50: Karkki Oy | O50: Lappeenranta | P50: Finland
A51: 50 | B51: Valkoinen suklaa | C51: 12 - 100 g bars | D51: 65 | E51: 0 | F51: 30 | G51: 0 | H51: 9.6822786 | I51: 11.160214 | J51: 12.642922 | K51: 4.5 | L51: Confections | M51: Desserts candies and sweet breads | N51: Karkki Oy | O51: Lappeenranta | P51: Finland
A52: 51 | B52: Manjimup Dried Apples | C52: 50 - 300 g pkgs. | D52: 20 | E52: 0 | F52: 10 | G52: 0 | H52: 28.875322 | I52: 36.88798 | J52: 39.514165 | K52: 4.5 | L52: Produce | M52: Dried fruit and bean curd | N52: G'day Mate | O52: Sydney | P52: Australia
A53: 52 | B53: Filo Mix | C53: 16 - 2 kg boxes | D53: 38 | E53: 0 | F53: 25 | G53: 0 | H53: 3.8535 | I53: 5.0017067 | J53: 5.2222234 | K53: 1.5 | L53: Grains/Cereals | M53: Breads crackers pasta and cereal | N53: G'day Mate | O53: Sydney | P53: Australia
A54: 53 | B54: Perth Pasties | C54: 48 pieces | D54: 0 | E54: 0 | F54: 0 | G54: 1 | H54: 18.33322 | I54: 21.814916 | J54: 22.926371 | K54: 4 | L54: Meat/Poultry | M54: Prepared meats | N54: G'day Mate | O54: Sydney | P54: Australia
A55: 54 | B55: Tourtière | C55: 16 pies | D55: 21 | E55: 0 | F55: 10 | G55: 0 | H55: 4.3098489 | I55: 4.9244478 | J55: 4.8847165 | K55: 5 | L55: Meat/Poultry | M55: Prepared meats | N55: Ma Maison | O55: Montréal | P55: Canada
A56: 55 | B56: Pâté chinois | C56: 24 boxes x 2 pies | D56: 115 | E56: 0 | F56: 20 | G56: 0 | H56: 12.974961 | I56: 14.923988 | J56: 16.959985 | K56: 4.5 | L56: Meat/Poultry | M56: Prepared meats | N56: Ma Maison | O56: Montréal | P56: Canada
A57: 56 | B57: Gnocchi di nonna Alice | C57: 24 - 250 g pkgs. | D57: 21 | E57: 10 | F57: 30 | G57: 0 | H57: 21.504006 | I57: 24.283424 | J57: 27.539159 | K57: 5 | L57: Grains/Cereals | M57: Breads crackers pasta and cereal | N57: Pasta Buttini s.r.l. | O57: Salerno | P57: Italy
A58: 57 | B58: Ravioli Angelo | C58: 24 - 250 g pkgs. | D58: 36 | E58: 0 | F58: 20 | G58: 0 | H58: 11.229508 | I58: 13.018709 | J58: 14.295348 | K58: 5 | L58: Grains/Cereals | M58: Breads crackers pasta and cereal | N58: Pasta Buttini s.r.l. | O58: Salerno | P58: Italy
A59: 58 | B59: Escargots de Bourgogne | C59: 24 pieces | D59: 62 | E59: 0 | F59: 20 | G59: 0 | H59: 6.3889393 | I59: 8.2084464 | J59: 8.6831022 | K59: 4.5 | L59: Seafood | M59: Seaweed and fish | N59: Escargots Nouveaux | O59: Montceau | P59: France
A60: 59 | B60: Raclette Courdavault | C60: 5 kg pkg. | D60: 79 | E60: 0 | F60: 0 | G60: 0 | H60: 29.20352 | I60: 35.204726 | J60: 36.748637 | K60: 4 | L60: Dairy Products | M60: Cheeses | N60: Gai pâturage | O60: Annecy | P60: France
A61: 60 | B61: Camembert Pierrot | C61: 15 - 300 g rounds | D61: 19 | E61: 0 | F61: 0 | G61: 0 | H61: 17.665635 | I61: 22.770983 | J61: 22.490912 | K61: 5 | L61: Dairy Products | M61: Cheeses | N61: Gai pâturage | O61: Annecy | P61: France
A62: 61 | B62: Sirop d'érable | C62: 24 - 500 ml bottles | D62: 113 | E62: 0 | F62: 25 | G62: 0 | I62: 17.199454 | J62: 18.744874 | K62: 4.5 | L62: Condiments | M62: Sweet and savory sauces relishes spreads and seasonings | N62: Forêts d'érables | O62: Ste-Hyacinthe | P62: Canada
A63: 62 | B63: Tarte au sucre | C63: 48 pies | D63: 17 | E63: 0 | F63: 0 | G63: 0 | H63: 29.359633 | I63: 35.347928 | J63: 34.88145 | K63: 5 | L63: Confections | M63: Desserts candies and sweet breads | N63: Forêts d'érables | O63: Ste-Hyacinthe | P63: Canada
A64: 63 | B64: Vegie-spread | C64: 15 - 625 g jars | D64: 24 | E64: 0 | F64: 5 | G64: 0 | H64: 23.813723 | I64: 27.722257 | J64: 32.591986 | K64: 5 | L64: Condiments | M64: Sweet and savory sauces relishes spreads and seasonings | N64: Pavlova Ltd. | O64: Melbourne | P64: Australia
A65: 64 | B65: Lukas' leckere Sauerteigweggla | C65: 20 bags x 4 pieces | D65: 22 | E65: 80 | F65: 30 | G65: 0 | H65: 19.369823 | I65: 21.885727 | J65: 22.724343 | K65: 5 | L65: Grains/Cereals | M65: Breads crackers pasta and cereal | N65: Plutzer Lebensmittelgroßmärkte AG | O65: Frankfurt | P65: Germany
A66: 65 | B66: Louisiana Fiery Hot Pepper Sauce | C66: 32 - 8 oz bottles | D66: 76 | E66: 0 | F66: 0 | G66: 0 | H66: 11.174102 | I66: 13.211222 | J66: 14.507382 | K66: 5 | L66: Condiments | M66: Sweet and savory sauces relishes spreads and seasonings | N66: New Orleans Cajun Delights | O66: New Orleans | P66: USA
A67: 66 | B67: Louisiana Hot Spiced Okra | C67: 24 - 8 oz jars | D67: 4 | E67: 100 | F67: 20 | G67: 0 | H67: 9.7173428 | I67: 10.173131 | J67: 11.667251 | K67: 4.5 | L67: Condiments | M67: Sweet and savory sauces relishes spreads and seasonings | N67: New Orleans Cajun Delights | O67: New Orleans | P67: USA
A68: 67 | B68: Laughing Lumberjack Lager | C68: 24 - 12 oz bottles | D68: 52 | E68: 0 | F68: 10 | G68: 0 | H68: 6.3335786 | I68: 10.352745 | J68: 9.4431928 | K68: 4 | L68: Beverages | M68: Soft drinks coffees teas beers and ales | N68: Bigfoot Breweries | O68: Bend | P68: USA
A69: 68 | B69: Scottish Longbreads | C69: 10 boxes x 8 pieces | D69: 6 | E69: 10 | F69: 15 | G69: 0 | H69: 7.3166565 | I69: 8.5000004 | J69: 9.5550317 | K69: 4.5 | L69: Confections | M69: Desserts candies and sweet breads | N69: Specialty Biscuits Ltd. | O69: Manchester | P69: UK
A70: 69 | B70: Gudbrandsdalsost | C70: 10 kg pkg. | D70: 26 | E70: 0 | F70: 15 | G70: 0 | H70: 20.712162 | I70: 21.824286 | J70: 24.682921 | K70: 4.5 | L70: Dairy Products | M70: Cheeses | N70: Norske Meierier | O70: Sandvika | P70: Norway
A71: 70 | B71: Outback Lager | C71: 24 - 355 ml bottles | D71: 15 | E71: 10 | F71: 30 | G71: 0 | H71: 8.0375209 | I71: 9.7930941 | J71: 10.032808 | K71: 4.5 | L71: Beverages | M71: Soft drinks coffees teas beers and ales | N71: Pavlova Ltd. | O71: Melbourne | P71: Australia
A72: 71 | B72: Flotemysost | C72: 10 - 500 g pkgs. | D72: 26 | E72: 0 | F72: 0 | G72: 0 | H72: 12.00719 | I72: 13.400366 | J72: 14.209776 | K72: 5 | L72: Dairy Products | M72: Cheeses | N72: Norske Meierier | O72: Sandvika | P72: Norway
A73: 72 | B73: Mozzarella di Giovanni | C73: 24 - 200 g pkgs. | D73: 14 | E73: 0 | F73: 0 | G73: 0 | H73: 19.208293 | I73: 23.519338 | J73: 24.350579 | K73: 5 | L73: Dairy Products | M73: Cheeses | N73: Formaggi Fortini s.r.l. | O73: Ravenna | P73: Italy
A74: 73 | B74: Röd Kaviar | C74: 24 - 150 g jars | D74: 101 | E74: 0 | F74: 5 | G74: 0 | H74: 8.4198187 | I74: 9.6929994 | J74: 10.380178 | K74: 4 | L74: Seafood | M74: Seaweed and fish | N74: Svensk Sjöföda AB | O74: Stockholm | P74: Sweden
... A78: 77 | B78: Original Frankfurter grüne Soße | C78: 12 boxes | D78: 32 | E78: 0 | F78: 15 | G78: 0 | H78: 7.4302728 | I78: 7.5390565 | J78: 9.2990252 | K78: 4.5 | L78: Condiments | M78: Sweet and savory sauces relishes spreads and seasonings | N78: Plutzer Lebensmittelgroßmärkte AG | O78: Frankfurt | P78: Germany

Sheet 3 customers
A1: customerID | B1: companyName | C1: contactName | D1: contactTitle | E1: address | F1: city | G1: region | H1: postalCode | I1: country | J1: phone
A2: ALFKI | B2: Alfreds Futterkiste | C2: Maria Anders | D2: Sales Representative | E2: Obere Str. 57 | F2: Berlin | G2: NULL | H2: 12209 | I2: Germany | J2: 030-0074321
A3: ANATR | B3: Ana Trujillo Emparedados y helados | C3: Ana Trujillo | D3: Owner | E3: Avda. de la Constitución 2222 | F3: México D.F. | G3: NULL | H3: 05021 | I3: Mexico | J3: (5) 555-4729
A4: ANTON | B4: Antonio Moreno Taquería | C4: Antonio Moreno | D4: Owner | E4: Mataderos 2312 | F4: México D.F. | G4: NULL | H4: 05023 | I4: Mexico | J4: (5) 555-3932
A5: AROUT | B5: Around the Horn | C5: Thomas Hardy | D5: Sales Representative | E5: 120 Hanover Sq. | F5: London | G5: NULL | H5: WA1 1DP | I5: UK | J5: (171) 555-7788
A6: BERGS | B6: Berglunds snabbköp | C6: Christina Berglund | D6: Order Administrator | E6: Berguvsvägen 8 | F6: Luleå | G6: NULL | H6: S-958 22 | I6: Sweden | J6: 0921-12 34 65
A7: BLAUS | B7: Blauer See Delikatessen | C7: Hanna Moos | D7: Sales Representative | E7: Forsterstr. 57 | F7: Mannheim | G7: NULL | H7: 68306 | I7: Germany | J7: 0621-08460
A8: BLONP | B8: Blondesddsl père et fils | C8: Frédérique Citeaux | D8: Marketing Manager | E8: 24 place Kléber | F8: Strasbourg | G8: NULL | H8: 67000 | I8: France | J8: 88.60.15.31
A9: BOLID | B9: Bólido Comidas preparadas | C9: Martín Sommer | D9: Owner | E9: 67C Araquil | F9: Madrid | G9: NULL | H9: 28023 | I9: Spain | J9: (91) 555 22 82
A10: BONAP | B10: Bon app' | C10: Laurence Lebihan | D10: Owner | E10: 12 rue des Bouchers | F10: Marseille | G10: NULL | H10: 13008 | I10: France | J10: 91.24.45.40
A11: BOTTM | B11: Bottom-Dollar Markets | C11: Elizabeth Lincoln | D11: Accounting Manager | E11: 23 Tsawassen Blvd. | F11: Tsawassen | G11: BC | H11: T2F 8M4 | I11: Canada | J11: (604) 555-4729
A12: BSBEV | B12: B's Beverages | C12: Victoria Ashworth | D12: Sales Representative | E12: Fauntleroy Circus | F12: London | G12: NULL | H12: EC2 5NT | I12: UK | J12: (171) 555-1212
... A92: WOLZA | B92: Wolski Zajazd | C92: Zbyszek Piestrzeniewicz | D92: Owner | E92: ul. Filtrowa 68 | F92: Warszawa | G92: NULL | H92: 01-012 | I92: Poland | J92: (26) 642-7012

Sheet analysis-dynamic
A1: orderID | B1: customerID | C1: customerName | D1: orderDate | E1: orderCount | F1: sinceLastOrder | G1: customerStatus | H1: productID | I1: productName | J1: productCategory | K1: productStatus | L1: productCost | M1: orderPrice | N1: productMarkup | O1: orderQuantity | P1: discountApllied | Q1: orderTotal | R1: revenue | S1: profit | T1: profitMargin
A2: 10248 | B2: VINET | C2: =VLOOKUP(dynamic[customerID],customers[],2,FALSE) -> Vins et alcools Chevalier | D2: 44746 | E2: =IFERROR(__xludf.DUMMYFUNCTION("COUNTUNIQUEIFS($A$2:$A2,$B$2:$B2,B2)"),1.0) -> 1 | F2: =IF(E2=1, 0, D2 - INDEX($D$2:$D2,MATCH(1, ($B$2:$B2=B2)*($E$2:$E2=E2-1), 0))) -> 0 | G2: =IF(MINIFS(dynamic[orderDate], dynamic[customerID], B2) >= DATE(2024,4,30)-120, "New", IF(MAXIFS(dynamic[orderCount], dynamic[customerID], B2)<=2, IF((DATE(2024,4,30) - MAXIFS(dynamic[orderDate], dynamic[customerID], B2)) > 180, "Non-Returning", "Dormant"), IF(AND(MAX(dynamic[sinceLastOrder]) > 365, (DATE(2024,4,30) - MAXIFS(dynamic[orderDate], dynamic[customerID], B2)) > 180), "Dormant", "Regular"))) -> Regular | H2: 11 | I2: =VLOOKUP(dynamic[productID],products[],2,FALSE) -> Queso Cabrales | J2: =VLOOKUP(dynamic[productID],products[],12,FALSE) -> Dairy Products | K2: =IF(VLOOKUP(dynamic[productID],products[],7,FALSE)=1,"Discontinued","Current") -> Current | L2: =VLOOKUP(dynamic[productID],products[],IF(YEAR(dynamic[orderDate])=2022,8,IF(YEAR(dynamic[orderDate])=2023,9,IF(YEAR(dynamic[orderDate])=2024,10,NA))),FALSE) -> 10.582311 | M2: 14 | N2: =(dynamic[orderPrice]-dynamic[productCost])/dynamic[productCost] -> 0.32296245 | O2: 12 | P2: 0 | Q2: =dynamic[orderPrice]*dynamic[orderQuantity] -> 168 | R2: =dynamic[orderTotal]*(1-dynamic[discountApllied]) -> 168 | S2: =dynamic[revenue]-(dynamic[productCost]*dynamic[orderQuantity]) -> 41.012268 | T2: =IFERROR(dynamic[profit]/dynamic[revenue], 0) -> 0.24412064
A3: 10248 | B3: VINET | C3: =VLOOKUP(dynamic[customerID],customers[],2,FALSE) -> Vins et alcools Chevalier | D3: 44746 | E3: =IFERROR(__xludf.DUMMYFUNCTION("COUNTUNIQUEIFS($A$2:$A3,$B$2:$B3,B3)"),1.0) -> 1 | F3: =IF(E3=1, 0, D3 - INDEX($D$2:$D3,MATCH(1, ($B$2:$B3=B3)*($E$2:$E3=E3-1), 0))) -> 0 | G3: =IF(MINIFS(dynamic[orderDate], dynamic[customerID], B3) >= DATE(2024,4,30)-120, "New", IF(MAXIFS(dynamic[orderCount], dynamic[customerID], B3)<=2, IF((DATE(2024,4,30) - MAXIFS(dynamic[orderDate], dynamic[customerID], B3)) > 180, "Non-Returning", "Dormant"), IF(AND(MAX(dynamic[sinceLastOrder]) > 365, (DATE(2024,4,30) - MAXIFS(dynamic[orderDate], dynamic[customerID], B3)) > 180), "Dormant", "Regular"))) -> Regular | H3: 42 | I3: =VLOOKUP(dynamic[productID],products[],2,FALSE) -> Singaporean Hokkien Fried Mee | J3: =VLOOKUP(dynamic[productID],products[],12,FALSE) -> Grains/Cereals | K3: =IF(VLOOKUP(dynamic[productID],products[],7,FALSE)=1,"Discontinued","Current") -> Discontinued | L3: =VLOOKUP(dynamic[productID],products[],IF(YEAR(dynamic[orderDate])=2022,8,IF(YEAR(dynamic[orderDate])=2023,9,IF(YEAR(dynamic[orderDate])=2024,10,NA))),FALSE) -> 7.8184259 | M3: 9.8 | N3: =(dynamic[orderPrice]-dynamic[productCost])/dynamic[productCost] -> 0.25344924 | O3: 10 | P3: 0 | Q3: =dynamic[orderPrice]*dynamic[orderQuantity] -> 98 | R3: =dynamic[orderTotal]*(1-dynamic[discountApllied]) -> 98 | S3: =dynamic[revenue]-(dynamic[productCost]*dynamic[orderQuantity]) -> 19.815741 | T3: =IFERROR(dynamic[profit]/dynamic[revenue], 0) -> 0.20220144
A4: 10248 | B4: VINET | C4: =VLOOKUP(dynamic[customerID],customers[],2,FALSE) -> Vins et alcools Chevalier | D4: 44746 | E4: =IFERROR(__xludf.DUMMYFUNCTION("COUNTUNIQUEIFS($A$2:$A4,$B$2:$B4,B4)"),1.0) -> 1 | F4: =IF(E4=1, 0, D4 - INDEX($D$2:$D4,MATCH(1, ($B$2:$B4=B4)*($E$2:$E4=E4-1), 0))) -> 0 | G4: =IF(MINIFS(dynamic[orderDate], dynamic[customerID], B4) >= DATE(2024,4,30)-120, "New", IF(MAXIFS(dynamic[orderCount], dynamic[customerID], B4)<=2, IF((DATE(2024,4,30) - MAXIFS(dynamic[orderDate], dynamic[customerID], B4)) > 180, "Non-Returning", "Dormant"), IF(AND(MAX(dynamic[sinceLastOrder]) > 365, (DATE(2024,4,30) - MAXIFS(dynamic[orderDate], dynamic[customerID], B4)) > 180), "Dormant", "Regular"))) -> Regular | H4: 72 | I4: =VLOOKUP(dynamic[productID],products[],2,FALSE) -> Mozzarella di Giovanni | J4: =VLOOKUP(dynamic[productID],products[],12,FALSE) -> Dairy Products | K4: =IF(VLOOKUP(dynamic[productID],products[],7,FALSE)=1,"Discontinued","Current") -> Current | L4: =VLOOKUP(dynamic[productID],products[],IF(YEAR(dynamic[orderDate])=2022,8,IF(YEAR(dynamic[orderDate])=2023,9,IF(YEAR(dynamic[orderDate])=2024,10,NA))),FALSE) -> 19.208293 | M4: 34.8 | N4: =(dynamic[orderPrice]-dynamic[productCost])/dynamic[productCost] -> 0.81171744 | O4: 5 | P4: 0 | Q4: =dynamic[orderPrice]*dynamic[orderQuantity] -> 174 | R4: =dynamic[orderTotal]*(1-dynamic[discountApllied]) -> 174 | S4: =dynamic[revenue]-(dynamic[productCost]*dynamic[orderQuantity]) -> 77.958533 | T4: =IFERROR(dynamic[profit]/dynamic[revenue], 0) -> 0.44803755
A5: 10249 | B5: TOMSP | C5: =VLOOKUP(dynamic[customerID],customers[],2,FALSE) -> Toms Spezialitäten | D5: 44747 | E5: =IFERROR(__xludf.DUMMYFUNCTION("COUNTUNIQUEIFS($A$2:$A5,$B$2:$B5,B5)"),1.0) -> 1 | F5: =IF(E5=1, 0, D5 - INDEX($D$2:$D5,MATCH(1, ($B$2:$B5=B5)*($E$2:$E5=E5-1), 0))) -> 0 | G5: =IF(MINIFS(dynamic[orderDate], dynamic[customerID], B5) >= DATE(2024,4,30)-120, "New", IF(MAXIFS(dynamic[orderCount], dynamic[customerID], B5)<=2, IF((DATE(2024,4,30) - MAXIFS(dynamic[orderDate], dynamic[customerID], B5)) > 180, "Non-Returning", "Dormant"), IF(AND(MAX(dynamic[sinceLastOrder]) > 365, (DATE(2024,4,30) - MAXIFS(dynamic[orderDate], dynamic[customerID], B5)) > 180), "Dormant", "Regular"))) -> Regular | H5: 14 | I5: =VLOOKUP(dynamic[productID],products[],2,FALSE) -> Tofu | J5: =VLOOKUP(dynamic[productID],products[],12,FALSE) -> Produce | K5: =IF(VLOOKUP(dynamic[productID],products[],7,FALSE)=1,"Discontinued","Current") -> Current | L5: =VLOOKUP(dynamic[productID],products[],IF(YEAR(dynamic[orderDate])=2022,8,IF(YEAR(dynamic[orderDate])=2023,9,IF(YEAR(dynamic[orderDate])=2024,10,NA))),FALSE) -> 13.952541 | M5: 18.6 | N5: =(dynamic[orderPrice]-dynamic[productCost])/dynamic[productCost] -> 0.33309053 | O5: 9 | P5: 0 | Q5: =dynamic[orderPrice]*dynamic[orderQuantity] -> 167.4 | R5: =dynamic[orderTotal]*(1-dynamic[discountApllied]) -> 167.4 | S5: =dynamic[revenue]-(dynamic[productCost]*dynamic[orderQuantity]) -> 41.827133 | T5: =IFERROR(dynamic[profit]/dynamic[revenue], 0) -> 0.2498634
A6: 10249 | B6: TOMSP | C6: =VLOOKUP(dynamic[customerID],customers[],2,FALSE) -> Toms Spezialitäten | D6: 44747 | E6: =IFERROR(__xludf.DUMMYFUNCTION("COUNTUNIQUEIFS($A$2:$A6,$B$2:$B6,B6)"),1.0) -> 1 | F6: =IF(E6=1, 0, D6 - INDEX($D$2:$D6,MATCH(1, ($B$2:$B6=B6)*($E$2:$E6=E6-1), 0))) -> 0 | G6: =IF(MINIFS(dynamic[orderDate], dynamic[customerID], B6) >= DATE(2024,4,30)-120, "New", IF(MAXIFS(dynamic[orderCount], dynamic[customerID], B6)<=2, IF((DATE(2024,4,30) - MAXIFS(dynamic[orderDate], dynamic[customerID], B6)) > 180, "Non-Returning", "Dormant"), IF(AND(MAX(dynamic[sinceLastOrder]) > 365, (DATE(2024,4,30) - MAXIFS(dynamic[orderDate], dynamic[customerID], B6)) > 180), "Dormant", "Regular"))) -> Regular | H6: 51 | I6: =VLOOKUP(dynamic[productID],products[],2,FALSE) -> Manjimup Dried Apples | J6: =VLOOKUP(dynamic[productID],products[],12,FALSE) -> Produce | K6: =IF(VLOOKUP(dynamic[productID],products[],7,FALSE)=1,"Discontinued","Current") -> Current | L6: =VLOOKUP(dynamic[productID],products[],IF(YEAR(dynamic[orderDate])=2022,8,IF(YEAR(dynamic[orderDate])=2023,9,IF(YEAR(dynamic[orderDate])=2024,10,NA))),FALSE) -> 28.875322 | M6: 42.4 | N6: =(dynamic[orderPrice]-dynamic[productCost])/dynamic[productCost] -> 0.46838192 | O6: 40 | P6: 0 | Q6: =dynamic[orderPrice]*dynamic[orderQuantity] -> 1696 | R6: =dynamic[orderTotal]*(1-dynamic[discountApllied]) -> 1696 | S6: =dynamic[revenue]-(dynamic[productCost]*dynamic[orderQuantity]) -> 540.98714 | T6: =IFERROR(dynamic[profit]/dynamic[revenue], 0) -> 0.31897827
A7: 10250 | B7: HANAR | C7: =VLOOKUP(dynamic[customerID],customers[],2,FALSE) -> Hanari Carnes | D7: 44750 | E7: =IFERROR(__xludf.DUMMYFUNCTION("COUNTUNIQUEIFS($A$2:$A7,$B$2:$B7,B7)"),1.0) -> 1 | F7: =IF(E7=1, 0, D7 - INDEX($D$2:$D7,MATCH(1, ($B$2:$B7=B7)*($E$2:$E7=E7-1), 0))) -> 0 | G7: =IF(MINIFS(dynamic[orderDate], dynamic[customerID], B7) >= DATE(2024,4,30)-120, "New", IF(MAXIFS(dynamic[orderCount], dynamic[customerID], B7)<=2, IF((DATE(2024,4,30) - MAXIFS(dynamic[orderDate], dynamic[customerID], B7)) > 180, "Non-Returning", "Dormant"), IF(AND(MAX(dynamic[sinceLastOrder]) > 365, (DATE(2024,4,30) - MAXIFS(dynamic[orderDate], dynamic[customerID], B7)) > 180), "Dormant", "Regular"))) -> Regular | H7: 41 | I7: =VLOOKUP(dynamic[productID],products[],2,FALSE) -> Jack's New England Clam Chowder | J7: =VLOOKUP(dynamic[productID],products[],12,FALSE) -> Seafood | K7: =IF(VLOOKUP(dynamic[productID],products[],7,FALSE)=1,"Discontinued","Current") -> Current | L7: =VLOOKUP(dynamic[productID],products[],IF(YEAR(dynamic[orderDate])=2022,8,IF(YEAR(dynamic[orderDate])=2023,9,IF(YEAR(dynamic[orderDate])=2024,10,NA))),FALSE) -> 5.1701987 | M7: 7.7 | N7: =(dynamic[orderPrice]-dynamic[productCost])/dynamic[productCost] -> 0.48930445 | O7: 10 | P7: 0 | Q7: =dynamic[orderPrice]*dynamic[orderQuantity] -> 77 | R7: =dynamic[orderTotal]*(1-dynamic[discountApllied]) -> 77 | S7: =dynamic[revenue]-(dynamic[productCost]*dynamic[orderQuantity]) -> 25.298013 | T7: =IFERROR(dynamic[profit]/dynamic[revenue], 0) -> 0.32854562
A8: 10250 | B8: HANAR | C8: =VLOOKUP(dynamic[customerID],customers[],2,FALSE) -> Hanari Carnes | D8: 44750 | E8: =IFERROR(__xludf.DUMMYFUNCTION("COUNTUNIQUEIFS($A$2:$A8,$B$2:$B8,B8)"),1.0) -> 1 | F8: =IF(E8=1, 0, D8 - INDEX($D$2:$D8,MATCH(1, ($B$2:$B8=B8)*($E$2:$E8=E8-1), 0))) -> 0 | G8: =IF(MINIFS(dynamic[orderDate], dynamic[customerID], B8) >= DATE(2024,4,30)-120, "New", IF(MAXIFS(dynamic[orderCount], dynamic[customerID], B8)<=2, IF((DATE(2024,4,30) - MAXIFS(dynamic[orderDate], dynamic[customerID], B8)) > 180, "Non-Returning", "Dormant"), IF(AND(MAX(dynamic[sinceLastOrder]) > 365, (DATE(2024,4,30) - MAXIFS(dynamic[orderDate], dynamic[customerID], B8)) > 180), "Dormant", "Regular"))) -> Regular | H8: 51 | I8: =VLOOKUP(dynamic[productID],products[],2,FALSE) -> Manjimup Dried Apples | J8: =VLOOKUP(dynamic[productID],products[],12,FALSE) -> Produce | K8: =IF(VLOOKUP(dynamic[productID],products[],7,FALSE)=1,"Discontinued","Current") -> Current | L8: =VLOOKUP(dynamic[productID],products[],IF(YEAR(dynamic[orderDate])=2022,8,IF(YEAR(dynamic[orderDate])=2023,9,IF(YEAR(dynamic[orderDate])=2024,10,NA))),FALSE) -> 28.875322 | M8: 42.4 | N8: =(dynamic[orderPrice]-dynamic[productCost])/dynamic[productCost] -> 0.46838192 | O8: 35 | P8: 0.15 | Q8: =dynamic[orderPrice]*dynamic[orderQuantity] -> 1484 | R8: =dynamic[orderTotal]*(1-dynamic[discountApllied]) -> 1261.4 | S8: =dynamic[revenue]-(dynamic[productCost]*dynamic[orderQuantity]) -> 250.76375 | T8: =IFERROR(dynamic[profit]/dynamic[revenue], 0) -> 0.19879796
A9: 10250 | B9: HANAR | C9: =VLOOKUP(dynamic[customerID],customers[],2,FALSE) -> Hanari Carnes | D9: 44750 | E9: =IFERROR(__xludf.DUMMYFUNCTION("COUNTUNIQUEIFS($A$2:$A9,$B$2:$B9,B9)"),1.0) -> 1 | F9: =IF(E9=1, 0, D9 - INDEX($D$2:$D9,MATCH(1, ($B$2:$B9=B9)*($E$2:$E9=E9-1), 0))) -> 0 | G9: =IF(MINIFS(dynamic[orderDate], dynamic[customerID], B9) >= DATE(2024,4,30)-120, "New", IF(MAXIFS(dynamic[orderCount], dynamic[customerID], B9)<=2, IF((DATE(2024,4,30) - MAXIFS(dynamic[orderDate], dynamic[customerID], B9)) > 180, "Non-Returning", "Dormant"), IF(AND(MAX(dynamic[sinceLastOrder]) > 365, (DATE(2024,4,30) - MAXIFS(dynamic[orderDate], dynamic[customerID], B9)) > 180), "Dormant", "Regular"))) -> Regular | H9: 65 | I9: =VLOOKUP(dynamic[productID],products[],2,FALSE) -> Louisiana Fiery Hot Pepper Sauce | J9: =VLOOKUP(dynamic[productID],products[],12,FALSE) -> Condiments | K9: =IF(VLOOKUP(dynamic[productID],products[],7,FALSE)=1,"Discontinued","Current") -> Current | L9: =VLOOKUP(dynamic[productID],products[],IF(YEAR(dynamic[orderDate])=2022,8,IF(YEAR(dynamic[orderDate])=2023,9,IF(YEAR(dynamic[orderDate])=2024,10,NA))),FALSE) -> 11.174102 | M9: 16.8 | N9: =(dynamic[orderPrice]-dynamic[productCost])/dynamic[productCost] -> 0.50347652 | O9: 15 | P9: 0.15 | Q9: =dynamic[orderPrice]*dynamic[orderQuantity] -> 252 | R9: =dynamic[orderTotal]*(1-dynamic[discountApllied]) -> 214.2 | S9: =dynamic[revenue]-(dynamic[productCost]*dynamic[orderQuantity]) -> 46.588469 | T9: =IFERROR(dynamic[profit]/dynamic[revenue], 0) -> 0.21749986
A10: 10251 | B10: VICTE | C10: =VLOOKUP(dynamic[customerID],customers[],2,FALSE) -> Victuailles en stock | D10: 44750 | E10: =IFERROR(__xludf.DUMMYFUNCTION("COUNTUNIQUEIFS($A$2:$A10,$B$2:$B10,B10)"),1.0) -> 1 | F10: =IF(E10=1, 0, D10 - INDEX($D$2:$D10,MATCH(1, ($B$2:$B10=B10)*($E$2:$E10=E10-1), 0))) -> 0 | G10: =IF(MINIFS(dynamic[orderDate], dynamic[customerID], B10) >= DATE(2024,4,30)-120, "New", IF(MAXIFS(dynamic[orderCount], dynamic[customerID], B10)<=2, IF((DATE(2024,4,30) - MAXIFS(dynamic[orderDate], dynamic[customerID], B10)) > 180, "Non-Returning", "Dormant"), IF(AND(MAX(dynamic[sinceLastOrder]) > 365, (DATE(2024,4,30) - MAXIFS(dynamic[orderDate], dynamic[customerID], B10)) > 180), "Dormant", "Regular"))) -> Regular | H10: 22 | I10: =VLOOKUP(dynamic[productID],products[],2,FALSE) -> Gustaf's Knäckebröd | J10: =VLOOKUP(dynamic[productID],products[],12,FALSE) -> Grains/Cereals | K10: =IF(VLOOKUP(dynamic[productID],products[],7,FALSE)=1,"Discontinued","Current") -> Current | L10: =VLOOKUP(dynamic[productID],products[],IF(YEAR(dynamic[orderDate])=2022,8,IF(YEAR(dynamic[orderDate])=2023,9,IF(YEAR(dynamic[orderDate])=2024,10,NA))),FALSE) -> 11.700492 | M10: 16.8 | N10: =(dynamic[orderPrice]-dynamic[productCost])/dynamic[productCost] -> 0.43583704 | O10: 6 | P10: 0.05 | Q10: =dynamic[orderPrice]*dynamic[orderQuantity] -> 100.8 | R10: =dynamic[orderTotal]*(1-dynamic[discountApllied]) -> 95.76 | S10: =dynamic[revenue]-(dynamic[productCost]*dynamic[orderQuantity]) -> 25.557047 | T10: =IFERROR(dynamic[profit]/dynamic[revenue], 0) -> 0.26688646
A11: 10251 | B11: VICTE | C11: =VLOOKUP(dynamic[customerID],customers[],2,FALSE) -> Victuailles en stock | D11: 44750 | E11: =IFERROR(__xludf.DUMMYFUNCTION("COUNTUNIQUEIFS($A$2:$A11,$B$2:$B11,B11)"),1.0) -> 1 | F11: =IF(E11=1, 0, D11 - INDEX($D$2:$D11,MATCH(1, ($B$2:$B11=B11)*($E$2:$E11=E11-1), 0))) -> 0 | G11: =IF(MINIFS(dynamic[orderDate], dynamic[customerID], B11) >= DATE(2024,4,30)-120, "New", IF(MAXIFS(dynamic[orderCount], dynamic[customerID], B11)<=2, IF((DATE(2024,4,30) - MAXIFS(dynamic[orderDate], dynamic[customerID], B11)) > 180, "Non-Returning", "Dormant"), IF(AND(MAX(dynamic[sinceLastOrder]) > 365, (DATE(2024,4,30) - MAXIFS(dynamic[orderDate], dynamic[customerID], B11)) > 180), "Dormant", "Regular"))) -> Regular | H11: 57 | I11: =VLOOKUP(dynamic[productID],products[],2,FALSE) -> Ravioli Angelo | J11: =VLOOKUP(dynamic[productID],products[],12,FALSE) -> Grains/Cereals | K11: =IF(VLOOKUP(dynamic[productID],products[],7,FALSE)=1,"Discontinued","Current") -> Current | L11: =VLOOKUP(dynamic[productID],products[],IF(YEAR(dynamic[orderDate])=2022,8,IF(YEAR(dynamic[orderDate])=2023,9,IF(YEAR(dynamic[orderDate])=2024,10,NA))),FALSE) -> 11.229508 | M11: 15.6 | N11: =(dynamic[orderPrice]-dynamic[productCost])/dynamic[productCost] -> 0.38919715 | O11: 15 | P11: 0.05 | Q11: =dynamic[orderPrice]*dynamic[orderQuantity] -> 234 | R11: =dynamic[orderTotal]*(1-dynamic[discountApllied]) -> 222.3 | S11: =dynamic[revenue]-(dynamic[productCost]*dynamic[orderQuantity]) -> 53.857385 | T11: =IFERROR(dynamic[profit]/dynamic[revenue], 0) -> 0.24227344
A12: 10251 | B12: VICTE | C12: =VLOOKUP(dynamic[customerID],customers[],2,FALSE) -> Victuailles en stock | D12: 44750 | E12: =IFERROR(__xludf.DUMMYFUNCTION("COUNTUNIQUEIFS($A$2:$A12,$B$2:$B12,B12)"),1.0) -> 1 | F12: =IF(E12=1, 0, D12 - INDEX($D$2:$D12,MATCH(1, ($B$2:$B12=B12)*($E$2:$E12=E12-1), 0))) -> 0 | G12: =IF(MINIFS(dynamic[orderDate], dynamic[customerID], B12) >= DATE(2024,4,30)-120, "New", IF(MAXIFS(dynamic[orderCount], dynamic[customerID], B12)<=2, IF((DATE(2024,4,30) - MAXIFS(dynamic[orderDate], dynamic[customerID], B12)) > 180, "Non-Returning", "Dormant"), IF(AND(MAX(dynamic[sinceLastOrder]) > 365, (DATE(2024,4,30) - MAXIFS(dynamic[orderDate], dynamic[customerID], B12)) > 180), "Dormant", "Regular"))) -> Regular | H12: 65 | I12: =VLOOKUP(dynamic[productID],products[],2,FALSE) -> Louisiana Fiery Hot Pepper Sauce | J12: =VLOOKUP(dynamic[productID],products[],12,FALSE) -> Condiments | K12: =IF(VLOOKUP(dynamic[productID],products[],7,FALSE)=1,"Discontinued","Current") -> Current | L12: =VLOOKUP(dynamic[productID],products[],IF(YEAR(dynamic[orderDate])=2022,8,IF(YEAR(dynamic[orderDate])=2023,9,IF(YEAR(dynamic[orderDate])=2024,10,NA))),FALSE) -> 11.174102 | M12: 16.8 | N12: =(dynamic[orderPrice]-dynamic[productCost])/dynamic[productCost] -> 0.50347652 | O12: 20 | P12: 0 | Q12: =dynamic[orderPrice]*dynamic[orderQuantity] -> 336 | R12: =dynamic[orderTotal]*(1-dynamic[discountApllied]) -> 336 | S12: =dynamic[revenue]-(dynamic[productCost]*dynamic[orderQuantity]) -> 112.51796 | T12: =IFERROR(dynamic[profit]/dynamic[revenue], 0) -> 0.33487488
A13: 10252 | B13: SUPRD | C13: =VLOOKUP(dynamic[customerID],customers[],2,FALSE) -> Suprêmes délices | D13: 44751 | E13: =IFERROR(__xludf.DUMMYFUNCTION("COUNTUNIQUEIFS($A$2:$A13,$B$2:$B13,B13)"),1.0) -> 1 | F13: =IF(E13=1, 0, D13 - INDEX($D$2:$D13,MATCH(1, ($B$2:$B13=B13)*($E$2:$E13=E13-1), 0))) -> 0 | G13: =IF(MINIFS(dynamic[orderDate], dynamic[customerID], B13) >= DATE(2024,4,30)-120, "New", IF(MAXIFS(dynamic[orderCount], dynamic[customerID], B13)<=2, IF((DATE(2024,4,30) - MAXIFS(dynamic[orderDate], dynamic[customerID], B13)) > 180, "Non-Returning", "Dormant"), IF(AND(MAX(dynamic[sinceLastOrder]) > 365, (DATE(2024,4,30) - MAXIFS(dynamic[orderDate], dynamic[customerID], B13)) > 180), "Dormant", "Regular"))) -> Regular | H13: 20 | I13: =VLOOKUP(dynamic[productID],products[],2,FALSE) -> Sir Rodney's Marmalade | J13: =VLOOKUP(dynamic[productID],products[],12,FALSE) -> Confections | K13: =IF(VLOOKUP(dynamic[productID],products[],7,FALSE)=1,"Discontinued","Current") -> Current | L13: =VLOOKUP(dynamic[productID],products[],IF(YEAR(dynamic[orderDate])=2022,8,IF(YEAR(dynamic[orderDate])=2023,9,IF(YEAR(dynamic[orderDate])=2024,10,NA))),FALSE) -> 45.942474 | M13: 64.8 | N13: =(dynamic[orderPrice]-dynamic[productCost])/dynamic[productCost] -> 0.41045951 | O13: 40 | P13: 0.05 | Q13: =dynamic[orderPrice]*dynamic[orderQuantity] -> 2592 | R13: =dynamic[orderTotal]*(1-dynamic[discountApllied]) -> 2462.4 | S13: =dynamic[revenue]-(dynamic[productCost]*dynamic[orderQuantity]) -> 624.70102 | T13: =IFERROR(dynamic[profit]/dynamic[revenue], 0) -> 0.253696
A14: 10252 | B14: SUPRD | C14: =VLOOKUP(dynamic[customerID],customers[],2,FALSE) -> Suprêmes délices | D14: 44751 | E14: =IFERROR(__xludf.DUMMYFUNCTION("COUNTUNIQUEIFS($A$2:$A14,$B$2:$B14,B14)"),1.0) -> 1 | F14: =IF(E14=1, 0, D14 - INDEX($D$2:$D14,MATCH(1, ($B$2:$B14=B14)*($E$2:$E14=E14-1), 0))) -> 0 | G14: =IF(MINIFS(dynamic[orderDate], dynamic[customerID], B14) >= DATE(2024,4,30)-120, "New", IF(MAXIFS(dynamic[orderCount], dynamic[customerID], B14)<=2, IF((DATE(2024,4,30) - MAXIFS(dynamic[orderDate], dynamic[customerID], B14)) > 180, "Non-Returning", "Dormant"), IF(AND(MAX(dynamic[sinceLastOrder]) > 365, (DATE(2024,4,30) - MAXIFS(dynamic[orderDate], dynamic[customerID], B14)) > 180), "Dormant", "Regular"))) -> Regular | H14: 33 | I14: =VLOOKUP(dynamic[productID],products[],2,FALSE) -> Geitost | J14: =VLOOKUP(dynamic[productID],products[],12,FALSE) -> Dairy Products | K14: =IF(VLOOKUP(dynamic[productID],products[],7,FALSE)=1,"Discontinued","Current") -> Current | L14: =VLOOKUP(dynamic[productID],products[],IF(YEAR(dynamic[orderDate])=2022,8,IF(YEAR(dynamic[orderDate])=2023,9,IF(YEAR(dynamic[orderDate])=2024,10,NA))),FALSE) -> 1.3938474 | M14: 2 | N14: =(dynamic[orderPrice]-dynamic[productCost])/dynamic[productCost] -> 0.43487727 | O14: 25 | P14: 0.05 | Q14: =dynamic[orderPrice]*dynamic[orderQuantity] -> 50 | R14: =dynamic[orderTotal]*(1-dynamic[discountApllied]) -> 47.5 | S14: =dynamic[revenue]-(dynamic[productCost]*dynamic[orderQuantity]) -> 12.653814 | T14: =IFERROR(dynamic[profit]/dynamic[revenue], 0) -> 0.26639609
A15: 10252 | B15: SUPRD | C15: =VLOOKUP(dynamic[customerID],customers[],2,FALSE) -> Suprêmes délices | D15: 44751 | E15: =IFERROR(__xludf.DUMMYFUNCTION("COUNTUNIQUEIFS($A$2:$A15,$B$2:$B15,B15)"),1.0) -> 1 | F15: =IF(E15=1, 0, D15 - INDEX($D$2:$D15,MATCH(1, ($B$2:$B15=B15)*($E$2:$E15=E15-1), 0))) -> 0 | G15: =IF(MINIFS(dynamic[orderDate], dynamic[customerID], B15) >= DATE(2024,4,30)-120, "New", IF(MAXIFS(dynamic[orderCount], dynamic[customerID], B15)<=2, IF((DATE(2024,4,30) - MAXIFS(dynamic[orderDate], dynamic[customerID], B15)) > 180, "Non-Returning", "Dormant"), IF(AND(MAX(dynamic[sinceLastOrder]) > 365, (DATE(2024,4,30) - MAXIFS(dynamic[orderDate], dynamic[customerID], B15)) > 180), "Dormant", "Regular"))) -> Regular | H15: 60 | I15: =VLOOKUP(dynamic[productID],products[],2,FALSE) -> Camembert Pierrot | J15: =VLOOKUP(dynamic[productID],products[],12,FALSE) -> Dairy Products | K15: =IF(VLOOKUP(dynamic[productID],products[],7,FALSE)=1,"Discontinued","Current") -> Current | L15: =VLOOKUP(dynamic[productID],products[],IF(YEAR(dynamic[orderDate])=2022,8,IF(YEAR(dynamic[orderDate])=2023,9,IF(YEAR(dynamic[orderDate])=2024,10,NA))),FALSE) -> 17.665635 | M15: 27.2 | N15: =(dynamic[orderPrice]-dynamic[productCost])/dynamic[productCost] -> 0.53971256 | O15: 40 | P15: 0 | Q15: =dynamic[orderPrice]*dynamic[orderQuantity] -> 1088 | R15: =dynamic[orderTotal]*(1-dynamic[discountApllied]) -> 1088 | S15: =dynamic[revenue]-(dynamic[productCost]*dynamic[orderQuantity]) -> 381.3746 | T15: =IFERROR(dynamic[profit]/dynamic[revenue], 0) -> 0.35052813
A16: 10253 | B16: HANAR | C16: =VLOOKUP(dynamic[customerID],customers[],2,FALSE) -> Hanari Carnes | D16: 44752 | E16: =IFERROR(__xludf.DUMMYFUNCTION("COUNTUNIQUEIFS($A$2:$A16,$B$2:$B16,B16)"),2.0) -> 2 | F16: =IF(E16=1, 0, D16 - INDEX($D$2:$D16,MATCH(1, ($B$2:$B16=B16)*($E$2:$E16=E16-1), 0))) -> 2 | G16: =IF(MINIFS(dynamic[orderDate], dynamic[customerID], B16) >= DATE(2024,4,30)-120, "New", IF(MAXIFS(dynamic[orderCount], dynamic[customerID], B16)<=2, IF((DATE(2024,4,30) - MAXIFS(dynamic[orderDate], dynamic[customerID], B16)) > 180, "Non-Returning", "Dormant"), IF(AND(MAX(dynamic[sinceLastOrder]) > 365, (DATE(2024,4,30) - MAXIFS(dynamic[orderDate], dynamic[customerID], B16)) > 180), "Dormant", "Regular"))) -> Regular | H16: 31 | I16: =VLOOKUP(dynamic[productID],products[],2,FALSE) -> Gorgonzola Telino | J16: =VLOOKUP(dynamic[productID],products[],12,FALSE) -> Dairy Products | K16: =IF(VLOOKUP(dynamic[productID],products[],7,FALSE)=1,"Discontinued","Current") -> Current | L16: =VLOOKUP(dynamic[productID],products[],IF(YEAR(dynamic[orderDate])=2022,8,IF(YEAR(dynamic[orderDate])=2023,9,IF(YEAR(dynamic[orderDate])=2024,10,NA))),FALSE) -> 6.4403197 | M16: 10 | N16: =(dynamic[orderPrice]-dynamic[productCost])/dynamic[productCost] -> 0.55271794 | O16: 20 | P16: 0 | Q16: =dynamic[orderPrice]*dynamic[orderQuantity] -> 200 | R16: =dynamic[orderTotal]*(1-dynamic[discountApllied]) -> 200 | S16: =dynamic[revenue]-(dynamic[productCost]*dynamic[orderQuantity]) -> 71.193605 | T16: =IFERROR(dynamic[profit]/dynamic[revenue], 0) -> 0.35596803
A17: 10253 | B17: HANAR | C17: =VLOOKUP(dynamic[customerID],customers[],2,FALSE) -> Hanari Carnes | D17: 44752 | E17: =IFERROR(__xludf.DUMMYFUNCTION("COUNTUNIQUEIFS($A$2:$A17,$B$2:$B17,B17)"),2.0) -> 2 | F17: =IF(E17=1, 0, D17 - INDEX($D$2:$D17,MATCH(1, ($B$2:$B17=B17)*($E$2:$E17=E17-1), 0))) -> 2 | G17: =IF(MINIFS(dynamic[orderDate], dynamic[customerID], B17) >= DATE(2024,4,30)-120, "New", IF(MAXIFS(dynamic[orderCount], dynamic[customerID], B17)<=2, IF((DATE(2024,4,30) - MAXIFS(dynamic[orderDate], dynamic[customerID], B17)) > 180, "Non-Returning", "Dormant"), IF(AND(MAX(dynamic[sinceLastOrder]) > 365, (DATE(2024,4,30) - MAXIFS(dynamic[orderDate], dynamic[customerID], B17)) > 180), "Dormant", "Regular"))) -> Regular | H17: 39 | I17: =VLOOKUP(dynamic[productID],products[],2,FALSE) -> Chartreuse verte | J17: =VLOOKUP(dynamic[productID],products[],12,FALSE) -> Beverages | K17: =IF(VLOOKUP(dynamic[productID],products[],7,FALSE)=1,"Discontinued","Current") -> Current | L17: =VLOOKUP(dynamic[productID],products[],IF(YEAR(dynamic[orderDate])=2022,8,IF(YEAR(dynamic[orderDate])=2023,9,IF(YEAR(dynamic[orderDate])=2024,10,NA))),FALSE) -> 9.7435172 | M17: 14.4 | N17: =(dynamic[orderPrice]-dynamic[productCost])/dynamic[productCost] -> 0.47790574 | O17: 42 | P17: 0 | Q17: =dynamic[orderPrice]*dynamic[orderQuantity] -> 604.8 | R17: =dynamic[orderTotal]*(1-dynamic[discountApllied]) -> 604.8 | S17: =dynamic[revenue]-(dynamic[productCost]*dynamic[orderQuantity]) -> 195.57228 | T17: =IFERROR(dynamic[profit]/dynamic[revenue], 0) -> 0.32336686
A18: 10253 | B18: HANAR | C18: =VLOOKUP(dynamic[customerID],customers[],2,FALSE) -> Hanari Carnes | D18: 44752 | E18: =IFERROR(__xludf.DUMMYFUNCTION("COUNTUNIQUEIFS($A$2:$A18,$B$2:$B18,B18)"),2.0) -> 2 | F18: =IF(E18=1, 0, D18 - INDEX($D$2:$D18,MATCH(1, ($B$2:$B18=B18)*($E$2:$E18=E18-1), 0))) -> 2 | G18: =IF(MINIFS(dynamic[orderDate], dynamic[customerID], B18) >= DATE(2024,4,30)-120, "New", IF(MAXIFS(dynamic[orderCount], dynamic[customerID], B18)<=2, IF((DATE(2024,4,30) - MAXIFS(dynamic[orderDate], dynamic[customerID], B18)) > 180, "Non-Returning", "Dormant"), IF(AND(MAX(dynamic[sinceLastOrder]) > 365, (DATE(2024,4,30) - MAXIFS(dynamic[orderDate], dynamic[customerID], B18)) > 180), "Dormant", "Regular"))) -> Regular | H18: 49 | I18: =VLOOKUP(dynamic[productID],products[],2,FALSE) -> Maxilaku | J18: =VLOOKUP(dynamic[productID],products[],12,FALSE) -> Confections | K18: =IF(VLOOKUP(dynamic[productID],products[],7,FALSE)=1,"Discontinued","Current") -> Current | L18: =VLOOKUP(dynamic[productID],products[],IF(YEAR(dynamic[orderDate])=2022,8,IF(YEAR(dynamic[orderDate])=2023,9,IF(YEAR(dynamic[orderDate])=2024,10,NA))),FALSE) -> 12.566636 | M18: 16 | N18: =(dynamic[orderPrice]-dynamic[productCost])/dynamic[productCost] -> 0.27321268 | O18: 40 | P18: 0 | Q18: =dynamic[orderPrice]*dynamic[orderQuantity] -> 640 | R18: =dynamic[orderTotal]*(1-dynamic[discountApllied]) -> 640 | S18: =dynamic[revenue]-(dynamic[productCost]*dynamic[orderQuantity]) -> 137.33457 | T18: =IFERROR(dynamic[profit]/dynamic[revenue], 0) -> 0.21458526
A19: 10254 | B19: CHOPS | C19: =VLOOKUP(dynamic[customerID],customers[],2,FALSE) -> Chop-suey Chinese | D19: 44753 | E19: =IFERROR(__xludf.DUMMYFUNCTION("COUNTUNIQUEIFS($A$2:$A19,$B$2:$B19,B19)"),1.0) -> 1 | F19: =IF(E19=1, 0, D19 - INDEX($D$2:$D19,MATCH(1, ($B$2:$B19=B19)*($E$2:$E19=E19-1), 0))) -> 0 | G19: =IF(MINIFS(dynamic[orderDate], dynamic[customerID], B19) >= DATE(2024,4,30)-120, "New", IF(MAXIFS(dynamic[orderCount], dynamic[customerID], B19)<=2, IF((DATE(2024,4,30) - MAXIFS(dynamic[orderDate], dynamic[customerID], B19)) > 180, "Non-Returning", "Dormant"), IF(AND(MAX(dynamic[sinceLastOrder]) > 365, (DATE(2024,4,30) - MAXIFS(dynamic[orderDate], dynamic[customerID], B19)) > 180), "Dormant", "Regular"))) -> Regular | H19: 24 | I19: =VLOOKUP(dynamic[productID],products[],2,FALSE) -> Brigadeiros Maravilhosos da Lilian | J19: =VLOOKUP(dynamic[productID],products[],12,FALSE) -> Confections | K19: =IF(VLOOKUP(dynamic[productID],products[],7,FALSE)=1,"Discontinued","Current") -> Discontinued | L19: =VLOOKUP(dynamic[productID],products[],IF(YEAR(dynamic[orderDate])=2022,8,IF(YEAR(dynamic[orderDate])=2023,9,IF(YEAR(dynamic[orderDate])=2024,10,NA))),FALSE) -> 2.6811725 | M19: 3.6 | N19: =(dynamic[orderPrice]-dynamic[productCost])/dynamic[productCost] -> 0.34269617 | O19: 15 | P19: 0.15 | Q19: =dynamic[orderPrice]*dynamic[orderQuantity] -> 54 | R19: =dynamic[orderTotal]*(1-dynamic[discountApllied]) -> 45.9 | S19: =dynamic[revenue]-(dynamic[productCost]*dynamic[orderQuantity]) -> 5.6824131 | T19: =IFERROR(dynamic[profit]/dynamic[revenue], 0) -> 0.12379985
A20: 10254 | B20: CHOPS | C20: =VLOOKUP(dynamic[customerID],customers[],2,FALSE) -> Chop-suey Chinese | D20: 44753 | E20: =IFERROR(__xludf.DUMMYFUNCTION("COUNTUNIQUEIFS($A$2:$A20,$B$2:$B20,B20)"),1.0) -> 1 | F20: =IF(E20=1, 0, D20 - INDEX($D$2:$D20,MATCH(1, ($B$2:$B20=B20)*($E$2:$E20=E20-1), 0))) -> 0 | G20: =IF(MINIFS(dynamic[orderDate], dynamic[customerID], B20) >= DATE(2024,4,30)-120, "New", IF(MAXIFS(dynamic[orderCount], dynamic[customerID], B20)<=2, IF((DATE(2024,4,30) - MAXIFS(dynamic[orderDate], dynamic[customerID], B20)) > 180, "Non-Returning", "Dormant"), IF(AND(MAX(dynamic[sinceLastOrder]) > 365, (DATE(2024,4,30) - MAXIFS(dynamic[orderDate], dynamic[customerID], B20)) > 180), "Dormant", "Regular"))) -> Regular | H20: 55 | I20: =VLOOKUP(dynamic[productID],products[],2,FALSE) -> Pâté chinois | J20: =VLOOKUP(dynamic[productID],products[],12,FALSE) -> Meat/Poultry | K20: =IF(VLOOKUP(dynamic[productID],products[],7,FALSE)=1,"Discontinued","Current") -> Current | L20: =VLOOKUP(dynamic[productID],products[],IF(YEAR(dynamic[orderDate])=2022,8,IF(YEAR(dynamic[orderDate])=2023,9,IF(YEAR(dynamic[orderDate])=2024,10,NA))),FALSE) -> 12.974961 | M20: 19.2 | N20: =(dynamic[orderPrice]-dynamic[productCost])/dynamic[productCost] -> 0.47977329 | O20: 21 | P20: 0.15 | Q20: =dynamic[orderPrice]*dynamic[orderQuantity] -> 403.2 | R20: =dynamic[orderTotal]*(1-dynamic[discountApllied]) -> 342.72 | S20: =dynamic[revenue]-(dynamic[productCost]*dynamic[orderQuantity]) -> 70.245829 | T20: =IFERROR(dynamic[profit]/dynamic[revenue], 0) -> 0.20496565
A21: 10254 | B21: CHOPS | C21: =VLOOKUP(dynamic[customerID],customers[],2,FALSE) -> Chop-suey Chinese | D21: 44753 | E21: =IFERROR(__xludf.DUMMYFUNCTION("COUNTUNIQUEIFS($A$2:$A21,$B$2:$B21,B21)"),1.0) -> 1 | F21: =IF(E21=1, 0, D21 - INDEX($D$2:$D21,MATCH(1, ($B$2:$B21=B21)*($E$2:$E21=E21-1), 0))) -> 0 | G21: =IF(MINIFS(dynamic[orderDate], dynamic[customerID], B21) >= DATE(2024,4,30)-120, "New", IF(MAXIFS(dynamic[orderCount], dynamic[customerID], B21)<=2, IF((DATE(2024,4,30) - MAXIFS(dynamic[orderDate], dynamic[customerID], B21)) > 180, "Non-Returning", "Dormant"), IF(AND(MAX(dynamic[sinceLastOrder]) > 365, (DATE(2024,4,30) - MAXIFS(dynamic[orderDate], dynamic[customerID], B21)) > 180), "Dormant", "Regular"))) -> Regular | H21: 74 | I21: =VLOOKUP(dynamic[productID],products[],2,FALSE) -> Longlife Tofu | J21: =VLOOKUP(dynamic[productID],products[],12,FALSE) -> Produce | K21: =IF(VLOOKUP(dynamic[productID],products[],7,FALSE)=1,"Discontinued","Current") -> Current | L21: =VLOOKUP(dynamic[productID],products[],IF(YEAR(dynamic[orderDate])=2022,8,IF(YEAR(dynamic[orderDate])=2023,9,IF(YEAR(dynamic[orderDate])=2024,10,NA))),FALSE) -> 5.6671301 | M21: 8 | N21: =(dynamic[orderPrice]-dynamic[productCost])/dynamic[productCost] -> 0.41164925 | O21: 21 | P21: 0 | Q21: =dynamic[orderPrice]*dynamic[orderQuantity] -> 168 | R21: =dynamic[orderTotal]*(1-dynamic[discountApllied]) -> 168 | S21: =dynamic[revenue]-(dynamic[productCost]*dynamic[orderQuantity]) -> 48.990267 | T21: =IFERROR(dynamic[profit]/dynamic[revenue], 0) -> 0.29160873
A22: 10255 | B22: RICSU | C22: =VLOOKUP(dynamic[customerID],customers[],2,FALSE) -> Richter Supermarkt | D22: 44754 | E22: =IFERROR(__xludf.DUMMYFUNCTION("COUNTUNIQUEIFS($A$2:$A22,$B$2:$B22,B22)"),1.0) -> 1 | F22: =IF(E22=1, 0, D22 - INDEX($D$2:$D22,MATCH(1, ($B$2:$B22=B22)*($E$2:$E22=E22-1), 0))) -> 0 | G22: =IF(MINIFS(dynamic[orderDate], dynamic[customerID], B22) >= DATE(2024,4,30)-120, "New", IF(MAXIFS(dynamic[orderCount], dynamic[customerID], B22)<=2, IF((DATE(2024,4,30) - MAXIFS(dynamic[orderDate], dynamic[customerID], B22)) > 180, "Non-Returning", "Dormant"), IF(AND(MAX(dynamic[sinceLastOrder]) > 365, (DATE(2024,4,30) - MAXIFS(dynamic[orderDate], dynamic[customerID], B22)) > 180), "Dormant", "Regular"))) -> Regular | H22: 2 | I22: =VLOOKUP(dynamic[productID],products[],2,FALSE) -> Chang | J22: =VLOOKUP(dynamic[productID],products[],12,FALSE) -> Beverages | K22: =IF(VLOOKUP(dynamic[productID],products[],7,FALSE)=1,"Discontinued","Current") -> Current | L22: =VLOOKUP(dynamic[productID],products[],IF(YEAR(dynamic[orderDate])=2022,8,IF(YEAR(dynamic[orderDate])=2023,9,IF(YEAR(dynamic[orderDate])=2024,10,NA))),FALSE) -> 9.7687469 | M22: 15.2 | N22: =(dynamic[orderPrice]-dynamic[productCost])/dynamic[productCost] -> 0.55598258 | O22: 20 | P22: 0 | Q22: =dynamic[orderPrice]*dynamic[orderQuantity] -> 304 | R22: =dynamic[orderTotal]*(1-dynamic[discountApllied]) -> 304 | S22: =dynamic[revenue]-(dynamic[productCost]*dynamic[orderQuantity]) -> 108.62506 | T22: =IFERROR(dynamic[profit]/dynamic[revenue], 0) -> 0.35731928
A23: 10255 | B23: RICSU | C23: =VLOOKUP(dynamic[customerID],customers[],2,FALSE) -> Richter Supermarkt | D23: 44754 | E23: =IFERROR(__xludf.DUMMYFUNCTION("COUNTUNIQUEIFS($A$2:$A23,$B$2:$B23,B23)"),1.0) -> 1 | F23: =IF(E23=1, 0, D23 - INDEX($D$2:$D23,MATCH(1, ($B$2:$B23=B23)*($E$2:$E23=E23-1), 0))) -> 0 | G23: =IF(MINIFS(dynamic[orderDate], dynamic[customerID], B23) >= DATE(2024,4,30)-120, "New", IF(MAXIFS(dynamic[orderCount], dynamic[customerID], B23)<=2, IF((DATE(2024,4,30) - MAXIFS(dynamic[orderDate], dynamic[customerID], B23)) > 180, "Non-Returning", "Dormant"), IF(AND(MAX(dynamic[sinceLastOrder]) > 365, (DATE(2024,4,30) - MAXIFS(dynamic[orderDate], dynamic[customerID], B23)) > 180), "Dormant", "Regular"))) -> Regular | H23: 16 | I23: =VLOOKUP(dynamic[productID],products[],2,FALSE) -> Pavlova | J23: =VLOOKUP(dynamic[productID],products[],12,FALSE) -> Confections | K23: =IF(VLOOKUP(dynamic[productID],products[],7,FALSE)=1,"Discontinued","Current") -> Current | L23: =VLOOKUP(dynamic[productID],products[],IF(YEAR(dynamic[orderDate])=2022,8,IF(YEAR(dynamic[orderDate])=2023,9,IF(YEAR(dynamic[orderDate])=2024,10,NA))),FALSE) -> 9.8065801 | M23: 13.9 | N23: =(dynamic[orderPrice]-dynamic[productCost])/dynamic[productCost] -> 0.41741564 | O23: 35 | P23: 0 | Q23: =dynamic[orderPrice]*dynamic[orderQuantity] -> 486.5 | R23: =dynamic[orderTotal]*(1-dynamic[discountApllied]) -> 486.5 | S23: =dynamic[revenue]-(dynamic[productCost]*dynamic[orderQuantity]) -> 143.2697 | T23: =IFERROR(dynamic[profit]/dynamic[revenue], 0) -> 0.29449064
A24: 10255 | B24: RICSU | C24: =VLOOKUP(dynamic[customerID],customers[],2,FALSE) -> Richter Supermarkt | D24: 44754 | E24: =IFERROR(__xludf.DUMMYFUNCTION("COUNTUNIQUEIFS($A$2:$A24,$B$2:$B24,B24)"),1.0) -> 1 | F24: =IF(E24=1, 0, D24 - INDEX($D$2:$D24,MATCH(1, ($B$2:$B24=B24)*($E$2:$E24=E24-1), 0))) -> 0 | G24: =IF(MINIFS(dynamic[orderDate], dynamic[customerID], B24) >= DATE(2024,4,30)-120, "New", IF(MAXIFS(dynamic[orderCount], dynamic[customerID], B24)<=2, IF((DATE(2024,4,30) - MAXIFS(dynamic[orderDate], dynamic[customerID], B24)) > 180, "Non-Returning", "Dormant"), IF(AND(MAX(dynamic[sinceLastOrder]) > 365, (DATE(2024,4,30) - MAXIFS(dynamic[orderDate], dynamic[customerID], B24)) > 180), "Dormant", "Regular"))) -> Regular | H24: 36 | I24: =VLOOKUP(dynamic[productID],products[],2,FALSE) -> Inlagd Sill | J24: =VLOOKUP(dynamic[productID],products[],12,FALSE) -> Seafood | K24: =IF(VLOOKUP(dynamic[productID],products[],7,FALSE)=1,"Discontinued","Current") -> Current | L24: =VLOOKUP(dynamic[productID],products[],IF(YEAR(dynamic[orderDate])=2022,8,IF(YEAR(dynamic[orderDate])=2023,9,IF(YEAR(dynamic[orderDate])=2024,10,NA))),FALSE) -> 9.7682384 | M24: 15.2 | N24: =(dynamic[orderPrice]-dynamic[productCost])/dynamic[productCost] -> 0.55606357 | O24: 25 | P24: 0 | Q24: =dynamic[orderPrice]*dynamic[orderQuantity] -> 380 | R24: =dynamic[orderTotal]*(1-dynamic[discountApllied]) -> 380 | S24: =dynamic[revenue]-(dynamic[productCost]*dynamic[orderQuantity]) -> 135.79404 | T24: =IFERROR(dynamic[profit]/dynamic[revenue], 0) -> 0.35735273
A25: 10255 | B25: RICSU | C25: =VLOOKUP(dynamic[customerID],customers[],2,FALSE) -> Richter Supermarkt | D25: 44754 | E25: =IFERROR(__xludf.DUMMYFUNCTION("COUNTUNIQUEIFS($A$2:$A25,$B$2:$B25,B25)"),1.0) -> 1 | F25: =IF(E25=1, 0, D25 - INDEX($D$2:$D25,MATCH(1, ($B$2:$B25=B25)*($E$2:$E25=E25-1), 0))) -> 0 | G25: =IF(MINIFS(dynamic[orderDate], dynamic[customerID], B25) >= DATE(2024,4,30)-120, "New", IF(MAXIFS(dynamic[orderCount], dynamic[customerID], B25)<=2, IF((DATE(2024,4,30) - MAXIFS(dynamic[orderDate], dynamic[customerID], B25)) > 180, "Non-Returning", "Dormant"), IF(AND(MAX(dynamic[sinceLastOrder]) > 365, (DATE(2024,4,30) - MAXIFS(dynamic[orderDate], dynamic[customerID], B25)) > 180), "Dormant", "Regular"))) -> Regular | H25: 59 | I25: =VLOOKUP(dynamic[productID],products[],2,FALSE) -> Raclette Courdavault | J25: =VLOOKUP(dynamic[productID],products[],12,FALSE) -> Dairy Products | K25: =IF(VLOOKUP(dynamic[productID],products[],7,FALSE)=1,"Discontinued","Current") -> Current | L25: =VLOOKUP(dynamic[productID],products[],IF(YEAR(dynamic[orderDate])=2022,8,IF(YEAR(dynamic[orderDate])=2023,9,IF(YEAR(dynamic[orderDate])=2024,10,NA))),FALSE) -> 29.20352 | M25: 44 | N25: =(dynamic[orderPrice]-dynamic[productCost])/dynamic[productCost] -> 0.50666771 | O25: 30 | P25: 0 | Q25: =dynamic[orderPrice]*dynamic[orderQuantity] -> 1320 | R25: =dynamic[orderTotal]*(1-dynamic[discountApllied]) -> 1320 | S25: =dynamic[revenue]-(dynamic[productCost]*dynamic[orderQuantity]) -> 443.89441 | T25: =IFERROR(dynamic[profit]/dynamic[revenue], 0) -> 0.33628365
A26: 10256 | B26: WELLI | C26: =VLOOKUP(dynamic[customerID],customers[],2,FALSE) -> Wellington Importadora | D26: 44757 | E26: =IFERROR(__xludf.DUMMYFUNCTION("COUNTUNIQUEIFS($A$2:$A26,$B$2:$B26,B26)"),1.0) -> 1 | F26: =IF(E26=1, 0, D26 - INDEX($D$2:$D26,MATCH(1, ($B$2:$B26=B26)*($E$2:$E26=E26-1), 0))) -> 0 | G26: =IF(MINIFS(dynamic[orderDate], dynamic[customerID], B26) >= DATE(2024,4,30)-120, "New", IF(MAXIFS(dynamic[orderCount], dynamic[customerID], B26)<=2, IF((DATE(2024,4,30) - MAXIFS(dynamic[orderDate], dynamic[customerID], B26)) > 180, "Non-Returning", "Dormant"), IF(AND(MAX(dynamic[sinceLastOrder]) > 365, (DATE(2024,4,30) - MAXIFS(dynamic[orderDate], dynamic[customerID], B26)) > 180), "Dormant", "Regular"))) -> Regular | H26: 53 | I26: =VLOOKUP(dynamic[productID],products[],2,FALSE) -> Perth Pasties | J26: =VLOOKUP(dynamic[productID],products[],12,FALSE) -> Meat/Poultry | K26: =IF(VLOOKUP(dynamic[productID],products[],7,FALSE)=1,"Discontinued","Current") -> Discontinued | L26: =VLOOKUP(dynamic[productID],products[],IF(YEAR(dynamic[orderDate])=2022,8,IF(YEAR(dynamic[orderDate])=2023,9,IF(YEAR(dynamic[orderDate])=2024,10,NA))),FALSE) -> 18.33322 | M26: 26.2 | N26: =(dynamic[orderPrice]-dynamic[productCost])/dynamic[productCost] -> 0.42909974 | O26: 15 | P26: 0 | Q26: =dynamic[orderPrice]*dynamic[orderQuantity] -> 393 | R26: =dynamic[orderTotal]*(1-dynamic[discountApllied]) -> 393 | S26: =dynamic[revenue]-(dynamic[productCost]*dynamic[orderQuantity]) -> 118.0017 | T26: =IFERROR(dynamic[profit]/dynamic[revenue], 0) -> 0.30025878
A27: 10256 | B27: WELLI | C27: =VLOOKUP(dynamic[customerID],customers[],2,FALSE) -> Wellington Importadora | D27: 44757 | E27: =IFERROR(__xludf.DUMMYFUNCTION("COUNTUNIQUEIFS($A$2:$A27,$B$2:$B27,B27)"),1.0) -> 1 | F27: =IF(E27=1, 0, D27 - INDEX($D$2:$D27,MATCH(1, ($B$2:$B27=B27)*($E$2:$E27=E27-1), 0))) -> 0 | G27: =IF(MINIFS(dynamic[orderDate], dynamic[customerID], B27) >= DATE(2024,4,30)-120, "New", IF(MAXIFS(dynamic[orderCount], dynamic[customerID], B27)<=2, IF((DATE(2024,4,30) - MAXIFS(dynamic[orderDate], dynamic[customerID], B27)) > 180, "Non-Returning", "Dormant"), IF(AND(MAX(dynamic[sinceLastOrder]) > 365, (DATE(2024,4,30) - MAXIFS(dynamic[orderDate], dynamic[customerID], B27)) > 180), "Dormant", "Regular"))) -> Regular | H27: 77 | I27: =VLOOKUP(dynamic[productID],products[],2,FALSE) -> Original Frankfurter grüne Soße | J27: =VLOOKUP(dynamic[productID],products[],12,FALSE) -> Condiments | K27: =IF(VLOOKUP(dynamic[productID],products[],7,FALSE)=1,"Discontinued","Current") -> Current | L27: =VLOOKUP(dynamic[productID],products[],IF(YEAR(dynamic[orderDate])=2022,8,IF(YEAR(dynamic[orderDate])=2023,9,IF(YEAR(dynamic[orderDate])=2024,10,NA))),FALSE) -> 7.4302728 | M27: 10.4 | N27: =(dynamic[orderPrice]-dynamic[productCost])/dynamic[productCost] -> 0.39967942 | O27: 12 | P27: 0 | Q27: =dynamic[orderPrice]*dynamic[orderQuantity] -> 124.8 | R27: =dynamic[orderTotal]*(1-dynamic[discountApllied]) -> 124.8 | S27: =dynamic[revenue]-(dynamic[productCost]*dynamic[orderQuantity]) -> 35.636726 | T27: =IFERROR(dynamic[profit]/dynamic[revenue], 0) -> 0.28555069
A28: 10257 | B28: HILAA | C28: =VLOOKUP(dynamic[customerID],customers[],2,FALSE) -> HILARION-Abastos | D28: 44758 | E28: =IFERROR(__xludf.DUMMYFUNCTION("COUNTUNIQUEIFS($A$2:$A28,$B$2:$B28,B28)"),1.0) -> 1 | F28: =IF(E28=1, 0, D28 - INDEX($D$2:$D28,MATCH(1, ($B$2:$B28=B28)*($E$2:$E28=E28-1), 0))) -> 0 | G28: =IF(MINIFS(dynamic[orderDate], dynamic[customerID], B28) >= DATE(2024,4,30)-120, "New", IF(MAXIFS(dynamic[orderCount], dynamic[customerID], B28)<=2, IF((DATE(2024,4,30) - MAXIFS(dynamic[orderDate], dynamic[customerID], B28)) > 180, "Non-Returning", "Dormant"), IF(AND(MAX(dynamic[sinceLastOrder]) > 365, (DATE(2024,4,30) - MAXIFS(dynamic[orderDate], dynamic[customerID], B28)) > 180), "Dormant", "Regular"))) -> Regular | H28: 27 | I28: =VLOOKUP(dynamic[productID],products[],2,FALSE) -> Schoggi Schokolade | J28: =VLOOKUP(dynamic[productID],products[],12,FALSE) -> Confections | K28: =IF(VLOOKUP(dynamic[productID],products[],7,FALSE)=1,"Discontinued","Current") -> Current | L28: =VLOOKUP(dynamic[productID],products[],IF(YEAR(dynamic[orderDate])=2022,8,IF(YEAR(dynamic[orderDate])=2023,9,IF(YEAR(dynamic[orderDate])=2024,10,NA))),FALSE) -> 23.205628 | M28: 35.1 | N28: =(dynamic[orderPrice]-dynamic[productCost])/dynamic[productCost] -> 0.51256408 | O28: 25 | P28: 0 | Q28: =dynamic[orderPrice]*dynamic[orderQuantity] -> 877.5 | R28: =dynamic[orderTotal]*(1-dynamic[discountApllied]) -> 877.5 | S28: =dynamic[revenue]-(dynamic[productCost]*dynamic[orderQuantity]) -> 297.35929 | T28: =IFERROR(dynamic[profit]/dynamic[revenue], 0) -> 0.33887099
A29: 10257 | B29: HILAA | C29: =VLOOKUP(dynamic[customerID],customers[],2,FALSE) -> HILARION-Abastos | D29: 44758 | E29: =IFERROR(__xludf.DUMMYFUNCTION("COUNTUNIQUEIFS($A$2:$A29,$B$2:$B29,B29)"),1.0) -> 1 | F29: =IF(E29=1, 0, D29 - INDEX($D$2:$D29,MATCH(1, ($B$2:$B29=B29)*($E$2:$E29=E29-1), 0))) -> 0 | G29: =IF(MINIFS(dynamic[orderDate], dynamic[customerID], B29) >= DATE(2024,4,30)-120, "New", IF(MAXIFS(dynamic[orderCount], dynamic[customerID], B29)<=2, IF((DATE(2024,4,30) - MAXIFS(dynamic[orderDate], dynamic[customerID], B29)) > 180, "Non-Returning", "Dormant"), IF(AND(MAX(dynamic[sinceLastOrder]) > 365, (DATE(2024,4,30) - MAXIFS(dynamic[orderDate], dynamic[customerID], B29)) > 180), "Dormant", "Regular"))) -> Regular | H29: 39 | I29: =VLOOKUP(dynamic[productID],products[],2,FALSE) -> Chartreuse verte | J29: =VLOOKUP(dynamic[productID],products[],12,FALSE) -> Beverages | K29: =IF(VLOOKUP(dynamic[productID],products[],7,FALSE)=1,"Discontinued","Current") -> Current | L29: =VLOOKUP(dynamic[productID],products[],IF(YEAR(dynamic[orderDate])=2022,8,IF(YEAR(dynamic[orderDate])=2023,9,IF(YEAR(dynamic[orderDate])=2024,10,NA))),FALSE) -> 9.7435172 | M29: 14.4 | N29: =(dynamic[orderPrice]-dynamic[productCost])/dynamic[productCost] -> 0.47790574 | O29: 6 | P29: 0 | Q29: =dynamic[orderPrice]*dynamic[orderQuantity] -> 86.4 | R29: =dynamic[orderTotal]*(1-dynamic[discountApllied]) -> 86.4 | S29: =dynamic[revenue]-(dynamic[productCost]*dynamic[orderQuantity]) -> 27.938897 | T29: =IFERROR(dynamic[profit]/dynamic[revenue], 0) -> 0.32336686
A30: 10257 | B30: HILAA | C30: =VLOOKUP(dynamic[customerID],customers[],2,FALSE) -> HILARION-Abastos | D30: 44758 | E30: =IFERROR(__xludf.DUMMYFUNCTION("COUNTUNIQUEIFS($A$2:$A30,$B$2:$B30,B30)"),1.0) -> 1 | F30: =IF(E30=1, 0, D30 - INDEX($D$2:$D30,MATCH(1, ($B$2:$B30=B30)*($E$2:$E30=E30-1), 0))) -> 0 | G30: =IF(MINIFS(dynamic[orderDate], dynamic[customerID], B30) >= DATE(2024,4,30)-120, "New", IF(MAXIFS(dynamic[orderCount], dynamic[customerID], B30)<=2, IF((DATE(2024,4,30) - MAXIFS(dynamic[orderDate], dynamic[customerID], B30)) > 180, "Non-Returning", "Dormant"), IF(AND(MAX(dynamic[sinceLastOrder]) > 365, (DATE(2024,4,30) - MAXIFS(dynamic[orderDate], dynamic[customerID], B30)) > 180), "Dormant", "Regular"))) -> Regular | H30: 77 | I30: =VLOOKUP(dynamic[productID],products[],2,FALSE) -> Original Frankfurter grüne Soße | J30: =VLOOKUP(dynamic[productID],products[],12,FALSE) -> Condiments | K30: =IF(VLOOKUP(dynamic[productID],products[],7,FALSE)=1,"Discontinued","Current") -> Current | L30: =VLOOKUP(dynamic[productID],products[],IF(YEAR(dynamic[orderDate])=2022,8,IF(YEAR(dynamic[orderDate])=2023,9,IF(YEAR(dynamic[orderDate])=2024,10,NA))),FALSE) -> 7.4302728 | M30: 10.4 | N30: =(dynamic[orderPrice]-dynamic[productCost])/dynamic[productCost] -> 0.39967942 | O30: 15 | P30: 0 | Q30: =dynamic[orderPrice]*dynamic[orderQuantity] -> 156 | R30: =dynamic[orderTotal]*(1-dynamic[discountApllied]) -> 156 | S30: =dynamic[revenue]-(dynamic[productCost]*dynamic[orderQuantity]) -> 44.545907 | T30: =IFERROR(dynamic[profit]/dynamic[revenue], 0) -> 0.28555069
A31: 10258 | B31: ERNSH | C31: =VLOOKUP(dynamic[customerID],customers[],2,FALSE) -> Ernst Handel | D31: 44759 | E31: =IFERROR(__xludf.DUMMYFUNCTION("COUNTUNIQUEIFS($A$2:$A31,$B$2:$B31,B31)"),1.0) -> 1 | F31: =IF(E31=1, 0, D31 - INDEX($D$2:$D31,MATCH(1, ($B$2:$B31=B31)*($E$2:$E31=E31-1), 0))) -> 0 | G31: =IF(MINIFS(dynamic[orderDate], dynamic[customerID], B31) >= DATE(2024,4,30)-120, "New", IF(MAXIFS(dynamic[orderCount], dynamic[customerID], B31)<=2, IF((DATE(2024,4,30) - MAXIFS(dynamic[orderDate], dynamic[customerID], B31)) > 180, "Non-Returning", "Dormant"), IF(AND(MAX(dynamic[sinceLastOrder]) > 365, (DATE(2024,4,30) - MAXIFS(dynamic[orderDate], dynamic[customerID], B31)) > 180), "Dormant", "Regular"))) -> Regular | H31: 2 | I31: =VLOOKUP(dynamic[productID],products[],2,FALSE) -> Chang | J31: =VLOOKUP(dynamic[productID],products[],12,FALSE) -> Beverages | K31: =IF(VLOOKUP(dynamic[productID],products[],7,FALSE)=1,"Discontinued","Current") -> Current | L31: =VLOOKUP(dynamic[productID],products[],IF(YEAR(dynamic[orderDate])=2022,8,IF(YEAR(dynamic[orderDate])=2023,9,IF(YEAR(dynamic[orderDate])=2024,10,NA))),FALSE) -> 9.7687469 | M31: 15.2 | N31: =(dynamic[orderPrice]-dynamic[productCost])/dynamic[productCost] -> 0.55598258 | O31: 50 | P31: 0.2 | Q31: =dynamic[orderPrice]*dynamic[orderQuantity] -> 760 | R31: =dynamic[orderTotal]*(1-dynamic[discountApllied]) -> 608 | S31: =dynamic[revenue]-(dynamic[productCost]*dynamic[orderQuantity]) -> 119.56266 | T31: =IFERROR(dynamic[profit]/dynamic[revenue], 0) -> 0.19664911
A32: 10258 | B32: ERNSH | C32: =VLOOKUP(dynamic[customerID],customers[],2,FALSE) -> Ernst Handel | D32: 44759 | E32: =IFERROR(__xludf.DUMMYFUNCTION("COUNTUNIQUEIFS($A$2:$A32,$B$2:$B32,B32)"),1.0) -> 1 | F32: =IF(E32=1, 0, D32 - INDEX($D$2:$D32,MATCH(1, ($B$2:$B32=B32)*($E$2:$E32=E32-1), 0))) -> 0 | G32: =IF(MINIFS(dynamic[orderDate], dynamic[customerID], B32) >= DATE(2024,4,30)-120, "New", IF(MAXIFS(dynamic[orderCount], dynamic[customerID], B32)<=2, IF((DATE(2024,4,30) - MAXIFS(dynamic[orderDate], dynamic[customerID], B32)) > 180, "Non-Returning", "Dormant"), IF(AND(MAX(dynamic[sinceLastOrder]) > 365, (DATE(2024,4,30) - MAXIFS(dynamic[orderDate], dynamic[customerID], B32)) > 180), "Dormant", "Regular"))) -> Regular | H32: 5 | I32: =VLOOKUP(dynamic[productID],products[],2,FALSE) -> Chef Anton's Gumbo Mix | J32: =VLOOKUP(dynamic[productID],products[],12,FALSE) -> Condiments | K32: =IF(VLOOKUP(dynamic[productID],products[],7,FALSE)=1,"Discontinued","Current") -> Discontinued | L32: =VLOOKUP(dynamic[productID],products[],IF(YEAR(dynamic[orderDate])=2022,8,IF(YEAR(dynamic[orderDate])=2023,9,IF(YEAR(dynamic[orderDate])=2024,10,NA))),FALSE) -> 10.905906 | M32: 17 | N32: =(dynamic[orderPrice]-dynamic[productCost])/dynamic[productCost] -> 0.55878844 | O32: 65 | P32: 0.2 | Q32: =dynamic[orderPrice]*dynamic[orderQuantity] -> 1105 | R32: =dynamic[orderTotal]*(1-dynamic[discountApllied]) -> 884 | S32: =dynamic[revenue]-(dynamic[productCost]*dynamic[orderQuantity]) -> 175.11612 | T32: =IFERROR(dynamic[profit]/dynamic[revenue], 0) -> 0.19809515
A33: 10258 | B33: ERNSH | C33: =VLOOKUP(dynamic[customerID],customers[],2,FALSE) -> Ernst Handel | D33: 44759 | E33: =IFERROR(__xludf.DUMMYFUNCTION("COUNTUNIQUEIFS($A$2:$A33,$B$2:$B33,B33)"),1.0) -> 1 | F33: =IF(E33=1, 0, D33 - INDEX($D$2:$D33,MATCH(1, ($B$2:$B33=B33)*($E$2:$E33=E33-1), 0))) -> 0 | G33: =IF(MINIFS(dynamic[orderDate], dynamic[customerID], B33) >= DATE(2024,4,30)-120, "New", IF(MAXIFS(dynamic[orderCount], dynamic[customerID], B33)<=2, IF((DATE(2024,4,30) - MAXIFS(dynamic[orderDate], dynamic[customerID], B33)) > 180, "Non-Returning", "Dormant"), IF(AND(MAX(dynamic[sinceLastOrder]) > 365, (DATE(2024,4,30) - MAXIFS(dynamic[orderDate], dynamic[customerID], B33)) > 180), "Dormant", "Regular"))) -> Regular | H33: 32 | I33: =VLOOKUP(dynamic[productID],products[],2,FALSE) -> Mascarpone Fabioli | J33: =VLOOKUP(dynamic[productID],products[],12,FALSE) -> Dairy Products | K33: =IF(VLOOKUP(dynamic[productID],products[],7,FALSE)=1,"Discontinued","Current") -> Current | L33: =VLOOKUP(dynamic[productID],products[],IF(YEAR(dynamic[orderDate])=2022,8,IF(YEAR(dynamic[orderDate])=2023,9,IF(YEAR(dynamic[orderDate])=2024,10,NA))),FALSE) -> 14.654925 | M33: 25.6 | N33: =(dynamic[orderPrice]-dynamic[productCost])/dynamic[productCost] -> 0.74685306 | O33: 6 | P33: 0.2 | Q33: =dynamic[orderPrice]*dynamic[orderQuantity] -> 153.6 | R33: =dynamic[orderTotal]*(1-dynamic[discountApllied]) -> 122.88 | S33: =dynamic[revenue]-(dynamic[productCost]*dynamic[orderQuantity]) -> 34.950452 | T33: =IFERROR(dynamic[profit]/dynamic[revenue], 0) -> 0.28442751
A34: 10259 | B34: CENTC | C34: =VLOOKUP(dynamic[customerID],customers[],2,FALSE) -> Centro comercial Moctezuma | D34: 44760 | E34: =IFERROR(__xludf.DUMMYFUNCTION("COUNTUNIQUEIFS($A$2:$A34,$B$2:$B34,B34)"),1.0) -> 1 | F34: =IF(E34=1, 0, D34 - INDEX($D$2:$D34,MATCH(1, ($B$2:$B34=B34)*($E$2:$E34=E34-1), 0))) -> 0 | G34: =IF(MINIFS(dynamic[orderDate], dynamic[customerID], B34) >= DATE(2024,4,30)-120, "New", IF(MAXIFS(dynamic[orderCount], dynamic[customerID], B34)<=2, IF((DATE(2024,4,30) - MAXIFS(dynamic[orderDate], dynamic[customerID], B34)) > 180, "Non-Returning", "Dormant"), IF(AND(MAX(dynamic[sinceLastOrder]) > 365, (DATE(2024,4,30) - MAXIFS(dynamic[orderDate], dynamic[customerID], B34)) > 180), "Dormant", "Regular"))) -> Non-Returning | H34: 21 | I34: =VLOOKUP(dynamic[productID],products[],2,FALSE) -> Sir Rodney's Scones | J34: =VLOOKUP(dynamic[productID],products[],12,FALSE) -> Confections | K34: =IF(VLOOKUP(dynamic[productID],products[],7,FALSE)=1,"Discontinued","Current") -> Current | L34: =VLOOKUP(dynamic[productID],products[],IF(YEAR(dynamic[orderDate])=2022,8,IF(YEAR(dynamic[orderDate])=2023,9,IF(YEAR(dynamic[orderDate])=2024,10,NA))),FALSE) -> 5.7738365 | M34: 8 | N34: =(dynamic[orderPrice]-dynamic[productCost])/dynamic[productCost] -> 0.38556055 | O34: 10 | P34: 0 | Q34: =dynamic[orderPrice]*dynamic[orderQuantity] -> 80 | R34: =dynamic[orderTotal]*(1-dynamic[discountApllied]) -> 80 | S34: =dynamic[revenue]-(dynamic[productCost]*dynamic[orderQuantity]) -> 22.261635 | T34: =IFERROR(dynamic[profit]/dynamic[revenue], 0) -> 0.27827044
A35: 10259 | B35: CENTC | C35: =VLOOKUP(dynamic[customerID],customers[],2,FALSE) -> Centro comercial Moctezuma | D35: 44760 | E35: =IFERROR(__xludf.DUMMYFUNCTION("COUNTUNIQUEIFS($A$2:$A35,$B$2:$B35,B35)"),1.0) -> 1 | F35: =IF(E35=1, 0, D35 - INDEX($D$2:$D35,MATCH(1, ($B$2:$B35=B35)*($E$2:$E35=E35-1), 0))) -> 0 | G35: =IF(MINIFS(dynamic[orderDate], dynamic[customerID], B35) >= DATE(2024,4,30)-120, "New", IF(MAXIFS(dynamic[orderCount], dynamic[customerID], B35)<=2, IF((DATE(2024,4,30) - MAXIFS(dynamic[orderDate], dynamic[customerID], B35)) > 180, "Non-Returning", "Dormant"), IF(AND(MAX(dynamic[sinceLastOrder]) > 365, (DATE(2024,4,30) - MAXIFS(dynamic[orderDate], dynamic[customerID], B35)) > 180), "Dormant", "Regular"))) -> Non-Returning | H35: 37 | I35: =VLOOKUP(dynamic[productID],products[],2,FALSE) -> Gravad lax | J35: =VLOOKUP(dynamic[productID],products[],12,FALSE) -> Seafood | K35: =IF(VLOOKUP(dynamic[productID],products[],7,FALSE)=1,"Discontinued","Current") -> Current | L35: =VLOOKUP(dynamic[productID],products[],IF(YEAR(dynamic[orderDate])=2022,8,IF(YEAR(dynamic[orderDate])=2023,9,IF(YEAR(dynamic[orderDate])=2024,10,NA))),FALSE) -> 14.59373 | M35: 20.8 | N35: =(dynamic[orderPrice]-dynamic[productCost])/dynamic[productCost] -> 0.42526966 | O35: 1 | P35: 0 | Q35: =dynamic[orderPrice]*dynamic[orderQuantity] -> 20.8 | R35: =dynamic[orderTotal]*(1-dynamic[discountApllied]) -> 20.8 | S35: =dynamic[revenue]-(dynamic[productCost]*dynamic[orderQuantity]) -> 6.2062705 | T35: =IFERROR(dynamic[profit]/dynamic[revenue], 0) -> 0.29837839
A36: 10260 | B36: OTTIK | C36: =VLOOKUP(dynamic[customerID],customers[],2,FALSE) -> Ottilies Käseladen | D36: 44761 | E36: =IFERROR(__xludf.DUMMYFUNCTION("COUNTUNIQUEIFS($A$2:$A36,$B$2:$B36,B36)"),1.0) -> 1 | F36: =IF(E36=1, 0, D36 - INDEX($D$2:$D36,MATCH(1, ($B$2:$B36=B36)*($E$2:$E36=E36-1), 0))) -> 0 | G36: =IF(MINIFS(dynamic[orderDate], dynamic[customerID], B36) >= DATE(2024,4,30)-120, "New", IF(MAXIFS(dynamic[orderCount], dynamic[customerID], B36)<=2, IF((DATE(2024,4,30) - MAXIFS(dynamic[orderDate], dynamic[customerID], B36)) > 180, "Non-Returning", "Dormant"), IF(AND(MAX(dynamic[sinceLastOrder]) > 365, (DATE(2024,4,30) - MAXIFS(dynamic[orderDate], dynamic[customerID], B36)) > 180), "Dormant", "Regular"))) -> Regular | H36: 41 | I36: =VLOOKUP(dynamic[productID],products[],2,FALSE) -> Jack's New England Clam Chowder | J36: =VLOOKUP(dynamic[productID],products[],12,FALSE) -> Seafood | K36: =IF(VLOOKUP(dynamic[productID],products[],7,FALSE)=1,"Discontinued","Current") -> Current | L36: =VLOOKUP(dynamic[productID],products[],IF(YEAR(dynamic[orderDate])=2022,8,IF(YEAR(dynamic[orderDate])=2023,9,IF(YEAR(dynamic[orderDate])=2024,10,NA))),FALSE) -> 5.1701987 | M36: 7.7 | N36: =(dynamic[orderPrice]-dynamic[productCost])/dynamic[productCost] -> 0.48930445 | O36: 16 | P36: 0.25 | Q36: =dynamic[orderPrice]*dynamic[orderQuantity] -> 123.2 | R36: =dynamic[orderTotal]*(1-dynamic[discountApllied]) -> 92.4 | S36: =dynamic[revenue]-(dynamic[productCost]*dynamic[orderQuantity]) -> 9.6768201 | T36: =IFERROR(dynamic[profit]/dynamic[revenue], 0) -> 0.10472749
A37: 10260 | B37: OTTIK | C37: =VLOOKUP(dynamic[customerID],customers[],2,FALSE) -> Ottilies Käseladen | D37: 44761 | E37: =IFERROR(__xludf.DUMMYFUNCTION("COUNTUNIQUEIFS($A$2:$A37,$B$2:$B37,B37)"),1.0) -> 1 | F37: =IF(E37=1, 0, D37 - INDEX($D$2:$D37,MATCH(1, ($B$2:$B37=B37)*($E$2:$E37=E37-1), 0))) -> 0 | G37: =IF(MINIFS(dynamic[orderDate], dynamic[customerID], B37) >= DATE(2024,4,30)-120, "New", IF(MAXIFS(dynamic[orderCount], dynamic[customerID], B37)<=2, IF((DATE(2024,4,30) - MAXIFS(dynamic[orderDate], dynamic[customerID], B37)) > 180, "Non-Returning", "Dormant"), IF(AND(MAX(dynamic[sinceLastOrder]) > 365, (DATE(2024,4,30) - MAXIFS(dynamic[orderDate], dynamic[customerID], B37)) > 180), "Dormant", "Regular"))) -> Regular | H37: 57 | I37: =VLOOKUP(dynamic[productID],products[],2,FALSE) -> Ravioli Angelo | J37: =VLOOKUP(dynamic[productID],products[],12,FALSE) -> Grains/Cereals | K37: =IF(VLOOKUP(dynamic[productID],products[],7,FALSE)=1,"Discontinued","Current") -> Current | L37: =VLOOKUP(dynamic[productID],products[],IF(YEAR(dynamic[orderDate])=2022,8,IF(YEAR(dynamic[orderDate])=2023,9,IF(YEAR(dynamic[orderDate])=2024,10,NA))),FALSE) -> 11.229508 | M37: 15.6 | N37: =(dynamic[orderPrice]-dynamic[productCost])/dynamic[productCost] -> 0.38919715 | O37: 50 | P37: 0 | Q37: =dynamic[orderPrice]*dynamic[orderQuantity] -> 780 | R37: =dynamic[orderTotal]*(1-dynamic[discountApllied]) -> 780 | S37: =dynamic[revenue]-(dynamic[productCost]*dynamic[orderQuantity]) -> 218.52462 | T37: =IFERROR(dynamic[profit]/dynamic[revenue], 0) -> 0.28015977
A38: 10260 | B38: OTTIK | C38: =VLOOKUP(dynamic[customerID],customers[],2,FALSE) -> Ottilies Käseladen | D38: 44761 | E38: =IFERROR(__xludf.DUMMYFUNCTION("COUNTUNIQUEIFS($A$2:$A38,$B$2:$B38,B38)"),1.0) -> 1 | F38: =IF(E38=1, 0, D38 - INDEX($D$2:$D38,MATCH(1, ($B$2:$B38=B38)*($E$2:$E38=E38-1), 0))) -> 0 | G38: =IF(MINIFS(dynamic[orderDate], dynamic[customerID], B38) >= DATE(2024,4,30)-120, "New", IF(MAXIFS(dynamic[orderCount], dynamic[customerID], B38)<=2, IF((DATE(2024,4,30) - MAXIFS(dynamic[orderDate], dynamic[customerID], B38)) > 180, "Non-Returning", "Dormant"), IF(AND(MAX(dynamic[sinceLastOrder]) > 365, (DATE(2024,4,30) - MAXIFS(dynamic[orderDate], dynamic[customerID], B38)) > 180), "Dormant", "Regular"))) -> Regular | H38: 62 | I38: =VLOOKUP(dynamic[productID],products[],2,FALSE) -> Tarte au sucre | J38: =VLOOKUP(dynamic[productID],products[],12,FALSE) -> Confections | K38: =IF(VLOOKUP(dynamic[productID],products[],7,FALSE)=1,"Discontinued","Current") -> Current | L38: =VLOOKUP(dynamic[productID],products[],IF(YEAR(dynamic[orderDate])=2022,8,IF(YEAR(dynamic[orderDate])=2023,9,IF(YEAR(dynamic[orderDate])=2024,10,NA))),FALSE) -> 29.359633 | M38: 39.4 | N38: =(dynamic[orderPrice]-dynamic[productCost])/dynamic[productCost] -> 0.34197862 | O38: 15 | P38: 0.25 | Q38: =dynamic[orderPrice]*dynamic[orderQuantity] -> 591 | R38: =dynamic[orderTotal]*(1-dynamic[discountApllied]) -> 443.25 | S38: =dynamic[revenue]-(dynamic[productCost]*dynamic[orderQuantity]) -> 2.8555021 | T38: =IFERROR(dynamic[profit]/dynamic[revenue], 0) -> 0.0064421932
A39: 10260 | B39: OTTIK | C39: =VLOOKUP(dynamic[customerID],customers[],2,FALSE) -> Ottilies Käseladen | D39: 44761 | E39: =IFERROR(__xludf.DUMMYFUNCTION("COUNTUNIQUEIFS($A$2:$A39,$B$2:$B39,B39)"),1.0) -> 1 | F39: =IF(E39=1, 0, D39 - INDEX($D$2:$D39,MATCH(1, ($B$2:$B39=B39)*($E$2:$E39=E39-1), 0))) -> 0 | G39: =IF(MINIFS(dynamic[orderDate], dynamic[customerID], B39) >= DATE(2024,4,30)-120, "New", IF(MAXIFS(dynamic[orderCount], dynamic[customerID], B39)<=2, IF((DATE(2024,4,30) - MAXIFS(dynamic[orderDate], dynamic[customerID], B39)) > 180, "Non-Returning", "Dormant"), IF(AND(MAX(dynamic[sinceLastOrder]) > 365, (DATE(2024,4,30) - MAXIFS(dynamic[orderDate], dynamic[customerID], B39)) > 180), "Dormant", "Regular"))) -> Regular | H39: 70 | I39: =VLOOKUP(dynamic[productID],products[],2,FALSE) -> Outback Lager | J39: =VLOOKUP(dynamic[productID],products[],12,FALSE) -> Beverages | K39: =IF(VLOOKUP(dynamic[productID],products[],7,FALSE)=1,"Discontinued","Current") -> Current | L39: =VLOOKUP(dynamic[productID],products[],IF(YEAR(dynamic[orderDate])=2022,8,IF(YEAR(dynamic[orderDate])=2023,9,IF(YEAR(dynamic[orderDate])=2024,10,NA))),FALSE) -> 8.0375209 | M39: 12 | N39: =(dynamic[orderPrice]-dynamic[productCost])/dynamic[productCost] -> 0.49299766 | O39: 21 | P39: 0.25 | Q39: =dynamic[orderPrice]*dynamic[orderQuantity] -> 252 | R39: =dynamic[orderTotal]*(1-dynamic[discountApllied]) -> 189 | S39: =dynamic[revenue]-(dynamic[productCost]*dynamic[orderQuantity]) -> 20.21206 | T39: =IFERROR(dynamic[profit]/dynamic[revenue], 0) -> 0.10694212
A40: 10261 | B40: QUEDE | C40: =VLOOKUP(dynamic[customerID],customers[],2,FALSE) -> Que Delícia | D40: 44761 | E40: =IFERROR(__xludf.DUMMYFUNCTION("COUNTUNIQUEIFS($A$2:$A40,$B$2:$B40,B40)"),1.0) -> 1 | F40: =IF(E40=1, 0, D40 - INDEX($D$2:$D40,MATCH(1, ($B$2:$B40=B40)*($E$2:$E40=E40-1), 0))) -> 0 | G40: =IF(MINIFS(dynamic[orderDate], dynamic[customerID], B40) >= DATE(2024,4,30)-120, "New", IF(MAXIFS(dynamic[orderCount], dynamic[customerID], B40)<=2, IF((DATE(2024,4,30) - MAXIFS(dynamic[orderDate], dynamic[customerID], B40)) > 180, "Non-Returning", "Dormant"), IF(AND(MAX(dynamic[sinceLastOrder]) > 365, (DATE(2024,4,30) - MAXIFS(dynamic[orderDate], dynamic[customerID], B40)) > 180), "Dormant", "Regular"))) -> Regular | H40: 21 | I40: =VLOOKUP(dynamic[productID],products[],2,FALSE) -> Sir Rodney's Scones | J40: =VLOOKUP(dynamic[productID],products[],12,FALSE) -> Confections | K40: =IF(VLOOKUP(dynamic[productID],products[],7,FALSE)=1,"Discontinued","Current") -> Current | L40: =VLOOKUP(dynamic[productID],products[],IF(YEAR(dynamic[orderDate])=2022,8,IF(YEAR(dynamic[orderDate])=2023,9,IF(YEAR(dynamic[orderDate])=2024,10,NA))),FALSE) -> 5.7738365 | M40: 8 | N40: =(dynamic[orderPrice]-dynamic[productCost])/dynamic[productCost] -> 0.38556055 | O40: 20 | P40: 0 | Q40: =dynamic[orderPrice]*dynamic[orderQuantity] -> 160 | R40: =dynamic[orderTotal]*(1-dynamic[discountApllied]) -> 160 | S40: =dynamic[revenue]-(dynamic[productCost]*dynamic[orderQuantity]) -> 44.523271 | T40: =IFERROR(dynamic[profit]/dynamic[revenue], 0) -> 0.27827044
A41: 10261 | B41: QUEDE | C41: =VLOOKUP(dynamic[customerID],customers[],2,FALSE) -> Que Delícia | D41: 44761 | E41: =IFERROR(__xludf.DUMMYFUNCTION("COUNTUNIQUEIFS($A$2:$A41,$B$2:$B41,B41)"),1.0) -> 1 | F41: =IF(E41=1, 0, D41 - INDEX($D$2:$D41,MATCH(1, ($B$2:$B41=B41)*($E$2:$E41=E41-1), 0))) -> 0 | G41: =IF(MINIFS(dynamic[orderDate], dynamic[customerID], B41) >= DATE(2024,4,30)-120, "New", IF(MAXIFS(dynamic[orderCount], dynamic[customerID], B41)<=2, IF((DATE(2024,4,30) - MAXIFS(dynamic[orderDate], dynamic[customerID], B41)) > 180, "Non-Returning", "Dormant"), IF(AND(MAX(dynamic[sinceLastOrder]) > 365, (DATE(2024,4,30) - MAXIFS(dynamic[orderDate], dynamic[customerID], B41)) > 180), "Dormant", "Regular"))) -> Regular | H41: 35 | I41: =VLOOKUP(dynamic[productID],products[],2,FALSE) -> Cold Brew Nitro | J41: =VLOOKUP(dynamic[productID],products[],12,FALSE) -> Beverages | K41: =IF(VLOOKUP(dynamic[productID],products[],7,FALSE)=1,"Discontinued","Current") -> Current | L41: =VLOOKUP(dynamic[productID],products[],IF(YEAR(dynamic[orderDate])=2022,8,IF(YEAR(dynamic[orderDate])=2023,9,IF(YEAR(dynamic[orderDate])=2024,10,NA))),FALSE) -> 10.198691 | M41: 14.4 | N41: =(dynamic[orderPrice]-dynamic[productCost])/dynamic[productCost] -> 0.41194592 | O41: 20 | P41: 0 | Q41: =dynamic[orderPrice]*dynamic[orderQuantity] -> 288 | R41: =dynamic[orderTotal]*(1-dynamic[discountApllied]) -> 288 | S41: =dynamic[revenue]-(dynamic[productCost]*dynamic[orderQuantity]) -> 84.026182 | T41: =IFERROR(dynamic[profit]/dynamic[revenue], 0) -> 0.29175758
A42: 10262 | B42: RATTC | C42: =VLOOKUP(dynamic[customerID],customers[],2,FALSE) -> Rattlesnake Canyon Grocery | D42: 44764 | E42: =IFERROR(__xludf.DUMMYFUNCTION("COUNTUNIQUEIFS($A$2:$A42,$B$2:$B42,B42)"),1.0) -> 1 | F42: =IF(E42=1, 0, D42 - INDEX($D$2:$D42,MATCH(1, ($B$2:$B42=B42)*($E$2:$E42=E42-1), 0))) -> 0 | G42: =IF(MINIFS(dynamic[orderDate], dynamic[customerID], B42) >= DATE(2024,4,30)-120, "New", IF(MAXIFS(dynamic[orderCount], dynamic[customerID], B42)<=2, IF((DATE(2024,4,30) - MAXIFS(dynamic[orderDate], dynamic[customerID], B42)) > 180, "Non-Returning", "Dormant"), IF(AND(MAX(dynamic[sinceLastOrder]) > 365, (DATE(2024,4,30) - MAXIFS(dynamic[orderDate], dynamic[customerID], B42)) > 180), "Dormant", "Regular"))) -> Regular | H42: 5 | I42: =VLOOKUP(dynamic[productID],products[],2,FALSE) -> Chef Anton's Gumbo Mix | J42: =VLOOKUP(dynamic[productID],products[],12,FALSE) -> Condiments | K42: =IF(VLOOKUP(dynamic[productID],products[],7,FALSE)=1,"Discontinued","Current") -> Discontinued | L42: =VLOOKUP(dynamic[productID],products[],IF(YEAR(dynamic[orderDate])=2022,8,IF(YEAR(dynamic[orderDate])=2023,9,IF(YEAR(dynamic[orderDate])=2024,10,NA))),FALSE) -> 10.905906 | M42: 17 | N42: =(dynamic[orderPrice]-dynamic[productCost])/dynamic[productCost] -> 0.55878844 | O42: 12 | P42: 0.2 | Q42: =dynamic[orderPrice]*dynamic[orderQuantity] -> 204 | R42: =dynamic[orderTotal]*(1-dynamic[discountApllied]) -> 163.2 | S42: =dynamic[revenue]-(dynamic[productCost]*dynamic[orderQuantity]) -> 32.329129 | T42: =IFERROR(dynamic[profit]/dynamic[revenue], 0) -> 0.19809515
A43: 10262 | B43: RATTC | C43: =VLOOKUP(dynamic[customerID],customers[],2,FALSE) -> Rattlesnake Canyon Grocery | D43: 44764 | E43: =IFERROR(__xludf.DUMMYFUNCTION("COUNTUNIQUEIFS($A$2:$A43,$B$2:$B43,B43)"),1.0) -> 1 | F43: =IF(E43=1, 0, D43 - INDEX($D$2:$D43,MATCH(1, ($B$2:$B43=B43)*($E$2:$E43=E43-1), 0))) -> 0 | G43: =IF(MINIFS(dynamic[orderDate], dynamic[customerID], B43) >= DATE(2024,4,30)-120, "New", IF(MAXIFS(dynamic[orderCount], dynamic[customerID], B43)<=2, IF((DATE(2024,4,30) - MAXIFS(dynamic[orderDate], dynamic[customerID], B43)) > 180, "Non-Returning", "Dormant"), IF(AND(MAX(dynamic[sinceLastOrder]) > 365, (DATE(2024,4,30) - MAXIFS(dynamic[orderDate], dynamic[customerID], B43)) > 180), "Dormant", "Regular"))) -> Regular | H43: 7 | I43: =VLOOKUP(dynamic[productID],products[],2,FALSE) -> Uncle Bob's Organic Dried Pears | J43: =VLOOKUP(dynamic[productID],products[],12,FALSE) -> Produce | K43: =IF(VLOOKUP(dynamic[productID],products[],7,FALSE)=1,"Discontinued","Current") -> Current | L43: =VLOOKUP(dynamic[productID],products[],IF(YEAR(dynamic[orderDate])=2022,8,IF(YEAR(dynamic[orderDate])=2023,9,IF(YEAR(dynamic[orderDate])=2024,10,NA))),FALSE) -> 16.429974 | M43: 24 | N43: =(dynamic[orderPrice]-dynamic[productCost])/dynamic[productCost] -> 0.46074483 | O43: 15 | P43: 0 | Q43: =dynamic[orderPrice]*dynamic[orderQuantity] -> 360 | R43: =dynamic[orderTotal]*(1-dynamic[discountApllied]) -> 360 | S43: =dynamic[revenue]-(dynamic[productCost]*dynamic[orderQuantity]) -> 113.55039 | T43: =IFERROR(dynamic[profit]/dynamic[revenue], 0) -> 0.31541774
A44: 10262 | B44: RATTC | C44: =VLOOKUP(dynamic[customerID],customers[],2,FALSE) -> Rattlesnake Canyon Grocery | D44: 44764 | E44: =IFERROR(__xludf.DUMMYFUNCTION("COUNTUNIQUEIFS($A$2:$A44,$B$2:$B44,B44)"),1.0) -> 1 | F44: =IF(E44=1, 0, D44 - INDEX($D$2:$D44,MATCH(1, ($B$2:$B44=B44)*($E$2:$E44=E44-1), 0))) -> 0 | G44: =IF(MINIFS(dynamic[orderDate], dynamic[customerID], B44) >= DATE(2024,4,30)-120, "New", IF(MAXIFS(dynamic[orderCount], dynamic[customerID], B44)<=2, IF((DATE(2024,4,30) - MAXIFS(dynamic[orderDate], dynamic[customerID], B44)) > 180, "Non-Returning", "Dormant"), IF(AND(MAX(dynamic[sinceLastOrder]) > 365, (DATE(2024,4,30) - MAXIFS(dynamic[orderDate], dynamic[customerID], B44)) > 180), "Dormant", "Regular"))) -> Regular | H44: 56 | I44: =VLOOKUP(dynamic[productID],products[],2,FALSE) -> Gnocchi di nonna Alice | J44: =VLOOKUP(dynamic[productID],products[],12,FALSE) -> Grains/Cereals | K44: =IF(VLOOKUP(dynamic[productID],products[],7,FALSE)=1,"Discontinued","Current") -> Current | L44: =VLOOKUP(dynamic[productID],products[],IF(YEAR(dynamic[orderDate])=2022,8,IF(YEAR(dynamic[orderDate])=2023,9,IF(YEAR(dynamic[orderDate])=2024,10,NA))),FALSE) -> 21.504006 | M44: 30.4 | N44: =(dynamic[orderPrice]-dynamic[productCost])/dynamic[productCost] -> 0.41369011 | O44: 2 | P44: 0 | Q44: =dynamic[orderPrice]*dynamic[orderQuantity] -> 60.8 | R44: =dynamic[orderTotal]*(1-dynamic[discountApllied]) -> 60.8 | S44: =dynamic[revenue]-(dynamic[productCost]*dynamic[orderQuantity]) -> 17.791989 | T44: =IFERROR(dynamic[profit]/dynamic[revenue], 0) -> 0.29263139
A45: 10263 | B45: ERNSH | C45: =VLOOKUP(dynamic[customerID],customers[],2,FALSE) -> Ernst Handel | D45: 44765 | E45: =IFERROR(__xludf.DUMMYFUNCTION("COUNTUNIQUEIFS($A$2:$A45,$B$2:$B45,B45)"),2.0) -> 2 | F45: =IF(E45=1, 0, D45 - INDEX($D$2:$D45,MATCH(1, ($B$2:$B45=B45)*($E$2:$E45=E45-1), 0))) -> 6 | G45: =IF(MINIFS(dynamic[orderDate], dynamic[customerID], B45) >= DATE(2024,4,30)-120, "New", IF(MAXIFS(dynamic[orderCount], dynamic[customerID], B45)<=2, IF((DATE(2024,4,30) - MAXIFS(dynamic[orderDate], dynamic[customerID], B45)) > 180, "Non-Returning", "Dormant"), IF(AND(MAX(dynamic[sinceLastOrder]) > 365, (DATE(2024,4,30) - MAXIFS(dynamic[orderDate], dynamic[customerID], B45)) > 180), "Dormant", "Regular"))) -> Regular | H45: 16 | I45: =VLOOKUP(dynamic[productID],products[],2,FALSE) -> Pavlova | J45: =VLOOKUP(dynamic[productID],products[],12,FALSE) -> Confections | K45: =IF(VLOOKUP(dynamic[productID],products[],7,FALSE)=1,"Discontinued","Current") -> Current | L45: =VLOOKUP(dynamic[productID],products[],IF(YEAR(dynamic[orderDate])=2022,8,IF(YEAR(dynamic[orderDate])=2023,9,IF(YEAR(dynamic[orderDate])=2024,10,NA))),FALSE) -> 9.8065801 | M45: 13.9 | N45: =(dynamic[orderPrice]-dynamic[productCost])/dynamic[productCost] -> 0.41741564 | O45: 60 | P45: 0.25 | Q45: =dynamic[orderPrice]*dynamic[orderQuantity] -> 834 | R45: =dynamic[orderTotal]*(1-dynamic[discountApllied]) -> 625.5 | S45: =dynamic[revenue]-(dynamic[productCost]*dynamic[orderQuantity]) -> 37.105195 | T45: =IFERROR(dynamic[profit]/dynamic[revenue], 0) -> 0.059320856
A46: 10263 | B46: ERNSH | C46: =VLOOKUP(dynamic[customerID],customers[],2,FALSE) -> Ernst Handel | D46: 44765 | E46: =IFERROR(__xludf.DUMMYFUNCTION("COUNTUNIQUEIFS($A$2:$A46,$B$2:$B46,B46)"),2.0) -> 2 | F46: =IF(E46=1, 0, D46 - INDEX($D$2:$D46,MATCH(1, ($B$2:$B46=B46)*($E$2:$E46=E46-1), 0))) -> 6 | G46: =IF(MINIFS(dynamic[orderDate], dynamic[customerID], B46) >= DATE(2024,4,30)-120, "New", IF(MAXIFS(dynamic[orderCount], dynamic[customerID], B46)<=2, IF((DATE(2024,4,30) - MAXIFS(dynamic[orderDate], dynamic[customerID], B46)) > 180, "Non-Returning", "Dormant"), IF(AND(MAX(dynamic[sinceLastOrder]) > 365, (DATE(2024,4,30) - MAXIFS(dynamic[orderDate], dynamic[customerID], B46)) > 180), "Dormant", "Regular"))) -> Regular | H46: 24 | I46: =VLOOKUP(dynamic[productID],products[],2,FALSE) -> Brigadeiros Maravilhosos da Lilian | J46: =VLOOKUP(dynamic[productID],products[],12,FALSE) -> Confections | K46: =IF(VLOOKUP(dynamic[productID],products[],7,FALSE)=1,"Discontinued","Current") -> Discontinued | L46: =VLOOKUP(dynamic[productID],products[],IF(YEAR(dynamic[orderDate])=2022,8,IF(YEAR(dynamic[orderDate])=2023,9,IF(YEAR(dynamic[orderDate])=2024,10,NA))),FALSE) -> 2.6811725 | M46: 3.6 | N46: =(dynamic[orderPrice]-dynamic[productCost])/dynamic[productCost] -> 0.34269617 | O46: 28 | P46: 0 | Q46: =dynamic[orderPrice]*dynamic[orderQuantity] -> 100.8 | R46: =dynamic[orderTotal]*(1-dynamic[discountApllied]) -> 100.8 | S46: =dynamic[revenue]-(dynamic[productCost]*dynamic[orderQuantity]) -> 25.727171 | T46: =IFERROR(dynamic[profit]/dynamic[revenue], 0) -> 0.25522987
A47: 10263 | B47: ERNSH | C47: =VLOOKUP(dynamic[customerID],customers[],2,FALSE) -> Ernst Handel | D47: 44765 | E47: =IFERROR(__xludf.DUMMYFUNCTION("COUNTUNIQUEIFS($A$2:$A47,$B$2:$B47,B47)"),2.0) -> 2 | F47: =IF(E47=1, 0, D47 - INDEX($D$2:$D47,MATCH(1, ($B$2:$B47=B47)*($E$2:$E47=E47-1), 0))) -> 6 | G47: =IF(MINIFS(dynamic[orderDate], dynamic[customerID], B47) >= DATE(2024,4,30)-120, "New", IF(MAXIFS(dynamic[orderCount], dynamic[customerID], B47)<=2, IF((DATE(2024,4,30) - MAXIFS(dynamic[orderDate], dynamic[customerID], B47)) > 180, "Non-Returning", "Dormant"), IF(AND(MAX(dynamic[sinceLastOrder]) > 365, (DATE(2024,4,30) - MAXIFS(dynamic[orderDate], dynamic[customerID], B47)) > 180), "Dormant", "Regular"))) -> Regular | H47: 30 | I47: =VLOOKUP(dynamic[productID],products[],2,FALSE) -> Nord-Ost Matjeshering | J47: =VLOOKUP(dynamic[productID],products[],12,FALSE) -> Seafood | K47: =IF(VLOOKUP(dynamic[productID],products[],7,FALSE)=1,"Discontinued","Current") -> Current | L47: =VLOOKUP(dynamic[productID],products[],IF(YEAR(dynamic[orderDate])=2022,8,IF(YEAR(dynamic[orderDate])=2023,9,IF(YEAR(dynamic[orderDate])=2024,10,NA))),FALSE) -> 13.416569 | M47: 20.7 | N47: =(dynamic[orderPrice]-dynamic[productCost])/dynamic[productCost] -> 0.54286841 | O47: 60 | P47: 0.25 | Q47: =dynamic[orderPrice]*dynamic[orderQuantity] -> 1242 | R47: =dynamic[orderTotal]*(1-dynamic[discountApllied]) -> 931.5 | S47: =dynamic[revenue]-(dynamic[productCost]*dynamic[orderQuantity]) -> 126.50588 | T47: =IFERROR(dynamic[profit]/dynamic[revenue], 0) -> 0.13580878
A48: 10263 | B48: ERNSH | C48: =VLOOKUP(dynamic[customerID],customers[],2,FALSE) -> Ernst Handel | D48: 44765 | E48: =IFERROR(__xludf.DUMMYFUNCTION("COUNTUNIQUEIFS($A$2:$A48,$B$2:$B48,B48)"),2.0) -> 2 | F48: =IF(E48=1, 0, D48 - INDEX($D$2:$D48,MATCH(1, ($B$2:$B48=B48)*($E$2:$E48=E48-1), 0))) -> 6 | G48: =IF(MINIFS(dynamic[orderDate], dynamic[customerID], B48) >= DATE(2024,4,30)-120, "New", IF(MAXIFS(dynamic[orderCount], dynamic[customerID], B48)<=2, IF((DATE(2024,4,30) - MAXIFS(dynamic[orderDate], dynamic[customerID], B48)) > 180, "Non-Returning", "Dormant"), IF(AND(MAX(dynamic[sinceLastOrder]) > 365, (DATE(2024,4,30) - MAXIFS(dynamic[orderDate], dynamic[customerID], B48)) > 180), "Dormant", "Regular"))) -> Regular | H48: 74 | I48: =VLOOKUP(dynamic[productID],products[],2,FALSE) -> Longlife Tofu | J48: =VLOOKUP(dynamic[productID],products[],12,FALSE) -> Produce | K48: =IF(VLOOKUP(dynamic[productID],products[],7,FALSE)=1,"Discontinued","Current") -> Current | L48: =VLOOKUP(dynamic[productID],products[],IF(YEAR(dynamic[orderDate])=2022,8,IF(YEAR(dynamic[orderDate])=2023,9,IF(YEAR(dynamic[orderDate])=2024,10,NA))),FALSE) -> 5.6671301 | M48: 8 | N48: =(dynamic[orderPrice]-dynamic[productCost])/dynamic[productCost] -> 0.41164925 | O48: 36 | P48: 0.25 | Q48: =dynamic[orderPrice]*dynamic[orderQuantity] -> 288 | R48: =dynamic[orderTotal]*(1-dynamic[discountApllied]) -> 216 | S48: =dynamic[revenue]-(dynamic[productCost]*dynamic[orderQuantity]) -> 11.983316 | T48: =IFERROR(dynamic[profit]/dynamic[revenue], 0) -> 0.055478313
A49: 10264 | B49: FOLKO | C49: =VLOOKUP(dynamic[customerID],customers[],2,FALSE) -> Folk och fä HB | D49: 44766 | E49: =IFERROR(__xludf.DUMMYFUNCTION("COUNTUNIQUEIFS($A$2:$A49,$B$2:$B49,B49)"),1.0) -> 1 | F49: =IF(E49=1, 0, D49 - INDEX($D$2:$D49,MATCH(1, ($B$2:$B49=B49)*($E$2:$E49=E49-1), 0))) -> 0 | G49: =IF(MINIFS(dynamic[orderDate], dynamic[customerID], B49) >= DATE(2024,4,30)-120, "New", IF(MAXIFS(dynamic[orderCount], dynamic[customerID], B49)<=2, IF((DATE(2024,4,30) - MAXIFS(dynamic[orderDate], dynamic[customerID], B49)) > 180, "Non-Returning", "Dormant"), IF(AND(MAX(dynamic[sinceLastOrder]) > 365, (DATE(2024,4,30) - MAXIFS(dynamic[orderDate], dynamic[customerID], B49)) > 180), "Dormant", "Regular"))) -> Regular | H49: 2 | I49: =VLOOKUP(dynamic[productID],products[],2,FALSE) -> Chang | J49: =VLOOKUP(dynamic[productID],products[],12,FALSE) -> Beverages | K49: =IF(VLOOKUP(dynamic[productID],products[],7,FALSE)=1,"Discontinued","Current") -> Current | L49: =VLOOKUP(dynamic[productID],products[],IF(YEAR(dynamic[orderDate])=2022,8,IF(YEAR(dynamic[orderDate])=2023,9,IF(YEAR(dynamic[orderDate])=2024,10,NA))),FALSE) -> 9.7687469 | M49: 15.2 | N49: =(dynamic[orderPrice]-dynamic[productCost])/dynamic[productCost] -> 0.55598258 | O49: 35 | P49: 0 | Q49: =dynamic[orderPrice]*dynamic[orderQuantity] -> 532 | R49: =dynamic[orderTotal]*(1-dynamic[discountApllied]) -> 532 | S49: =dynamic[revenue]-(dynamic[productCost]*dynamic[orderQuantity]) -> 190.09386 | T49: =IFERROR(dynamic[profit]/dynamic[revenue], 0) -> 0.35731928
A50: 10264 | B50: FOLKO | C50: =VLOOKUP(dynamic[customerID],customers[],2,FALSE) -> Folk och fä HB | D50: 44766 | E50: =IFERROR(__xludf.DUMMYFUNCTION("COUNTUNIQUEIFS($A$2:$A50,$B$2:$B50,B50)"),1.0) -> 1 | F50: =IF(E50=1, 0, D50 - INDEX($D$2:$D50,MATCH(1, ($B$2:$B50=B50)*($E$2:$E50=E50-1), 0))) -> 0 | G50: =IF(MINIFS(dynamic[orderDate], dynamic[customerID], B50) >= DATE(2024,4,30)-120, "New", IF(MAXIFS(dynamic[orderCount], dynamic[customerID], B50)<=2, IF((DATE(2024,4,30) - MAXIFS(dynamic[orderDate], dynamic[customerID], B50)) > 180, "Non-Returning", "Dormant"), IF(AND(MAX(dynamic[sinceLastOrder]) > 365, (DATE(2024,4,30) - MAXIFS(dynamic[orderDate], dynamic[customerID], B50)) > 180), "Dormant", "Regular"))) -> Regular | H50: 41 | I50: =VLOOKUP(dynamic[productID],products[],2,FALSE) -> Jack's New England Clam Chowder | J50: =VLOOKUP(dynamic[productID],products[],12,FALSE) -> Seafood | K50: =IF(VLOOKUP(dynamic[productID],products[],7,FALSE)=1,"Discontinued","Current") -> Current | L50: =VLOOKUP(dynamic[productID],products[],IF(YEAR(dynamic[orderDate])=2022,8,IF(YEAR(dynamic[orderDate])=2023,9,IF(YEAR(dynamic[orderDate])=2024,10,NA))),FALSE) -> 5.1701987 | M50: 7.7 | N50: =(dynamic[orderPrice]-dynamic[productCost])/dynamic[productCost] -> 0.48930445 | O50: 25 | P50: 0.15 | Q50: =dynamic[orderPrice]*dynamic[orderQuantity] -> 192.5 | R50: =dynamic[orderTotal]*(1-dynamic[discountApllied]) -> 163.625 | S50: =dynamic[revenue]-(dynamic[productCost]*dynamic[orderQuantity]) -> 34.370031 | T50: =IFERROR(dynamic[profit]/dynamic[revenue], 0) -> 0.21005367
A51: 10265 | B51: BLONP | C51: =VLOOKUP(dynamic[customerID],customers[],2,FALSE) -> Blondesddsl père et fils | D51: 44767 | E51: =IFERROR(__xludf.DUMMYFUNCTION("COUNTUNIQUEIFS($A$2:$A51,$B$2:$B51,B51)"),1.0) -> 1 | F51: =IF(E51=1, 0, D51 - INDEX($D$2:$D51,MATCH(1, ($B$2:$B51=B51)*($E$2:$E51=E51-1), 0))) -> 0 | G51: =IF(MINIFS(dynamic[orderDate], dynamic[customerID], B51) >= DATE(2024,4,30)-120, "New", IF(MAXIFS(dynamic[orderCount], dynamic[customerID], B51)<=2, IF((DATE(2024,4,30) - MAXIFS(dynamic[orderDate], dynamic[customerID], B51)) > 180, "Non-Returning", "Dormant"), IF(AND(MAX(dynamic[sinceLastOrder]) > 365, (DATE(2024,4,30) - MAXIFS(dynamic[orderDate], dynamic[customerID], B51)) > 180), "Dormant", "Regular"))) -> Regular | H51: 17 | I51: =VLOOKUP(dynamic[productID],products[],2,FALSE) -> Alice Mutton | J51: =VLOOKUP(dynamic[productID],products[],12,FALSE) -> Meat/Poultry | K51: =IF(VLOOKUP(dynamic[productID],products[],7,FALSE)=1,"Discontinued","Current") -> Discontinued | L51: =VLOOKUP(dynamic[productID],products[],IF(YEAR(dynamic[orderDate])=2022,8,IF(YEAR(dynamic[orderDate])=2023,9,IF(YEAR(dynamic[orderDate])=2024,10,NA))),FALSE) -> 21.253774 | M51: 31.2 | N51: =(dynamic[orderPrice]-dynamic[productCost])/dynamic[productCost] -> 0.46797458 | O51: 30 | P51: 0 | Q51: =dynamic[orderPrice]*dynamic[orderQuantity] -> 936 | R51: =dynamic[orderTotal]*(1-dynamic[discountApllied]) -> 936 | S51: =dynamic[revenue]-(dynamic[productCost]*dynamic[orderQuantity]) -> 298.38678 | T51: =IFERROR(dynamic[profit]/dynamic[revenue], 0) -> 0.31878929
A52: 10265 | B52: BLONP | C52: =VLOOKUP(dynamic[customerID],customers[],2,FALSE) -> Blondesddsl père et fils | D52: 44767 | E52: =IFERROR(__xludf.DUMMYFUNCTION("COUNTUNIQUEIFS($A$2:$A52,$B$2:$B52,B52)"),1.0) -> 1 | F52: =IF(E52=1, 0, D52 - INDEX($D$2:$D52,MATCH(1, ($B$2:$B52=B52)*($E$2:$E52=E52-1), 0))) -> 0 | G52: =IF(MINIFS(dynamic[orderDate], dynamic[customerID], B52) >= DATE(2024,4,30)-120, "New", IF(MAXIFS(dynamic[orderCount], dynamic[customerID], B52)<=2, IF((DATE(2024,4,30) - MAXIFS(dynamic[orderDate], dynamic[customerID], B52)) > 180, "Non-Returning", "Dormant"), IF(AND(MAX(dynamic[sinceLastOrder]) > 365, (DATE(2024,4,30) - MAXIFS(dynamic[orderDate], dynamic[customerID], B52)) > 180), "Dormant", "Regular"))) -> Regular | H52: 70 | I52: =VLOOKUP(dynamic[productID],products[],2,FALSE) -> Outback Lager | J52: =VLOOKUP(dynamic[productID],products[],12,FALSE) -> Beverages | K52: =IF(VLOOKUP(dynamic[productID],products[],7,FALSE)=1,"Discontinued","Current") -> Current | L52: =VLOOKUP(dynamic[productID],products[],IF(YEAR(dynamic[orderDate])=2022,8,IF(YEAR(dynamic[orderDate])=2023,9,IF(YEAR(dynamic[orderDate])=2024,10,NA))),FALSE) -> 8.0375209 | M52: 12 | N52: =(dynamic[orderPrice]-dynamic[productCost])/dynamic[productCost] -> 0.49299766 | O52: 20 | P52: 0 | Q52: =dynamic[orderPrice]*dynamic[orderQuantity] -> 240 | R52: =dynamic[orderTotal]*(1-dynamic[discountApllied]) -> 240 | S52: =dynamic[revenue]-(dynamic[productCost]*dynamic[orderQuantity]) -> 79.249581 | T52: =IFERROR(dynamic[profit]/dynamic[revenue], 0) -> 0.33020659
A53: 10266 | B53: WARTH | C53: =VLOOKUP(dynamic[customerID],customers[],2,FALSE) -> Wartian Herkku | D53: 44768 | E53: =IFERROR(__xludf.DUMMYFUNCTION("COUNTUNIQUEIFS($A$2:$A53,$B$2:$B53,B53)"),1.0) -> 1 | F53: =IF(E53=1, 0, D53 - INDEX($D$2:$D53,MATCH(1, ($B$2:$B53=B53)*($E$2:$E53=E53-1), 0))) -> 0 | G53: =IF(MINIFS(dynamic[orderDate], dynamic[customerID], B53) >= DATE(2024,4,30)-120, "New", IF(MAXIFS(dynamic[orderCount], dynamic[customerID], B53)<=2, IF((DATE(2024,4,30) - MAXIFS(dynamic[orderDate], dynamic[customerID], B53)) > 180, "Non-Returning", "Dormant"), IF(AND(MAX(dynamic[sinceLastOrder]) > 365, (DATE(2024,4,30) - MAXIFS(dynamic[orderDate], dynamic[customerID], B53)) > 180), "Dormant", "Regular"))) -> Regular | H53: 12 | I53: =VLOOKUP(dynamic[productID],products[],2,FALSE) -> Queso Manchego La Pastora | J53: =VLOOKUP(dynamic[productID],products[],12,FALSE) -> Dairy Products | K53: =IF(VLOOKUP(dynamic[productID],products[],7,FALSE)=1,"Discontinued","Current") -> Current | L53: =VLOOKUP(dynamic[productID],products[],IF(YEAR(dynamic[orderDate])=2022,8,IF(YEAR(dynamic[orderDate])=2023,9,IF(YEAR(dynamic[orderDate])=2024,10,NA))),FALSE) -> 20.012451 | M53: 30.4 | N53: =(dynamic[orderPrice]-dynamic[productCost])/dynamic[productCost] -> 0.51905431 | O53: 12 | P53: 0.05 | Q53: =dynamic[orderPrice]*dynamic[orderQuantity] -> 364.8 | R53: =dynamic[orderTotal]*(1-dynamic[discountApllied]) -> 346.56 | S53: =dynamic[revenue]-(dynamic[productCost]*dynamic[orderQuantity]) -> 106.41059 | T53: =IFERROR(dynamic[profit]/dynamic[revenue], 0) -> 0.30704809
A54: 10267 | B54: FRANK | C54: =VLOOKUP(dynamic[customerID],customers[],2,FALSE) -> Frankenversand | D54: 44771 | E54: =IFERROR(__xludf.DUMMYFUNCTION("COUNTUNIQUEIFS($A$2:$A54,$B$2:$B54,B54)"),1.0) -> 1 | F54: =IF(E54=1, 0, D54 - INDEX($D$2:$D54,MATCH(1, ($B$2:$B54=B54)*($E$2:$E54=E54-1), 0))) -> 0 | G54: =IF(MINIFS(dynamic[orderDate], dynamic[customerID], B54) >= DATE(2024,4,30)-120, "New", IF(MAXIFS(dynamic[orderCount], dynamic[customerID], B54)<=2, IF((DATE(2024,4,30) - MAXIFS(dynamic[orderDate], dynamic[customerID], B54)) > 180, "Non-Returning", "Dormant"), IF(AND(MAX(dynamic[sinceLastOrder]) > 365, (DATE(2024,4,30) - MAXIFS(dynamic[orderDate], dynamic[customerID], B54)) > 180), "Dormant", "Regular"))) -> Regular | H54: 40 | I54: =VLOOKUP(dynamic[productID],products[],2,FALSE) -> Boston Crab Meat | J54: =VLOOKUP(dynamic[productID],products[],12,FALSE) -> Seafood | K54: =IF(VLOOKUP(dynamic[productID],products[],7,FALSE)=1,"Discontinued","Current") -> Current | L54: =VLOOKUP(dynamic[productID],products[],IF(YEAR(dynamic[orderDate])=2022,8,IF(YEAR(dynamic[orderDate])=2023,9,IF(YEAR(dynamic[orderDate])=2024,10,NA))),FALSE) -> 9.6806491 | M54: 14.7 | N54: =(dynamic[orderPrice]-dynamic[productCost])/dynamic[productCost] -> 0.51849322 | O54: 50 | P54: 0 | Q54: =dynamic[orderPrice]*dynamic[orderQuantity] -> 735 | R54: =dynamic[orderTotal]*(1-dynamic[discountApllied]) -> 735 | S54: =dynamic[revenue]-(dynamic[productCost]*dynamic[orderQuantity]) -> 250.96754 | T54: =IFERROR(dynamic[profit]/dynamic[revenue], 0) -> 0.34145244
A55: 10267 | B55: FRANK | C55: =VLOOKUP(dynamic[customerID],customers[],2,FALSE) -> Frankenversand | D55: 44771 | E55: =IFERROR(__xludf.DUMMYFUNCTION("COUNTUNIQUEIFS($A$2:$A55,$B$2:$B55,B55)"),1.0) -> 1 | F55: =IF(E55=1, 0, D55 - INDEX($D$2:$D55,MATCH(1, ($B$2:$B55=B55)*($E$2:$E55=E55-1), 0))) -> 0 | G55: =IF(MINIFS(dynamic[orderDate], dynamic[customerID], B55) >= DATE(2024,4,30)-120, "New", IF(MAXIFS(dynamic[orderCount], dynamic[customerID], B55)<=2, IF((DATE(2024,4,30) - MAXIFS(dynamic[orderDate], dynamic[customerID], B55)) > 180, "Non-Returning", "Dormant"), IF(AND(MAX(dynamic[sinceLastOrder]) > 365, (DATE(2024,4,30) - MAXIFS(dynamic[orderDate], dynamic[customerID], B55)) > 180), "Dormant", "Regular"))) -> Regular | H55: 59 | I55: =VLOOKUP(dynamic[productID],products[],2,FALSE) -> Raclette Courdavault | J55: =VLOOKUP(dynamic[productID],products[],12,FALSE) -> Dairy Products | K55: =IF(VLOOKUP(dynamic[productID],products[],7,FALSE)=1,"Discontinued","Current") -> Current | L55: =VLOOKUP(dynamic[productID],products[],IF(YEAR(dynamic[orderDate])=2022,8,IF(YEAR(dynamic[orderDate])=2023,9,IF(YEAR(dynamic[orderDate])=2024,10,NA))),FALSE) -> 29.20352 | M55: 44 | N55: =(dynamic[orderPrice]-dynamic[productCost])/dynamic[productCost] -> 0.50666771 | O55: 70 | P55: 0.15 | Q55: =dynamic[orderPrice]*dynamic[orderQuantity] -> 3080 | R55: =dynamic[orderTotal]*(1-dynamic[discountApllied]) -> 2618 | S55: =dynamic[revenue]-(dynamic[productCost]*dynamic[orderQuantity]) -> 573.75363 | T55: =IFERROR(dynamic[profit]/dynamic[revenue], 0) -> 0.21915723
A56: 10267 | B56: FRANK | C56: =VLOOKUP(dynamic[customerID],customers[],2,FALSE) -> Frankenversand | D56: 44771 | E56: =IFERROR(__xludf.DUMMYFUNCTION("COUNTUNIQUEIFS($A$2:$A56,$B$2:$B56,B56)"),1.0) -> 1 | F56: =IF(E56=1, 0, D56 - INDEX($D$2:$D56,MATCH(1, ($B$2:$B56=B56)*($E$2:$E56=E56-1), 0))) -> 0 | G56: =IF(MINIFS(dynamic[orderDate], dynamic[customerID], B56) >= DATE(2024,4,30)-120, "New", IF(MAXIFS(dynamic[orderCount], dynamic[customerID], B56)<=2, IF((DATE(2024,4,30) - MAXIFS(dynamic[orderDate], dynamic[customerID], B56)) > 180, "Non-Returning", "Dormant"), IF(AND(MAX(dynamic[sinceLastOrder]) > 365, (DATE(2024,4,30) - MAXIFS(dynamic[orderDate], dynamic[customerID], B56)) > 180), "Dormant", "Regular"))) -> Regular | H56: 76 | I56: =VLOOKUP(dynamic[productID],products[],2,FALSE) -> Lakkalikööri | J56: =VLOOKUP(dynamic[productID],products[],12,FALSE) -> Beverages | K56: =IF(VLOOKUP(dynamic[productID],products[],7,FALSE)=1,"Discontinued","Current") -> Current | L56: =VLOOKUP(dynamic[productID],products[],IF(YEAR(dynamic[orderDate])=2022,8,IF(YEAR(dynamic[orderDate])=2023,9,IF(YEAR(dynamic[orderDate])=2024,10,NA))),FALSE) -> 10.196093 | M56: 14.4 | N56: =(dynamic[orderPrice]-dynamic[productCost])/dynamic[productCost] -> 0.41230574 | O56: 15 | P56: 0.15 | Q56: =dynamic[orderPrice]*dynamic[orderQuantity] -> 216 | R56: =dynamic[orderTotal]*(1-dynamic[discountApllied]) -> 183.6 | S56: =dynamic[revenue]-(dynamic[productCost]*dynamic[orderQuantity]) -> 30.658612 | T56: =IFERROR(dynamic[profit]/dynamic[revenue], 0) -> 0.1669859
A57: 10268 | B57: GROSR | C57: =VLOOKUP(dynamic[customerID],customers[],2,FALSE) -> GROSELLA-Restaurante | D57: 44772 | E57: =IFERROR(__xludf.DUMMYFUNCTION("COUNTUNIQUEIFS($A$2:$A57,$B$2:$B57,B57)"),1.0) -> 1 | F57: =IF(E57=1, 0, D57 - INDEX($D$2:$D57,MATCH(1, ($B$2:$B57=B57)*($E$2:$E57=E57-1), 0))) -> 0 | G57: =IF(MINIFS(dynamic[orderDate], dynamic[customerID], B57) >= DATE(2024,4,30)-120, "New", IF(MAXIFS(dynamic[orderCount], dynamic[customerID], B57)<=2, IF((DATE(2024,4,30) - MAXIFS(dynamic[orderDate], dynamic[customerID], B57)) > 180, "Non-Returning", "Dormant"), IF(AND(MAX(dynamic[sinceLastOrder]) > 365, (DATE(2024,4,30) - MAXIFS(dynamic[orderDate], dynamic[customerID], B57)) > 180), "Dormant", "Regular"))) -> Dormant | H57: 29 | I57: =VLOOKUP(dynamic[productID],products[],2,FALSE) -> Thüringer Rostbratwurst | J57: =VLOOKUP(dynamic[productID],products[],12,FALSE) -> Meat/Poultry | K57: =IF(VLOOKUP(dynamic[productID],products[],7,FALSE)=1,"Discontinued","Current") -> Discontinued | L57: =VLOOKUP(dynamic[productID],products[],IF(YEAR(dynamic[orderDate])=2022,8,IF(YEAR(dynamic[orderDate])=2023,9,IF(YEAR(dynamic[orderDate])=2024,10,NA))),FALSE) -> 70.259453 | M57: 99 | N57: =(dynamic[orderPrice]-dynamic[productCost])/dynamic[productCost] -> 0.40906307 | O57: 10 | P57: 0 | Q57: =dynamic[orderPrice]*dynamic[orderQuantity] -> 990 | R57: =dynamic[orderTotal]*(1-dynamic[discountApllied]) -> 990 | S57: =dynamic[revenue]-(dynamic[productCost]*dynamic[orderQuantity]) -> 287.40547 | T57: =IFERROR(dynamic[profit]/dynamic[revenue], 0) -> 0.29030856
A58: 10268 | B58: GROSR | C58: =VLOOKUP(dynamic[customerID],customers[],2,FALSE) -> GROSELLA-Restaurante | D58: 44772 | E58: =IFERROR(__xludf.DUMMYFUNCTION("COUNTUNIQUEIFS($A$2:$A58,$B$2:$B58,B58)"),1.0) -> 1 | F58: =IF(E58=1, 0, D58 - INDEX($D$2:$D58,MATCH(1, ($B$2:$B58=B58)*($E$2:$E58=E58-1), 0))) -> 0 | G58: =IF(MINIFS(dynamic[orderDate], dynamic[customerID], B58) >= DATE(2024,4,30)-120, "New", IF(MAXIFS(dynamic[orderCount], dynamic[customerID], B58)<=2, IF((DATE(2024,4,30) - MAXIFS(dynamic[orderDate], dynamic[customerID], B58)) > 180, "Non-Returning", "Dormant"), IF(AND(MAX(dynamic[sinceLastOrder]) > 365, (DATE(2024,4,30) - MAXIFS(dynamic[orderDate], dynamic[customerID], B58)) > 180), "Dormant", "Regular"))) -> Dormant | H58: 72 | I58: =VLOOKUP(dynamic[productID],products[],2,FALSE) -> Mozzarella di Giovanni | J58: =VLOOKUP(dynamic[productID],products[],12,FALSE) -> Dairy Products | K58: =IF(VLOOKUP(dynamic[productID],products[],7,FALSE)=1,"Discontinued","Current") -> Current | L58: =VLOOKUP(dynamic[productID],products[],IF(YEAR(dynamic[orderDate])=2022,8,IF(YEAR(dynamic[orderDate])=2023,9,IF(YEAR(dynamic[orderDate])=2024,10,NA))),FALSE) -> 19.208293 | M58: 27.8 | N58: =(dynamic[orderPrice]-dynamic[productCost])/dynamic[productCost] -> 0.44729152 | O58: 4 | P58: 0 | Q58: =dynamic[orderPrice]*dynamic[orderQuantity] -> 111.2 | R58: =dynamic[orderTotal]*(1-dynamic[discountApllied]) -> 111.2 | S58: =dynamic[revenue]-(dynamic[productCost]*dynamic[orderQuantity]) -> 34.366827 | T58: =IFERROR(dynamic[profit]/dynamic[revenue], 0) -> 0.3090542
A59: 10269 | B59: WHITC | C59: =VLOOKUP(dynamic[customerID],customers[],2,FALSE) -> White Clover Markets | D59: 44773 | E59: =IFERROR(__xludf.DUMMYFUNCTION("COUNTUNIQUEIFS($A$2:$A59,$B$2:$B59,B59)"),1.0) -> 1 | F59: =IF(E59=1, 0, D59 - INDEX($D$2:$D59,MATCH(1, ($B$2:$B59=B59)*($E$2:$E59=E59-1), 0))) -> 0 | G59: =IF(MINIFS(dynamic[orderDate], dynamic[customerID], B59) >= DATE(2024,4,30)-120, "New", IF(MAXIFS(dynamic[orderCount], dynamic[customerID], B59)<=2, IF((DATE(2024,4,30) - MAXIFS(dynamic[orderDate], dynamic[customerID], B59)) > 180, "Non-Returning", "Dormant"), IF(AND(MAX(dynamic[sinceLastOrder]) > 365, (DATE(2024,4,30) - MAXIFS(dynamic[orderDate], dynamic[customerID], B59)) > 180), "Dormant", "Regular"))) -> Regular | H59: 33 | I59: =VLOOKUP(dynamic[productID],products[],2,FALSE) -> Geitost | J59: =VLOOKUP(dynamic[productID],products[],12,FALSE) -> Dairy Products | K59: =IF(VLOOKUP(dynamic[productID],products[],7,FALSE)=1,"Discontinued","Current") -> Current | L59: =VLOOKUP(dynamic[productID],products[],IF(YEAR(dynamic[orderDate])=2022,8,IF(YEAR(dynamic[orderDate])=2023,9,IF(YEAR(dynamic[orderDate])=2024,10,NA))),FALSE) -> 1.3938474 | M59: 2 | N59: =(dynamic[orderPrice]-dynamic[productCost])/dynamic[productCost] -> 0.43487727 | O59: 60 | P59: 0.05 | Q59: =dynamic[orderPrice]*dynamic[orderQuantity] -> 120 | R59: =dynamic[orderTotal]*(1-dynamic[discountApllied]) -> 114 | S59: =dynamic[revenue]-(dynamic[productCost]*dynamic[orderQuantity]) -> 30.369154 | T59: =IFERROR(dynamic[profit]/dynamic[revenue], 0) -> 0.26639609
A60: 10269 | B60: WHITC | C60: =VLOOKUP(dynamic[customerID],customers[],2,FALSE) -> White Clover Markets | D60: 44773 | E60: =IFERROR(__xludf.DUMMYFUNCTION("COUNTUNIQUEIFS($A$2:$A60,$B$2:$B60,B60)"),1.0) -> 1 | F60: =IF(E60=1, 0, D60 - INDEX($D$2:$D60,MATCH(1, ($B$2:$B60=B60)*($E$2:$E60=E60-1), 0))) -> 0 | G60: =IF(MINIFS(dynamic[orderDate], dynamic[customerID], B60) >= DATE(2024,4,30)-120, "New", IF(MAXIFS(dynamic[orderCount], dynamic[customerID], B60)<=2, IF((DATE(2024,4,30) - MAXIFS(dynamic[orderDate], dynamic[customerID], B60)) > 180, "Non-Returning", "Dormant"), IF(AND(MAX(dynamic[sinceLastOrder]) > 365, (DATE(2024,4,30) - MAXIFS(dynamic[orderDate], dynamic[customerID], B60)) > 180), "Dormant", "Regular"))) -> Regular | H60: 72 | I60: =VLOOKUP(dynamic[productID],products[],2,FALSE) -> Mozzarella di Giovanni | J60: =VLOOKUP(dynamic[productID],products[],12,FALSE) -> Dairy Products | K60: =IF(VLOOKUP(dynamic[productID],products[],7,FALSE)=1,"Discontinued","Current") -> Current | L60: =VLOOKUP(dynamic[productID],products[],IF(YEAR(dynamic[orderDate])=2022,8,IF(YEAR(dynamic[orderDate])=2023,9,IF(YEAR(dynamic[orderDate])=2024,10,NA))),FALSE) -> 19.208293 | M60: 27.8 | N60: =(dynamic[orderPrice]-dynamic[productCost])/dynamic[productCost] -> 0.44729152 | O60: 20 | P60: 0.05 | Q60: =dynamic[orderPrice]*dynamic[orderQuantity] -> 556 | R60: =dynamic[orderTotal]*(1-dynamic[discountApllied]) -> 528.2 | S60: =dynamic[revenue]-(dynamic[productCost]*dynamic[orderQuantity]) -> 144.03413 | T60: =IFERROR(dynamic[profit]/dynamic[revenue], 0) -> 0.27268863
A61: 10270 | B61: WARTH | C61: =VLOOKUP(dynamic[customerID],customers[],2,FALSE) -> Wartian Herkku | D61: 44774 | E61: =IFERROR(__xludf.DUMMYFUNCTION("COUNTUNIQUEIFS($A$2:$A61,$B$2:$B61,B61)"),2.0) -> 2 | F61: =IF(E61=1, 0, D61 - INDEX($D$2:$D61,MATCH(1, ($B$2:$B61=B61)*($E$2:$E61=E61-1), 0))) -> 6 | G61: =IF(MINIFS(dynamic[orderDate], dynamic[customerID], B61) >= DATE(2024,4,30)-120, "New", IF(MAXIFS(dynamic[orderCount], dynamic[customerID], B61)<=2, IF((DATE(2024,4,30) - MAXIFS(dynamic[orderDate], dynamic[customerID], B61)) > 180, "Non-Returning", "Dormant"), IF(AND(MAX(dynamic[sinceLastOrder]) > 365, (DATE(2024,4,30) - MAXIFS(dynamic[orderDate], dynamic[customerID], B61)) > 180), "Dormant", "Regular"))) -> Regular | H61: 36 | I61: =VLOOKUP(dynamic[productID],products[],2,FALSE) -> Inlagd Sill | J61: =VLOOKUP(dynamic[productID],products[],12,FALSE) -> Seafood | K61: =IF(VLOOKUP(dynamic[productID],products[],7,FALSE)=1,"Discontinued","Current") -> Current | L61: =VLOOKUP(dynamic[productID],products[],IF(YEAR(dynamic[orderDate])=2022,8,IF(YEAR(dynamic[orderDate])=2023,9,IF(YEAR(dynamic[orderDate])=2024,10,NA))),FALSE) -> 9.7682384 | M61: 15.2 | N61: =(dynamic[orderPrice]-dynamic[productCost])/dynamic[productCost] -> 0.55606357 | O61: 30 | P61: 0 | Q61: =dynamic[orderPrice]*dynamic[orderQuantity] -> 456 | R61: =dynamic[orderTotal]*(1-dynamic[discountApllied]) -> 456 | S61: =dynamic[revenue]-(dynamic[productCost]*dynamic[orderQuantity]) -> 162.95285 | T61: =IFERROR(dynamic[profit]/dynamic[revenue], 0) -> 0.35735273
A62: 10270 | B62: WARTH | C62: =VLOOKUP(dynamic[customerID],customers[],2,FALSE) -> Wartian Herkku | D62: 44774 | E62: =IFERROR(__xludf.DUMMYFUNCTION("COUNTUNIQUEIFS($A$2:$A62,$B$2:$B62,B62)"),2.0) -> 2 | F62: =IF(E62=1, 0, D62 - INDEX($D$2:$D62,MATCH(1, ($B$2:$B62=B62)*($E$2:$E62=E62-1), 0))) -> 6 | G62: =IF(MINIFS(dynamic[orderDate], dynamic[customerID], B62) >= DATE(2024,4,30)-120, "New", IF(MAXIFS(dynamic[orderCount], dynamic[customerID], B62)<=2, IF((DATE(2024,4,30) - MAXIFS(dynamic[orderDate], dynamic[customerID], B62)) > 180, "Non-Returning", "Dormant"), IF(AND(MAX(dynamic[sinceLastOrder]) > 365, (DATE(2024,4,30) - MAXIFS(dynamic[orderDate], dynamic[customerID], B62)) > 180), "Dormant", "Regular"))) -> Regular | H62: 43 | I62: =VLOOKUP(dynamic[productID],products[],2,FALSE) -> Ipoh Coffee | J62: =VLOOKUP(dynamic[productID],products[],12,FALSE) -> Beverages | K62: =IF(VLOOKUP(dynamic[productID],products[],7,FALSE)=1,"Discontinued","Current") -> Current | L62: =VLOOKUP(dynamic[productID],products[],IF(YEAR(dynamic[orderDate])=2022,8,IF(YEAR(dynamic[orderDate])=2023,9,IF(YEAR(dynamic[orderDate])=2024,10,NA))),FALSE) -> 25.794919 | M62: 36.8 | N62: =(dynamic[orderPrice]-dynamic[productCost])/dynamic[productCost] -> 0.42663754 | O62: 25 | P62: 0 | Q62: =dynamic[orderPrice]*dynamic[orderQuantity] -> 920 | R62: =dynamic[orderTotal]*(1-dynamic[discountApllied]) -> 920 | S62: =dynamic[revenue]-(dynamic[productCost]*dynamic[orderQuantity]) -> 275.12702 | T62: =IFERROR(dynamic[profit]/dynamic[revenue], 0) -> 0.29905111
A63: 10271 | B63: SPLIR | C63: =VLOOKUP(dynamic[customerID],customers[],2,FALSE) -> Split Rail Beer & Ale | D63: 44774 | E63: =IFERROR(__xludf.DUMMYFUNCTION("COUNTUNIQUEIFS($A$2:$A63,$B$2:$B63,B63)"),1.0) -> 1 | F63: =IF(E63=1, 0, D63 - INDEX($D$2:$D63,MATCH(1, ($B$2:$B63=B63)*($E$2:$E63=E63-1), 0))) -> 0 | G63: =IF(MINIFS(dynamic[orderDate], dynamic[customerID], B63) >= DATE(2024,4,30)-120, "New", IF(MAXIFS(dynamic[orderCount], dynamic[customerID], B63)<=2, IF((DATE(2024,4,30) - MAXIFS(dynamic[orderDate], dynamic[customerID], B63)) > 180, "Non-Returning", "Dormant"), IF(AND(MAX(dynamic[sinceLastOrder]) > 365, (DATE(2024,4,30) - MAXIFS(dynamic[orderDate], dynamic[customerID], B63)) > 180), "Dormant", "Regular"))) -> Regular | H63: 33 | I63: =VLOOKUP(dynamic[productID],products[],2,FALSE) -> Geitost | J63: =VLOOKUP(dynamic[productID],products[],12,FALSE) -> Dairy Products | K63: =IF(VLOOKUP(dynamic[productID],products[],7,FALSE)=1,"Discontinued","Current") -> Current | L63: =VLOOKUP(dynamic[productID],products[],IF(YEAR(dynamic[orderDate])=2022,8,IF(YEAR(dynamic[orderDate])=2023,9,IF(YEAR(dynamic[orderDate])=2024,10,NA))),FALSE) -> 1.3938474 | M63: 2 | N63: =(dynamic[orderPrice]-dynamic[productCost])/dynamic[productCost] -> 0.43487727 | O63: 24 | P63: 0 | Q63: =dynamic[orderPrice]*dynamic[orderQuantity] -> 48 | R63: =dynamic[orderTotal]*(1-dynamic[discountApllied]) -> 48 | S63: =dynamic[revenue]-(dynamic[productCost]*dynamic[orderQuantity]) -> 14.547662 | T63: =IFERROR(dynamic[profit]/dynamic[revenue], 0) -> 0.30307628
A64: 10272 | B64: RATTC | C64: =VLOOKUP(dynamic[customerID],customers[],2,FALSE) -> Rattlesnake Canyon Grocery | D64: 44775 | E64: =IFERROR(__xludf.DUMMYFUNCTION("COUNTUNIQUEIFS($A$2:$A64,$B$2:$B64,B64)"),2.0) -> 2 | F64: =IF(E64=1, 0, D64 - INDEX($D$2:$D64,MATCH(1, ($B$2:$B64=B64)*($E$2:$E64=E64-1), 0))) -> 11 | G64: =IF(MINIFS(dynamic[orderDate], dynamic[customerID], B64) >= DATE(2024,4,30)-120, "New", IF(MAXIFS(dynamic[orderCount], dynamic[customerID], B64)<=2, IF((DATE(2024,4,30) - MAXIFS(dynamic[orderDate], dynamic[customerID], B64)) > 180, "Non-Returning", "Dormant"), IF(AND(MAX(dynamic[sinceLastOrder]) > 365, (DATE(2024,4,30) - MAXIFS(dynamic[orderDate], dynamic[customerID], B64)) > 180), "Dormant", "Regular"))) -> Regular | H64: 20 | I64: =VLOOKUP(dynamic[productID],products[],2,FALSE) -> Sir Rodney's Marmalade | J64: =VLOOKUP(dynamic[productID],products[],12,FALSE) -> Confections | K64: =IF(VLOOKUP(dynamic[productID],products[],7,FALSE)=1,"Discontinued","Current") -> Current | L64: =VLOOKUP(dynamic[productID],products[],IF(YEAR(dynamic[orderDate])=2022,8,IF(YEAR(dynamic[orderDate])=2023,9,IF(YEAR(dynamic[orderDate])=2024,10,NA))),FALSE) -> 45.942474 | M64: 64.8 | N64: =(dynamic[orderPrice]-dynamic[productCost])/dynamic[productCost] -> 0.41045951 | O64: 6 | P64: 0 | Q64: =dynamic[orderPrice]*dynamic[orderQuantity] -> 388.8 | R64: =dynamic[orderTotal]*(1-dynamic[discountApllied]) -> 388.8 | S64: =dynamic[revenue]-(dynamic[productCost]*dynamic[orderQuantity]) -> 113.14515 | T64: =IFERROR(dynamic[profit]/dynamic[revenue], 0) -> 0.2910112
A65: 10272 | B65: RATTC | C65: =VLOOKUP(dynamic[customerID],customers[],2,FALSE) -> Rattlesnake Canyon Grocery | D65: 44775 | E65: =IFERROR(__xludf.DUMMYFUNCTION("COUNTUNIQUEIFS($A$2:$A65,$B$2:$B65,B65)"),2.0) -> 2 | F65: =IF(E65=1, 0, D65 - INDEX($D$2:$D65,MATCH(1, ($B$2:$B65=B65)*($E$2:$E65=E65-1), 0))) -> 11 | G65: =IF(MINIFS(dynamic[orderDate], dynamic[customerID], B65) >= DATE(2024,4,30)-120, "New", IF(MAXIFS(dynamic[orderCount], dynamic[customerID], B65)<=2, IF((DATE(2024,4,30) - MAXIFS(dynamic[orderDate], dynamic[customerID], B65)) > 180, "Non-Returning", "Dormant"), IF(AND(MAX(dynamic[sinceLastOrder]) > 365, (DATE(2024,4,30) - MAXIFS(dynamic[orderDate], dynamic[customerID], B65)) > 180), "Dormant", "Regular"))) -> Regular | H65: 31 | I65: =VLOOKUP(dynamic[productID],products[],2,FALSE) -> Gorgonzola Telino | J65: =VLOOKUP(dynamic[productID],products[],12,FALSE) -> Dairy Products | K65: =IF(VLOOKUP(dynamic[productID],products[],7,FALSE)=1,"Discontinued","Current") -> Current | L65: =VLOOKUP(dynamic[productID],products[],IF(YEAR(dynamic[orderDate])=2022,8,IF(YEAR(dynamic[orderDate])=2023,9,IF(YEAR(dynamic[orderDate])=2024,10,NA))),FALSE) -> 6.4403197 | M65: 10 | N65: =(dynamic[orderPrice]-dynamic[productCost])/dynamic[productCost] -> 0.55271794 | O65: 40 | P65: 0 | Q65: =dynamic[orderPrice]*dynamic[orderQuantity] -> 400 | R65: =dynamic[orderTotal]*(1-dynamic[discountApllied]) -> 400 | S65: =dynamic[revenue]-(dynamic[productCost]*dynamic[orderQuantity]) -> 142.38721 | T65: =IFERROR(dynamic[profit]/dynamic[revenue], 0) -> 0.35596803
A66: 10272 | B66: RATTC | C66: =VLOOKUP(dynamic[customerID],customers[],2,FALSE) -> Rattlesnake Canyon Grocery | D66: 44775 | E66: =IFERROR(__xludf.DUMMYFUNCTION("COUNTUNIQUEIFS($A$2:$A66,$B$2:$B66,B66)"),2.0) -> 2 | F66: =IF(E66=1, 0, D66 - INDEX($D$2:$D66,MATCH(1, ($B$2:$B66=B66)*($E$2:$E66=E66-1), 0))) -> 11 | G66: =IF(MINIFS(dynamic[orderDate], dynamic[customerID], B66) >= DATE(2024,4,30)-120, "New", IF(MAXIFS(dynamic[orderCount], dynamic[customerID], B66)<=2, IF((DATE(2024,4,30) - MAXIFS(dynamic[orderDate], dynamic[customerID], B66)) > 180, "Non-Returning", "Dormant"), IF(AND(MAX(dynamic[sinceLastOrder]) > 365, (DATE(2024,4,30) - MAXIFS(dynamic[orderDate], dynamic[customerID], B66)) > 180), "Dormant", "Regular"))) -> Regular | H66: 72 | I66: =VLOOKUP(dynamic[productID],products[],2,FALSE) -> Mozzarella di Giovanni | J66: =VLOOKUP(dynamic[productID],products[],12,FALSE) -> Dairy Products | K66: =IF(VLOOKUP(dynamic[productID],products[],7,FALSE)=1,"Discontinued","Current") -> Current | L66: =VLOOKUP(dynamic[productID],products[],IF(YEAR(dynamic[orderDate])=2022,8,IF(YEAR(dynamic[orderDate])=2023,9,IF(YEAR(dynamic[orderDate])=2024,10,NA))),FALSE) -> 19.208293 | M66: 27.8 | N66: =(dynamic[orderPrice]-dynamic[productCost])/dynamic[productCost] -> 0.44729152 | O66: 24 | P66: 0 | Q66: =dynamic[orderPrice]*dynamic[orderQuantity] -> 667.2 | R66: =dynamic[orderTotal]*(1-dynamic[discountApllied]) -> 667.2 | S66: =dynamic[revenue]-(dynamic[productCost]*dynamic[orderQuantity]) -> 206.20096 | T66: =IFERROR(dynamic[profit]/dynamic[revenue], 0) -> 0.3090542
A67: 10273 | B67: QUICK | C67: =VLOOKUP(dynamic[customerID],customers[],2,FALSE) -> QUICK-Stop | D67: 44778 | E67: =IFERROR(__xludf.DUMMYFUNCTION("COUNTUNIQUEIFS($A$2:$A67,$B$2:$B67,B67)"),1.0) -> 1 | F67: =IF(E67=1, 0, D67 - INDEX($D$2:$D67,MATCH(1, ($B$2:$B67=B67)*($E$2:$E67=E67-1), 0))) -> 0 | G67: =IF(MINIFS(dynamic[orderDate], dynamic[customerID], B67) >= DATE(2024,4,30)-120, "New", IF(MAXIFS(dynamic[orderCount], dynamic[customerID], B67)<=2, IF((DATE(2024,4,30) - MAXIFS(dynamic[orderDate], dynamic[customerID], B67)) > 180, "Non-Returning", "Dormant"), IF(AND(MAX(dynamic[sinceLastOrder]) > 365, (DATE(2024,4,30) - MAXIFS(dynamic[orderDate], dynamic[customerID], B67)) > 180), "Dormant", "Regular"))) -> Regular | H67: 10 | I67: =VLOOKUP(dynamic[productID],products[],2,FALSE) -> Ikura | J67: =VLOOKUP(dynamic[productID],products[],12,FALSE) -> Seafood | K67: =IF(VLOOKUP(dynamic[productID],products[],7,FALSE)=1,"Discontinued","Current") -> Current | L67: =VLOOKUP(dynamic[productID],products[],IF(YEAR(dynamic[orderDate])=2022,8,IF(YEAR(dynamic[orderDate])=2023,9,IF(YEAR(dynamic[orderDate])=2024,10,NA))),FALSE) -> 16.076307 | M67: 24.8 | N67: =(dynamic[orderPrice]-dynamic[productCost])/dynamic[productCost] -> 0.54264282 | O67: 24 | P67: 0.05 | Q67: =dynamic[orderPrice]*dynamic[orderQuantity] -> 595.2 | R67: =dynamic[orderTotal]*(1-dynamic[discountApllied]) -> 565.44 | S67: =dynamic[revenue]-(dynamic[productCost]*dynamic[orderQuantity]) -> 179.60862 | T67: =IFERROR(dynamic[profit]/dynamic[revenue], 0) -> 0.317644
A68: 10273 | B68: QUICK | C68: =VLOOKUP(dynamic[customerID],customers[],2,FALSE) -> QUICK-Stop | D68: 44778 | E68: =IFERROR(__xludf.DUMMYFUNCTION("COUNTUNIQUEIFS($A$2:$A68,$B$2:$B68,B68)"),1.0) -> 1 | F68: =IF(E68=1, 0, D68 - INDEX($D$2:$D68,MATCH(1, ($B$2:$B68=B68)*($E$2:$E68=E68-1), 0))) -> 0 | G68: =IF(MINIFS(dynamic[orderDate], dynamic[customerID], B68) >= DATE(2024,4,30)-120, "New", IF(MAXIFS(dynamic[orderCount], dynamic[customerID], B68)<=2, IF((DATE(2024,4,30) - MAXIFS(dynamic[orderDate], dynamic[customerID], B68)) > 180, "Non-Returning", "Dormant"), IF(AND(MAX(dynamic[sinceLastOrder]) > 365, (DATE(2024,4,30) - MAXIFS(dynamic[orderDate], dynamic[customerID], B68)) > 180), "Dormant", "Regular"))) -> Regular | H68: 31 | I68: =VLOOKUP(dynamic[productID],products[],2,FALSE) -> Gorgonzola Telino | J68: =VLOOKUP(dynamic[productID],products[],12,FALSE) -> Dairy Products | K68: =IF(VLOOKUP(dynamic[productID],products[],7,FALSE)=1,"Discontinued","Current") -> Current | L68: =VLOOKUP(dynamic[productID],products[],IF(YEAR(dynamic[orderDate])=2022,8,IF(YEAR(dynamic[orderDate])=2023,9,IF(YEAR(dynamic[orderDate])=2024,10,NA))),FALSE) -> 6.4403197 | M68: 10 | N68: =(dynamic[orderPrice]-dynamic[productCost])/dynamic[productCost] -> 0.55271794 | O68: 15 | P68: 0.05 | Q68: =dynamic[orderPrice]*dynamic[orderQuantity] -> 150 | R68: =dynamic[orderTotal]*(1-dynamic[discountApllied]) -> 142.5 | S68: =dynamic[revenue]-(dynamic[productCost]*dynamic[orderQuantity]) -> 45.895204 | T68: =IFERROR(dynamic[profit]/dynamic[revenue], 0) -> 0.32207161
A69: 10273 | B69: QUICK | C69: =VLOOKUP(dynamic[customerID],customers[],2,FALSE) -> QUICK-Stop | D69: 44778 | E69: =IFERROR(__xludf.DUMMYFUNCTION("COUNTUNIQUEIFS($A$2:$A69,$B$2:$B69,B69)"),1.0) -> 1 | F69: =IF(E69=1, 0, D69 - INDEX($D$2:$D69,MATCH(1, ($B$2:$B69=B69)*($E$2:$E69=E69-1), 0))) -> 0 | G69: =IF(MINIFS(dynamic[orderDate], dynamic[customerID], B69) >= DATE(2024,4,30)-120, "New", IF(MAXIFS(dynamic[orderCount], dynamic[customerID], B69)<=2, IF((DATE(2024,4,30) - MAXIFS(dynamic[orderDate], dynamic[customerID], B69)) > 180, "Non-Returning", "Dormant"), IF(AND(MAX(dynamic[sinceLastOrder]) > 365, (DATE(2024,4,30) - MAXIFS(dynamic[orderDate], dynamic[customerID], B69)) > 180), "Dormant", "Regular"))) -> Regular | H69: 33 | I69: =VLOOKUP(dynamic[productID],products[],2,FALSE) -> Geitost | J69: =VLOOKUP(dynamic[productID],products[],12,FALSE) -> Dairy Products | K69: =IF(VLOOKUP(dynamic[productID],products[],7,FALSE)=1,"Discontinued","Current") -> Current | L69: =VLOOKUP(dynamic[productID],products[],IF(YEAR(dynamic[orderDate])=2022,8,IF(YEAR(dynamic[orderDate])=2023,9,IF(YEAR(dynamic[orderDate])=2024,10,NA))),FALSE) -> 1.3938474 | M69: 2 | N69: =(dynamic[orderPrice]-dynamic[productCost])/dynamic[productCost] -> 0.43487727 | O69: 20 | P69: 0 | Q69: =dynamic[orderPrice]*dynamic[orderQuantity] -> 40 | R69: =dynamic[orderTotal]*(1-dynamic[discountApllied]) -> 40 | S69: =dynamic[revenue]-(dynamic[productCost]*dynamic[orderQuantity]) -> 12.123051 | T69: =IFERROR(dynamic[profit]/dynamic[revenue], 0) -> 0.30307628
A70: 10273 | B70: QUICK | C70: =VLOOKUP(dynamic[customerID],customers[],2,FALSE) -> QUICK-Stop | D70: 44778 | E70: =IFERROR(__xludf.DUMMYFUNCTION("COUNTUNIQUEIFS($A$2:$A70,$B$2:$B70,B70)"),1.0) -> 1 | F70: =IF(E70=1, 0, D70 - INDEX($D$2:$D70,MATCH(1, ($B$2:$B70=B70)*($E$2:$E70=E70-1), 0))) -> 0 | G70: =IF(MINIFS(dynamic[orderDate], dynamic[customerID], B70) >= DATE(2024,4,30)-120, "New", IF(MAXIFS(dynamic[orderCount], dynamic[customerID], B70)<=2, IF((DATE(2024,4,30) - MAXIFS(dynamic[orderDate], dynamic[customerID], B70)) > 180, "Non-Returning", "Dormant"), IF(AND(MAX(dynamic[sinceLastOrder]) > 365, (DATE(2024,4,30) - MAXIFS(dynamic[orderDate], dynamic[customerID], B70)) > 180), "Dormant", "Regular"))) -> Regular | H70: 40 | I70: =VLOOKUP(dynamic[productID],products[],2,FALSE) -> Boston Crab Meat | J70: =VLOOKUP(dynamic[productID],products[],12,FALSE) -> Seafood | K70: =IF(VLOOKUP(dynamic[productID],products[],7,FALSE)=1,"Discontinued","Current") -> Current | L70: =VLOOKUP(dynamic[productID],products[],IF(YEAR(dynamic[orderDate])=2022,8,IF(YEAR(dynamic[orderDate])=2023,9,IF(YEAR(dynamic[orderDate])=2024,10,NA))),FALSE) -> 9.6806491 | M70: 14.7 | N70: =(dynamic[orderPrice]-dynamic[productCost])/dynamic[productCost] -> 0.51849322 | O70: 60 | P70: 0.05 | Q70: =dynamic[orderPrice]*dynamic[orderQuantity] -> 882 | R70: =dynamic[orderTotal]*(1-dynamic[discountApllied]) -> 837.9 | S70: =dynamic[revenue]-(dynamic[productCost]*dynamic[orderQuantity]) -> 257.06105 | T70: =IFERROR(dynamic[profit]/dynamic[revenue], 0) -> 0.30679204
A71: 10273 | B71: QUICK | C71: =VLOOKUP(dynamic[customerID],customers[],2,FALSE) -> QUICK-Stop | D71: 44778 | E71: =IFERROR(__xludf.DUMMYFUNCTION("COUNTUNIQUEIFS($A$2:$A71,$B$2:$B71,B71)"),1.0) -> 1 | F71: =IF(E71=1, 0, D71 - INDEX($D$2:$D71,MATCH(1, ($B$2:$B71=B71)*($E$2:$E71=E71-1), 0))) -> 0 | G71: =IF(MINIFS(dynamic[orderDate], dynamic[customerID], B71) >= DATE(2024,4,30)-120, "New", IF(MAXIFS(dynamic[orderCount], dynamic[customerID], B71)<=2, IF((DATE(2024,4,30) - MAXIFS(dynamic[orderDate], dynamic[customerID], B71)) > 180, "Non-Returning", "Dormant"), IF(AND(MAX(dynamic[sinceLastOrder]) > 365, (DATE(2024,4,30) - MAXIFS(dynamic[orderDate], dynamic[customerID], B71)) > 180), "Dormant", "Regular"))) -> Regular | H71: 76 | I71: =VLOOKUP(dynamic[productID],products[],2,FALSE) -> Lakkalikööri | J71: =VLOOKUP(dynamic[productID],products[],12,FALSE) -> Beverages | K71: =IF(VLOOKUP(dynamic[productID],products[],7,FALSE)=1,"Discontinued","Current") -> Current | L71: =VLOOKUP(dynamic[productID],products[],IF(YEAR(dynamic[orderDate])=2022,8,IF(YEAR(dynamic[orderDate])=2023,9,IF(YEAR(dynamic[orderDate])=2024,10,NA))),FALSE) -> 10.196093 | M71: 14.4 | N71: =(dynamic[orderPrice]-dynamic[productCost])/dynamic[productCost] -> 0.41230574 | O71: 33 | P71: 0.05 | Q71: =dynamic[orderPrice]*dynamic[orderQuantity] -> 475.2 | R71: =dynamic[orderTotal]*(1-dynamic[discountApllied]) -> 451.44 | S71: =dynamic[revenue]-(dynamic[productCost]*dynamic[orderQuantity]) -> 114.96895 | T71: =IFERROR(dynamic[profit]/dynamic[revenue], 0) -> 0.2546716
A72: 10274 | B72: VINET | C72: =VLOOKUP(dynamic[customerID],customers[],2,FALSE) -> Vins et alcools Chevalier | D72: 44779 | E72: =IFERROR(__xludf.DUMMYFUNCTION("COUNTUNIQUEIFS($A$2:$A72,$B$2:$B72,B72)"),2.0) -> 2 | F72: =IF(E72=1, 0, D72 - INDEX($D$2:$D72,MATCH(1, ($B$2:$B72=B72)*($E$2:$E72=E72-1), 0))) -> 33 | G72: =IF(MINIFS(dynamic[orderDate], dynamic[customerID], B72) >= DATE(2024,4,30)-120, "New", IF(MAXIFS(dynamic[orderCount], dynamic[customerID], B72)<=2, IF((DATE(2024,4,30) - MAXIFS(dynamic[orderDate], dynamic[customerID], B72)) > 180, "Non-Returning", "Dormant"), IF(AND(MAX(dynamic[sinceLastOrder]) > 365, (DATE(2024,4,30) - MAXIFS(dynamic[orderDate], dynamic[customerID], B72)) > 180), "Dormant", "Regular"))) -> Regular | H72: 71 | I72: =VLOOKUP(dynamic[productID],products[],2,FALSE) -> Flotemysost | J72: =VLOOKUP(dynamic[productID],products[],12,FALSE) -> Dairy Products | K72: =IF(VLOOKUP(dynamic[productID],products[],7,FALSE)=1,"Discontinued","Current") -> Current | L72: =VLOOKUP(dynamic[productID],products[],IF(YEAR(dynamic[orderDate])=2022,8,IF(YEAR(dynamic[orderDate])=2023,9,IF(YEAR(dynamic[orderDate])=2024,10,NA))),FALSE) -> 12.00719 | M72: 17.2 | N72: =(dynamic[orderPrice]-dynamic[productCost])/dynamic[productCost] -> 0.43247501 | O72: 20 | P72: 0 | Q72: =dynamic[orderPrice]*dynamic[orderQuantity] -> 344 | R72: =dynamic[orderTotal]*(1-dynamic[discountApllied]) -> 344 | S72: =dynamic[revenue]-(dynamic[productCost]*dynamic[orderQuantity]) -> 103.85619 | T72: =IFERROR(dynamic[profit]/dynamic[revenue], 0) -> 0.30190754
A73: 10274 | B73: VINET | C73: =VLOOKUP(dynamic[customerID],customers[],2,FALSE) -> Vins et alcools Chevalier | D73: 44779 | E73: =IFERROR(__xludf.DUMMYFUNCTION("COUNTUNIQUEIFS($A$2:$A73,$B$2:$B73,B73)"),2.0) -> 2 | F73: =IF(E73=1, 0, D73 - INDEX($D$2:$D73,MATCH(1, ($B$2:$B73=B73)*($E$2:$E73=E73-1), 0))) -> 33 | G73: =IF(MINIFS(dynamic[orderDate], dynamic[customerID], B73) >= DATE(2024,4,30)-120, "New", IF(MAXIFS(dynamic[orderCount], dynamic[customerID], B73)<=2, IF((DATE(2024,4,30) - MAXIFS(dynamic[orderDate], dynamic[customerID], B73)) > 180, "Non-Returning", "Dormant"), IF(AND(MAX(dynamic[sinceLastOrder]) > 365, (DATE(2024,4,30) - MAXIFS(dynamic[orderDate], dynamic[customerID], B73)) > 180), "Dormant", "Regular"))) -> Regular | H73: 72 | I73: =VLOOKUP(dynamic[productID],products[],2,FALSE) -> Mozzarella di Giovanni | J73: =VLOOKUP(dynamic[productID],products[],12,FALSE) -> Dairy Products | K73: =IF(VLOOKUP(dynamic[productID],products[],7,FALSE)=1,"Discontinued","Current") -> Current | L73: =VLOOKUP(dynamic[productID],products[],IF(YEAR(dynamic[orderDate])=2022,8,IF(YEAR(dynamic[orderDate])=2023,9,IF(YEAR(dynamic[orderDate])=2024,10,NA))),FALSE) -> 19.208293 | M73: 27.8 | N73: =(dynamic[orderPrice]-dynamic[productCost])/dynamic[productCost] -> 0.44729152 | O73: 7 | P73: 0 | Q73: =dynamic[orderPrice]*dynamic[orderQuantity] -> 194.6 | R73: =dynamic[orderTotal]*(1-dynamic[discountApllied]) -> 194.6 | S73: =dynamic[revenue]-(dynamic[productCost]*dynamic[orderQuantity]) -> 60.141947 | T73: =IFERROR(dynamic[profit]/dynamic[revenue], 0) -> 0.3090542
A74: 10275 | B74: MAGAA | C74: =VLOOKUP(dynamic[customerID],customers[],2,FALSE) -> Magazzini Alimentari Riuniti | D74: 44780 | E74: =IFERROR(__xludf.DUMMYFUNCTION("COUNTUNIQUEIFS($A$2:$A74,$B$2:$B74,B74)"),1.0) -> 1 | F74: =IF(E74=1, 0, D74 - INDEX($D$2:$D74,MATCH(1, ($B$2:$B74=B74)*($E$2:$E74=E74-1), 0))) -> 0 | G74: =IF(MINIFS(dynamic[orderDate], dynamic[customerID], B74) >= DATE(2024,4,30)-120, "New", IF(MAXIFS(dynamic[orderCount], dynamic[customerID], B74)<=2, IF((DATE(2024,4,30) - MAXIFS(dynamic[orderDate], dynamic[customerID], B74)) > 180, "Non-Returning", "Dormant"), IF(AND(MAX(dynamic[sinceLastOrder]) > 365, (DATE(2024,4,30) - MAXIFS(dynamic[orderDate], dynamic[customerID], B74)) > 180), "Dormant", "Regular"))) -> Regular | H74: 24 | I74: =VLOOKUP(dynamic[productID],products[],2,FALSE) -> Brigadeiros Maravilhosos da Lilian | J74: =VLOOKUP(dynamic[productID],products[],12,FALSE) -> Confections | K74: =IF(VLOOKUP(dynamic[productID],products[],7,FALSE)=1,"Discontinued","Current") -> Discontinued | L74: =VLOOKUP(dynamic[productID],products[],IF(YEAR(dynamic[orderDate])=2022,8,IF(YEAR(dynamic[orderDate])=2023,9,IF(YEAR(dynamic[orderDate])=2024,10,NA))),FALSE) -> 2.6811725 | M74: 3.6 | N74: =(dynamic[orderPrice]-dynamic[productCost])/dynamic[productCost] -> 0.34269617 | O74: 12 | P74: 0.05 | Q74: =dynamic[orderPrice]*dynamic[orderQuantity] -> 43.2 | R74: =dynamic[orderTotal]*(1-dynamic[discountApllied]) -> 41.04 | S74: =dynamic[revenue]-(dynamic[productCost]*dynamic[orderQuantity]) -> 8.8659305 | T74: =IFERROR(dynamic[profit]/dynamic[revenue], 0) -> 0.21603144
A75: 10275 | B75: MAGAA | C75: =VLOOKUP(dynamic[customerID],customers[],2,FALSE) -> Magazzini Alimentari Riuniti | D75: 44780 | E75: =IFERROR(__xludf.DUMMYFUNCTION("COUNTUNIQUEIFS($A$2:$A75,$B$2:$B75,B75)"),1.0) -> 1 | F75: =IF(E75=1, 0, D75 - INDEX($D$2:$D75,MATCH(1, ($B$2:$B75=B75)*($E$2:$E75=E75-1), 0))) -> 0 | G75: =IF(MINIFS(dynamic[orderDate], dynamic[customerID], B75) >= DATE(2024,4,30)-120, "New", IF(MAXIFS(dynamic[orderCount], dynamic[customerID], B75)<=2, IF((DATE(2024,4,30) - MAXIFS(dynamic[orderDate], dynamic[customerID], B75)) > 180, "Non-Returning", "Dormant"), IF(AND(MAX(dynamic[sinceLastOrder]) > 365, (DATE(2024,4,30) - MAXIFS(dynamic[orderDate], dynamic[customerID], B75)) > 180), "Dormant", "Regular"))) -> Regular | H75: 59 | I75: =VLOOKUP(dynamic[productID],products[],2,FALSE) -> Raclette Courdavault | J75: =VLOOKUP(dynamic[productID],products[],12,FALSE) -> Dairy Products | K75: =IF(VLOOKUP(dynamic[productID],products[],7,FALSE)=1,"Discontinued","Current") -> Current | L75: =VLOOKUP(dynamic[productID],products[],IF(YEAR(dynamic[orderDate])=2022,8,IF(YEAR(dynamic[orderDate])=2023,9,IF(YEAR(dynamic[orderDate])=2024,10,NA))),FALSE) -> 29.20352 | M75: 44 | N75: =(dynamic[orderPrice]-dynamic[productCost])/dynamic[productCost] -> 0.50666771 | O75: 6 | P75: 0.05 | Q75: =dynamic[orderPrice]*dynamic[orderQuantity] -> 264 | R75: =dynamic[orderTotal]*(1-dynamic[discountApllied]) -> 250.8 | S75: =dynamic[revenue]-(dynamic[productCost]*dynamic[orderQuantity]) -> 75.578883 | T75: =IFERROR(dynamic[profit]/dynamic[revenue], 0) -> 0.30135121
A76: 10276 | B76: TORTU | C76: =VLOOKUP(dynamic[customerID],customers[],2,FALSE) -> Tortuga Restaurante | D76: 44781 | E76: =IFERROR(__xludf.DUMMYFUNCTION("COUNTUNIQUEIFS($A$2:$A76,$B$2:$B76,B76)"),1.0) -> 1 | F76: =IF(E76=1, 0, D76 - INDEX($D$2:$D76,MATCH(1, ($B$2:$B76=B76)*($E$2:$E76=E76-1), 0))) -> 0 | G76: =IF(MINIFS(dynamic[orderDate], dynamic[customerID], B76) >= DATE(2024,4,30)-120, "New", IF(MAXIFS(dynamic[orderCount], dynamic[customerID], B76)<=2, IF((DATE(2024,4,30) - MAXIFS(dynamic[orderDate], dynamic[customerID], B76)) > 180, "Non-Returning", "Dormant"), IF(AND(MAX(dynamic[sinceLastOrder]) > 365, (DATE(2024,4,30) - MAXIFS(dynamic[orderDate], dynamic[customerID], B76)) > 180), "Dormant", "Regular"))) -> Regular | H76: 10 | I76: =VLOOKUP(dynamic[productID],products[],2,FALSE) -> Ikura | J76: =VLOOKUP(dynamic[productID],products[],12,FALSE) -> Seafood | K76: =IF(VLOOKUP(dynamic[productID],products[],7,FALSE)=1,"Discontinued","Current") -> Current | L76: =VLOOKUP(dynamic[productID],products[],IF(YEAR(dynamic[orderDate])=2022,8,IF(YEAR(dynamic[orderDate])=2023,9,IF(YEAR(dynamic[orderDate])=2024,10,NA))),FALSE) -> 16.076307 | M76: 24.8 | N76: =(dynamic[orderPrice]-dynamic[productCost])/dynamic[productCost] -> 0.54264282 | O76: 15 | P76: 0 | Q76: =dynamic[orderPrice]*dynamic[orderQuantity] -> 372 | R76: =dynamic[orderTotal]*(1-dynamic[discountApllied]) -> 372 | S76: =dynamic[revenue]-(dynamic[productCost]*dynamic[orderQuantity]) -> 130.85539 | T76: =IFERROR(dynamic[profit]/dynamic[revenue], 0) -> 0.3517618
A77: 10276 | B77: TORTU | C77: =VLOOKUP(dynamic[customerID],customers[],2,FALSE) -> Tortuga Restaurante | D77: 44781 | E77: =IFERROR(__xludf.DUMMYFUNCTION("COUNTUNIQUEIFS($A$2:$A77,$B$2:$B77,B77)"),1.0) -> 1 | F77: =IF(E77=1, 0, D77 - INDEX($D$2:$D77,MATCH(1, ($B$2:$B77=B77)*($E$2:$E77=E77-1), 0))) -> 0 | G77: =IF(MINIFS(dynamic[orderDate], dynamic[customerID], B77) >= DATE(2024,4,30)-120, "New", IF(MAXIFS(dynamic[orderCount], dynamic[customerID], B77)<=2, IF((DATE(2024,4,30) - MAXIFS(dynamic[orderDate], dynamic[customerID], B77)) > 180, "Non-Returning", "Dormant"), IF(AND(MAX(dynamic[sinceLastOrder]) > 365, (DATE(2024,4,30) - MAXIFS(dynamic[orderDate], dynamic[customerID], B77)) > 180), "Dormant", "Regular"))) -> Regular | H77: 13 | I77: =VLOOKUP(dynamic[productID],products[],2,FALSE) -> Konbu | J77: =VLOOKUP(dynamic[productID],products[],12,FALSE) -> Seafood | K77: =IF(VLOOKUP(dynamic[productID],products[],7,FALSE)=1,"Discontinued","Current") -> Current | L77: =VLOOKUP(dynamic[productID],products[],IF(YEAR(dynamic[orderDate])=2022,8,IF(YEAR(dynamic[orderDate])=2023,9,IF(YEAR(dynamic[orderDate])=2024,10,NA))),FALSE) -> 3.2367274 | M77: 4.8 | N77: =(dynamic[orderPrice]-dynamic[productCost])/dynamic[productCost] -> 0.48297939 | O77: 10 | P77: 0 | Q77: =dynamic[orderPrice]*dynamic[orderQuantity] -> 48 | R77: =dynamic[orderTotal]*(1-dynamic[discountApllied]) -> 48 | S77: =dynamic[revenue]-(dynamic[productCost]*dynamic[orderQuantity]) -> 15.632726 | T77: =IFERROR(dynamic[profit]/dynamic[revenue], 0) -> 0.3256818
A78: 10277 | B78: MORGK | C78: =VLOOKUP(dynamic[customerID],customers[],2,FALSE) -> Morgenstern Gesundkost | D78: 44782 | E78: =IFERROR(__xludf.DUMMYFUNCTION("COUNTUNIQUEIFS($A$2:$A78,$B$2:$B78,B78)"),1.0) -> 1 | F78: =IF(E78=1, 0, D78 - INDEX($D$2:$D78,MATCH(1, ($B$2:$B78=B78)*($E$2:$E78=E78-1), 0))) -> 0 | G78: =IF(MINIFS(dynamic[orderDate], dynamic[customerID], B78) >= DATE(2024,4,30)-120, "New", IF(MAXIFS(dynamic[orderCount], dynamic[customerID], B78)<=2, IF((DATE(2024,4,30) - MAXIFS(dynamic[orderDate], dynamic[customerID], B78)) > 180, "Non-Returning", "Dormant"), IF(AND(MAX(dynamic[sinceLastOrder]) > 365, (DATE(2024,4,30) - MAXIFS(dynamic[orderDate], dynamic[customerID], B78)) > 180), "Dormant", "Regular"))) -> Regular | H78: 28 | I78: =VLOOKUP(dynamic[productID],products[],2,FALSE) -> Rössle Sauerkraut | J78: =VLOOKUP(dynamic[productID],products[],12,FALSE) -> Produce | K78: =IF(VLOOKUP(dynamic[productID],products[],7,FALSE)=1,"Discontinued","Current") -> Discontinued | L78: =VLOOKUP(dynamic[productID],products[],IF(YEAR(dynamic[orderDate])=2022,8,IF(YEAR(dynamic[orderDate])=2023,9,IF(YEAR(dynamic[orderDate])=2024,10,NA))),FALSE) -> 27.519923 | M78: 36.4 | N78: =(dynamic[orderPrice]-dynamic[productCost])/dynamic[productCost] -> 0.32267813 | O78: 20 | P78: 0 | Q78: =dynamic[orderPrice]*dynamic[orderQuantity] -> 728 | R78: =dynamic[orderTotal]*(1-dynamic[discountApllied]) -> 728 | S78: =dynamic[revenue]-(dynamic[productCost]*dynamic[orderQuantity]) -> 177.60155 | T78: =IFERROR(dynamic[profit]/dynamic[revenue], 0) -> 0.24395817
A79: 10277 | B79: MORGK | C79: =VLOOKUP(dynamic[customerID],customers[],2,FALSE) -> Morgenstern Gesundkost | D79: 44782 | E79: =IFERROR(__xludf.DUMMYFUNCTION("COUNTUNIQUEIFS($A$2:$A79,$B$2:$B79,B79)"),1.0) -> 1 | F79: =IF(E79=1, 0, D79 - INDEX($D$2:$D79,MATCH(1, ($B$2:$B79=B79)*($E$2:$E79=E79-1), 0))) -> 0 | G79: =IF(MINIFS(dynamic[orderDate], dynamic[customerID], B79) >= DATE(2024,4,30)-120, "New", IF(MAXIFS(dynamic[orderCount], dynamic[customerID], B79)<=2, IF((DATE(2024,4,30) - MAXIFS(dynamic[orderDate], dynamic[customerID], B79)) > 180, "Non-Returning", "Dormant"), IF(AND(MAX(dynamic[sinceLastOrder]) > 365, (DATE(2024,4,30) - MAXIFS(dynamic[orderDate], dynamic[customerID], B79)) > 180), "Dormant", "Regular"))) -> Regular | H79: 62 | I79: =VLOOKUP(dynamic[productID],products[],2,FALSE) -> Tarte au sucre | J79: =VLOOKUP(dynamic[productID],products[],12,FALSE) -> Confections | K79: =IF(VLOOKUP(dynamic[productID],products[],7,FALSE)=1,"Discontinued","Current") -> Current | L79: =VLOOKUP(dynamic[productID],products[],IF(YEAR(dynamic[orderDate])=2022,8,IF(YEAR(dynamic[orderDate])=2023,9,IF(YEAR(dynamic[orderDate])=2024,10,NA))),FALSE) -> 29.359633 | M79: 39.4 | N79: =(dynamic[orderPrice]-dynamic[productCost])/dynamic[productCost] -> 0.34197862 | O79: 12 | P79: 0 | Q79: =dynamic[orderPrice]*dynamic[orderQuantity] -> 472.8 | R79: =dynamic[orderTotal]*(1-dynamic[discountApllied]) -> 472.8 | S79: =dynamic[revenue]-(dynamic[productCost]*dynamic[orderQuantity]) -> 120.4844 | T79: =IFERROR(dynamic[profit]/dynamic[revenue], 0) -> 0.25483164
A80: 10278 | B80: BERGS | C80: =VLOOKUP(dynamic[customerID],customers[],2,FALSE) -> Berglunds snabbköp | D80: 44785 | E80: =IFERROR(__xludf.DUMMYFUNCTION("COUNTUNIQUEIFS($A$2:$A80,$B$2:$B80,B80)"),1.0) -> 1 | F80: =IF(E80=1, 0, D80 - INDEX($D$2:$D80,MATCH(1, ($B$2:$B80=B80)*($E$2:$E80=E80-1), 0))) -> 0 | G80: =IF(MINIFS(dynamic[orderDate], dynamic[customerID], B80) >= DATE(2024,4,30)-120, "New", IF(MAXIFS(dynamic[orderCount], dynamic[customerID], B80)<=2, IF((DATE(2024,4,30) - MAXIFS(dynamic[orderDate], dynamic[customerID], B80)) > 180, "Non-Returning", "Dormant"), IF(AND(MAX(dynamic[sinceLastOrder]) > 365, (DATE(2024,4,30) - MAXIFS(dynamic[orderDate], dynamic[customerID], B80)) > 180), "Dormant", "Regular"))) -> Regular | H80: 44 | I80: =VLOOKUP(dynamic[productID],products[],2,FALSE) -> Gula Malacca | J80: =VLOOKUP(dynamic[productID],products[],12,FALSE) -> Condiments | K80: =IF(VLOOKUP(dynamic[productID],products[],7,FALSE)=1,"Discontinued","Current") -> Current | L80: =VLOOKUP(dynamic[productID],products[],IF(YEAR(dynamic[orderDate])=2022,8,IF(YEAR(dynamic[orderDate])=2023,9,IF(YEAR(dynamic[orderDate])=2024,10,NA))),FALSE) -> 10.651651 | M80: 15.5 | N80: =(dynamic[orderPrice]-dynamic[productCost])/dynamic[productCost] -> 0.45517341 | O80: 16 | P80: 0 | Q80: =dynamic[orderPrice]*dynamic[orderQuantity] -> 248 | R80: =dynamic[orderTotal]*(1-dynamic[discountApllied]) -> 248 | S80: =dynamic[revenue]-(dynamic[productCost]*dynamic[orderQuantity]) -> 77.573577 | T80: =IFERROR(dynamic[profit]/dynamic[revenue], 0) -> 0.31279668
A81: 10278 | B81: BERGS | C81: =VLOOKUP(dynamic[customerID],customers[],2,FALSE) -> Berglunds snabbköp | D81: 44785 | E81: =IFERROR(__xludf.DUMMYFUNCTION("COUNTUNIQUEIFS($A$2:$A81,$B$2:$B81,B81)"),1.0) -> 1 | F81: =IF(E81=1, 0, D81 - INDEX($D$2:$D81,MATCH(1, ($B$2:$B81=B81)*($E$2:$E81=E81-1), 0))) -> 0 | G81: =IF(MINIFS(dynamic[orderDate], dynamic[customerID], B81) >= DATE(2024,4,30)-120, "New", IF(MAXIFS(dynamic[orderCount], dynamic[customerID], B81)<=2, IF((DATE(2024,4,30) - MAXIFS(dynamic[orderDate], dynamic[customerID], B81)) > 180, "Non-Returning", "Dormant"), IF(AND(MAX(dynamic[sinceLastOrder]) > 365, (DATE(2024,4,30) - MAXIFS(dynamic[orderDate], dynamic[customerID], B81)) > 180), "Dormant", "Regular"))) -> Regular | H81: 59 | I81: =VLOOKUP(dynamic[productID],products[],2,FALSE) -> Raclette Courdavault | J81: =VLOOKUP(dynamic[productID],products[],12,FALSE) -> Dairy Products | K81: =IF(VLOOKUP(dynamic[productID],products[],7,FALSE)=1,"Discontinued","Current") -> Current | L81: =VLOOKUP(dynamic[productID],products[],IF(YEAR(dynamic[orderDate])=2022,8,IF(YEAR(dynamic[orderDate])=2023,9,IF(YEAR(dynamic[orderDate])=2024,10,NA))),FALSE) -> 29.20352 | M81: 44 | N81: =(dynamic[orderPrice]-dynamic[productCost])/dynamic[productCost] -> 0.50666771 | O81: 15 | P81: 0 | Q81: =dynamic[orderPrice]*dynamic[orderQuantity] -> 660 | R81: =dynamic[orderTotal]*(1-dynamic[discountApllied]) -> 660 | S81: =dynamic[revenue]-(dynamic[productCost]*dynamic[orderQuantity]) -> 221.94721 | T81: =IFERROR(dynamic[profit]/dynamic[revenue], 0) -> 0.33628365
A82: 10278 | B82: BERGS | C82: =VLOOKUP(dynamic[customerID],customers[],2,FALSE) -> Berglunds snabbköp | D82: 44785 | E82: =IFERROR(__xludf.DUMMYFUNCTION("COUNTUNIQUEIFS($A$2:$A82,$B$2:$B82,B82)"),1.0) -> 1 | F82: =IF(E82=1, 0, D82 - INDEX($D$2:$D82,MATCH(1, ($B$2:$B82=B82)*($E$2:$E82=E82-1), 0))) -> 0 | G82: =IF(MINIFS(dynamic[orderDate], dynamic[customerID], B82) >= DATE(2024,4,30)-120, "New", IF(MAXIFS(dynamic[orderCount], dynamic[customerID], B82)<=2, IF((DATE(2024,4,30) - MAXIFS(dynamic[orderDate], dynamic[customerID], B82)) > 180, "Non-Returning", "Dormant"), IF(AND(MAX(dynamic[sinceLastOrder]) > 365, (DATE(2024,4,30) - MAXIFS(dynamic[orderDate], dynamic[customerID], B82)) > 180), "Dormant", "Regular"))) -> Regular | H82: 63 | I82: =VLOOKUP(dynamic[productID],products[],2,FALSE) -> Vegie-spread | J82: =VLOOKUP(dynamic[productID],products[],12,FALSE) -> Condiments | K82: =IF(VLOOKUP(dynamic[productID],products[],7,FALSE)=1,"Discontinued","Current") -> Current | L82: =VLOOKUP(dynamic[productID],products[],IF(YEAR(dynamic[orderDate])=2022,8,IF(YEAR(dynamic[orderDate])=2023,9,IF(YEAR(dynamic[orderDate])=2024,10,NA))),FALSE) -> 23.813723 | M82: 35.1 | N82: =(dynamic[orderPrice]-dynamic[productCost])/dynamic[productCost] -> 0.47394005 | O82: 8 | P82: 0 | Q82: =dynamic[orderPrice]*dynamic[orderQuantity] -> 280.8 | R82: =dynamic[orderTotal]*(1-dynamic[discountApllied]) -> 280.8 | S82: =dynamic[revenue]-(dynamic[productCost]*dynamic[orderQuantity]) -> 90.290217 | T82: =IFERROR(dynamic[profit]/dynamic[revenue], 0) -> 0.32154636
A83: 10278 | B83: BERGS | C83: =VLOOKUP(dynamic[customerID],customers[],2,FALSE) -> Berglunds snabbköp | D83: 44785 | E83: =IFERROR(__xludf.DUMMYFUNCTION("COUNTUNIQUEIFS($A$2:$A83,$B$2:$B83,B83)"),1.0) -> 1 | F83: =IF(E83=1, 0, D83 - INDEX($D$2:$D83,MATCH(1, ($B$2:$B83=B83)*($E$2:$E83=E83-1), 0))) -> 0 | G83: =IF(MINIFS(dynamic[orderDate], dynamic[customerID], B83) >= DATE(2024,4,30)-120, "New", IF(MAXIFS(dynamic[orderCount], dynamic[customerID], B83)<=2, IF((DATE(2024,4,30) - MAXIFS(dynamic[orderDate], dynamic[customerID], B83)) > 180, "Non-Returning", "Dormant"), IF(AND(MAX(dynamic[sinceLastOrder]) > 365, (DATE(2024,4,30) - MAXIFS(dynamic[orderDate], dynamic[customerID], B83)) > 180), "Dormant", "Regular"))) -> Regular | H83: 73 | I83: =VLOOKUP(dynamic[productID],products[],2,FALSE) -> Röd Kaviar | J83: =VLOOKUP(dynamic[productID],products[],12,FALSE) -> Seafood | K83: =IF(VLOOKUP(dynamic[productID],products[],7,FALSE)=1,"Discontinued","Current") -> Current | L83: =VLOOKUP(dynamic[productID],products[],IF(YEAR(dynamic[orderDate])=2022,8,IF(YEAR(dynamic[orderDate])=2023,9,IF(YEAR(dynamic[orderDate])=2024,10,NA))),FALSE) -> 8.4198187 | M83: 12 | N83: =(dynamic[orderPrice]-dynamic[productCost])/dynamic[productCost] -> 0.42520883 | O83: 25 | P83: 0 | Q83: =dynamic[orderPrice]*dynamic[orderQuantity] -> 300 | R83: =dynamic[orderTotal]*(1-dynamic[discountApllied]) -> 300 | S83: =dynamic[revenue]-(dynamic[productCost]*dynamic[orderQuantity]) -> 89.504532 | T83: =IFERROR(dynamic[profit]/dynamic[revenue], 0) -> 0.29834844
A84: 10279 | B84: LEHMS | C84: =VLOOKUP(dynamic[customerID],customers[],2,FALSE) -> Lehmanns Marktstand | D84: 44786 | E84: =IFERROR(__xludf.DUMMYFUNCTION("COUNTUNIQUEIFS($A$2:$A84,$B$2:$B84,B84)"),1.0) -> 1 | F84: =IF(E84=1, 0, D84 - INDEX($D$2:$D84,MATCH(1, ($B$2:$B84=B84)*($E$2:$E84=E84-1), 0))) -> 0 | G84: =IF(MINIFS(dynamic[orderDate], dynamic[customerID], B84) >= DATE(2024,4,30)-120, "New", IF(MAXIFS(dynamic[orderCount], dynamic[customerID], B84)<=2, IF((DATE(2024,4,30) - MAXIFS(dynamic[orderDate], dynamic[customerID], B84)) > 180, "Non-Returning", "Dormant"), IF(AND(MAX(dynamic[sinceLastOrder]) > 365, (DATE(2024,4,30) - MAXIFS(dynamic[orderDate], dynamic[customerID], B84)) > 180), "Dormant", "Regular"))) -> Regular | H84: 17 | I84: =VLOOKUP(dynamic[productID],products[],2,FALSE) -> Alice Mutton | J84: =VLOOKUP(dynamic[productID],products[],12,FALSE) -> Meat/Poultry | K84: =IF(VLOOKUP(dynamic[productID],products[],7,FALSE)=1,"Discontinued","Current") -> Discontinued | L84: =VLOOKUP(dynamic[productID],products[],IF(YEAR(dynamic[orderDate])=2022,8,IF(YEAR(dynamic[orderDate])=2023,9,IF(YEAR(dynamic[orderDate])=2024,10,NA))),FALSE) -> 21.253774 | M84: 31.2 | N84: =(dynamic[orderPrice]-dynamic[productCost])/dynamic[productCost] -> 0.46797458 | O84: 15 | P84: 0.25 | Q84: =dynamic[orderPrice]*dynamic[orderQuantity] -> 468 | R84: =dynamic[orderTotal]*(1-dynamic[discountApllied]) -> 351 | S84: =dynamic[revenue]-(dynamic[productCost]*dynamic[orderQuantity]) -> 32.193389 | T84: =IFERROR(dynamic[profit]/dynamic[revenue], 0) -> 0.091719057
A85: 10280 | B85: BERGS | C85: =VLOOKUP(dynamic[customerID],customers[],2,FALSE) -> Berglunds snabbköp | D85: 44787 | E85: =IFERROR(__xludf.DUMMYFUNCTION("COUNTUNIQUEIFS($A$2:$A85,$B$2:$B85,B85)"),2.0) -> 2 | F85: =IF(E85=1, 0, D85 - INDEX($D$2:$D85,MATCH(1, ($B$2:$B85=B85)*($E$2:$E85=E85-1), 0))) -> 2 | G85: =IF(MINIFS(dynamic[orderDate], dynamic[customerID], B85) >= DATE(2024,4,30)-120, "New", IF(MAXIFS(dynamic[orderCount], dynamic[customerID], B85)<=2, IF((DATE(2024,4,30) - MAXIFS(dynamic[orderDate], dynamic[customerID], B85)) > 180, "Non-Returning", "Dormant"), IF(AND(MAX(dynamic[sinceLastOrder]) > 365, (DATE(2024,4,30) - MAXIFS(dynamic[orderDate], dynamic[customerID], B85)) > 180), "Dormant", "Regular"))) -> Regular | H85: 24 | I85: =VLOOKUP(dynamic[productID],products[],2,FALSE) -> Brigadeiros Maravilhosos da Lilian | J85: =VLOOKUP(dynamic[productID],products[],12,FALSE) -> Confections | K85: =IF(VLOOKUP(dynamic[productID],products[],7,FALSE)=1,"Discontinued","Current") -> Discontinued | L85: =VLOOKUP(dynamic[productID],products[],IF(YEAR(dynamic[orderDate])=2022,8,IF(YEAR(dynamic[orderDate])=2023,9,IF(YEAR(dynamic[orderDate])=2024,10,NA))),FALSE) -> 2.6811725 | M85: 3.6 | N85: =(dynamic[orderPrice]-dynamic[productCost])/dynamic[productCost] -> 0.34269617 | O85: 12 | P85: 0 | Q85: =dynamic[orderPrice]*dynamic[orderQuantity] -> 43.2 | R85: =dynamic[orderTotal]*(1-dynamic[discountApllied]) -> 43.2 | S85: =dynamic[revenue]-(dynamic[productCost]*dynamic[orderQuantity]) -> 11.02593 | T85: =IFERROR(dynamic[profit]/dynamic[revenue], 0) -> 0.25522987
A86: 10280 | B86: BERGS | C86: =VLOOKUP(dynamic[customerID],customers[],2,FALSE) -> Berglunds snabbköp | D86: 44787 | E86: =IFERROR(__xludf.DUMMYFUNCTION("COUNTUNIQUEIFS($A$2:$A86,$B$2:$B86,B86)"),2.0) -> 2 | F86: =IF(E86=1, 0, D86 - INDEX($D$2:$D86,MATCH(1, ($B$2:$B86=B86)*($E$2:$E86=E86-1), 0))) -> 2 | G86: =IF(MINIFS(dynamic[orderDate], dynamic[customerID], B86) >= DATE(2024,4,30)-120, "New", IF(MAXIFS(dynamic[orderCount], dynamic[customerID], B86)<=2, IF((DATE(2024,4,30) - MAXIFS(dynamic[orderDate], dynamic[customerID], B86)) > 180, "Non-Returning", "Dormant"), IF(AND(MAX(dynamic[sinceLastOrder]) > 365, (DATE(2024,4,30) - MAXIFS(dynamic[orderDate], dynamic[customerID], B86)) > 180), "Dormant", "Regular"))) -> Regular | H86: 55 | I86: =VLOOKUP(dynamic[productID],products[],2,FALSE) -> Pâté chinois | J86: =VLOOKUP(dynamic[productID],products[],12,FALSE) -> Meat/Poultry | K86: =IF(VLOOKUP(dynamic[productID],products[],7,FALSE)=1,"Discontinued","Current") -> Current | L86: =VLOOKUP(dynamic[productID],products[],IF(YEAR(dynamic[orderDate])=2022,8,IF(YEAR(dynamic[orderDate])=2023,9,IF(YEAR(dynamic[orderDate])=2024,10,NA))),FALSE) -> 12.974961 | M86: 19.2 | N86: =(dynamic[orderPrice]-dynamic[productCost])/dynamic[productCost] -> 0.47977329 | O86: 20 | P86: 0 | Q86: =dynamic[orderPrice]*dynamic[orderQuantity] -> 384 | R86: =dynamic[orderTotal]*(1-dynamic[discountApllied]) -> 384 | S86: =dynamic[revenue]-(dynamic[productCost]*dynamic[orderQuantity]) -> 124.50079 | T86: =IFERROR(dynamic[profit]/dynamic[revenue], 0) -> 0.32422081
A87: 10280 | B87: BERGS | C87: =VLOOKUP(dynamic[customerID],customers[],2,FALSE) -> Berglunds snabbköp | D87: 44787 | E87: =IFERROR(__xludf.DUMMYFUNCTION("COUNTUNIQUEIFS($A$2:$A87,$B$2:$B87,B87)"),2.0) -> 2 | F87: =IF(E87=1, 0, D87 - INDEX($D$2:$D87,MATCH(1, ($B$2:$B87=B87)*($E$2:$E87=E87-1), 0))) -> 2 | G87: =IF(MINIFS(dynamic[orderDate], dynamic[customerID], B87) >= DATE(2024,4,30)-120, "New", IF(MAXIFS(dynamic[orderCount], dynamic[customerID], B87)<=2, IF((DATE(2024,4,30) - MAXIFS(dynamic[orderDate], dynamic[customerID], B87)) > 180, "Non-Returning", "Dormant"), IF(AND(MAX(dynamic[sinceLastOrder]) > 365, (DATE(2024,4,30) - MAXIFS(dynamic[orderDate], dynamic[customerID], B87)) > 180), "Dormant", "Regular"))) -> Regular | H87: 75 | I87: =VLOOKUP(dynamic[productID],products[],2,FALSE) -> Rhönbräu Klosterbier | J87: =VLOOKUP(dynamic[productID],products[],12,FALSE) -> Beverages | K87: =IF(VLOOKUP(dynamic[productID],products[],7,FALSE)=1,"Discontinued","Current") -> Current | L87: =VLOOKUP(dynamic[productID],products[],IF(YEAR(dynamic[orderDate])=2022,8,IF(YEAR(dynamic[orderDate])=2023,9,IF(YEAR(dynamic[orderDate])=2024,10,NA))),FALSE) -> 4.2690338 | M87: 6.2 | N87: =(dynamic[orderPrice]-dynamic[productCost])/dynamic[productCost] -> 0.45231925 | O87: 30 | P87: 0 | Q87: =dynamic[orderPrice]*dynamic[orderQuantity] -> 186 | R87: =dynamic[orderTotal]*(1-dynamic[discountApllied]) -> 186 | S87: =dynamic[revenue]-(dynamic[productCost]*dynamic[orderQuantity]) -> 57.928985 | T87: =IFERROR(dynamic[profit]/dynamic[revenue], 0) -> 0.31144616
A88: 10281 | B88: ROMEY | C88: =VLOOKUP(dynamic[customerID],customers[],2,FALSE) -> Romero y tomillo | D88: 44787 | E88: =IFERROR(__xludf.DUMMYFUNCTION("COUNTUNIQUEIFS($A$2:$A88,$B$2:$B88,B88)"),1.0) -> 1 | F88: =IF(E88=1, 0, D88 - INDEX($D$2:$D88,MATCH(1, ($B$2:$B88=B88)*($E$2:$E88=E88-1), 0))) -> 0 | G88: =IF(MINIFS(dynamic[orderDate], dynamic[customerID], B88) >= DATE(2024,4,30)-120, "New", IF(MAXIFS(dynamic[orderCount], dynamic[customerID], B88)<=2, IF((DATE(2024,4,30) - MAXIFS(dynamic[orderDate], dynamic[customerID], B88)) > 180, "Non-Returning", "Dormant"), IF(AND(MAX(dynamic[sinceLastOrder]) > 365, (DATE(2024,4,30) - MAXIFS(dynamic[orderDate], dynamic[customerID], B88)) > 180), "Dormant", "Regular"))) -> Regular | H88: 19 | I88: =VLOOKUP(dynamic[productID],products[],2,FALSE) -> Teatime Chocolate Biscuits | J88: =VLOOKUP(dynamic[productID],products[],12,FALSE) -> Confections | K88: =IF(VLOOKUP(dynamic[productID],products[],7,FALSE)=1,"Discontinued","Current") -> Current | L88: =VLOOKUP(dynamic[productID],products[],IF(YEAR(dynamic[orderDate])=2022,8,IF(YEAR(dynamic[orderDate])=2023,9,IF(YEAR(dynamic[orderDate])=2024,10,NA))),FALSE) -> 5.5812009 | M88: 7.3 | N88: =(dynamic[orderPrice]-dynamic[productCost])/dynamic[productCost] -> 0.30796223 | O88: 1 | P88: 0 | Q88: =dynamic[orderPrice]*dynamic[orderQuantity] -> 7.3 | R88: =dynamic[orderTotal]*(1-dynamic[discountApllied]) -> 7.3 | S88: =dynamic[revenue]-(dynamic[productCost]*dynamic[orderQuantity]) -> 1.7187991 | T88: =IFERROR(dynamic[profit]/dynamic[revenue], 0) -> 0.23545193
A89: 10281 | B89: ROMEY | C89: =VLOOKUP(dynamic[customerID],customers[],2,FALSE) -> Romero y tomillo | D89: 44787 | E89: =IFERROR(__xludf.DUMMYFUNCTION("COUNTUNIQUEIFS($A$2:$A89,$B$2:$B89,B89)"),1.0) -> 1 | F89: =IF(E89=1, 0, D89 - INDEX($D$2:$D89,MATCH(1, ($B$2:$B89=B89)*($E$2:$E89=E89-1), 0))) -> 0 | G89: =IF(MINIFS(dynamic[orderDate], dynamic[customerID], B89) >= DATE(2024,4,30)-120, "New", IF(MAXIFS(dynamic[orderCount], dynamic[customerID], B89)<=2, IF((DATE(2024,4,30) - MAXIFS(dynamic[orderDate], dynamic[customerID], B89)) > 180, "Non-Returning", "Dormant"), IF(AND(MAX(dynamic[sinceLastOrder]) > 365, (DATE(2024,4,30) - MAXIFS(dynamic[orderDate], dynamic[customerID], B89)) > 180), "Dormant", "Regular"))) -> Regular | H89: 24 | I89: =VLOOKUP(dynamic[productID],products[],2,FALSE) -> Brigadeiros Maravilhosos da Lilian | J89: =VLOOKUP(dynamic[productID],products[],12,FALSE) -> Confections | K89: =IF(VLOOKUP(dynamic[productID],products[],7,FALSE)=1,"Discontinued","Current") -> Discontinued | L89: =VLOOKUP(dynamic[productID],products[],IF(YEAR(dynamic[orderDate])=2022,8,IF(YEAR(dynamic[orderDate])=2023,9,IF(YEAR(dynamic[orderDate])=2024,10,NA))),FALSE) -> 2.6811725 | M89: 3.6 | N89: =(dynamic[orderPrice]-dynamic[productCost])/dynamic[productCost] -> 0.34269617 | O89: 6 | P89: 0 | Q89: =dynamic[orderPrice]*dynamic[orderQuantity] -> 21.6 | R89: =dynamic[orderTotal]*(1-dynamic[discountApllied]) -> 21.6 | S89: =dynamic[revenue]-(dynamic[productCost]*dynamic[orderQuantity]) -> 5.5129652 | T89: =IFERROR(dynamic[profit]/dynamic[revenue], 0) -> 0.25522987
A90: 10281 | B90: ROMEY | C90: =VLOOKUP(dynamic[customerID],customers[],2,FALSE) -> Romero y tomillo | D90: 44787 | E90: =IFERROR(__xludf.DUMMYFUNCTION("COUNTUNIQUEIFS($A$2:$A90,$B$2:$B90,B90)"),1.0) -> 1 | F90: =IF(E90=1, 0, D90 - INDEX($D$2:$D90,MATCH(1, ($B$2:$B90=B90)*($E$2:$E90=E90-1), 0))) -> 0 | G90: =IF(MINIFS(dynamic[orderDate], dynamic[customerID], B90) >= DATE(2024,4,30)-120, "New", IF(MAXIFS(dynamic[orderCount], dynamic[customerID], B90)<=2, IF((DATE(2024,4,30) - MAXIFS(dynamic[orderDate], dynamic[customerID], B90)) > 180, "Non-Returning", "Dormant"), IF(AND(MAX(dynamic[sinceLastOrder]) > 365, (DATE(2024,4,30) - MAXIFS(dynamic[orderDate], dynamic[customerID], B90)) > 180), "Dormant", "Regular"))) -> Regular | H90: 35 | I90: =VLOOKUP(dynamic[productID],products[],2,FALSE) -> Cold Brew Nitro | J90: =VLOOKUP(dynamic[productID],products[],12,FALSE) -> Beverages | K90: =IF(VLOOKUP(dynamic[productID],products[],7,FALSE)=1,"Discontinued","Current") -> Current | L90: =VLOOKUP(dynamic[productID],products[],IF(YEAR(dynamic[orderDate])=2022,8,IF(YEAR(dynamic[orderDate])=2023,9,IF(YEAR(dynamic[orderDate])=2024,10,NA))),FALSE) -> 10.198691 | M90: 14.4 | N90: =(dynamic[orderPrice]-dynamic[productCost])/dynamic[productCost] -> 0.41194592 | O90: 4 | P90: 0 | Q90: =dynamic[orderPrice]*dynamic[orderQuantity] -> 57.6 | R90: =dynamic[orderTotal]*(1-dynamic[discountApllied]) -> 57.6 | S90: =dynamic[revenue]-(dynamic[productCost]*dynamic[orderQuantity]) -> 16.805236 | T90: =IFERROR(dynamic[profit]/dynamic[revenue], 0) -> 0.29175758
A91: 10282 | B91: ROMEY | C91: =VLOOKUP(dynamic[customerID],customers[],2,FALSE) -> Romero y tomillo | D91: 44788 | E91: =IFERROR(__xludf.DUMMYFUNCTION("COUNTUNIQUEIFS($A$2:$A91,$B$2:$B91,B91)"),2.0) -> 2 | F91: =IF(E91=1, 0, D91 - INDEX($D$2:$D91,MATCH(1, ($B$2:$B91=B91)*($E$2:$E91=E91-1), 0))) -> 1 | G91: =IF(MINIFS(dynamic[orderDate], dynamic[customerID], B91) >= DATE(2024,4,30)-120, "New", IF(MAXIFS(dynamic[orderCount], dynamic[customerID], B91)<=2, IF((DATE(2024,4,30) - MAXIFS(dynamic[orderDate], dynamic[customerID], B91)) > 180, "Non-Returning", "Dormant"), IF(AND(MAX(dynamic[sinceLastOrder]) > 365, (DATE(2024,4,30) - MAXIFS(dynamic[orderDate], dynamic[customerID], B91)) > 180), "Dormant", "Regular"))) -> Regular | H91: 30 | I91: =VLOOKUP(dynamic[productID],products[],2,FALSE) -> Nord-Ost Matjeshering | J91: =VLOOKUP(dynamic[productID],products[],12,FALSE) -> Seafood | K91: =IF(VLOOKUP(dynamic[productID],products[],7,FALSE)=1,"Discontinued","Current") -> Current | L91: =VLOOKUP(dynamic[productID],products[],IF(YEAR(dynamic[orderDate])=2022,8,IF(YEAR(dynamic[orderDate])=2023,9,IF(YEAR(dynamic[orderDate])=2024,10,NA))),FALSE) -> 13.416569 | M91: 20.7 | N91: =(dynamic[orderPrice]-dynamic[productCost])/dynamic[productCost] -> 0.54286841 | O91: 6 | P91: 0 | Q91: =dynamic[orderPrice]*dynamic[orderQuantity] -> 124.2 | R91: =dynamic[orderTotal]*(1-dynamic[discountApllied]) -> 124.2 | S91: =dynamic[revenue]-(dynamic[productCost]*dynamic[orderQuantity]) -> 43.700588 | T91: =IFERROR(dynamic[profit]/dynamic[revenue], 0) -> 0.35185659
A92: 10282 | B92: ROMEY | C92: =VLOOKUP(dynamic[customerID],customers[],2,FALSE) -> Romero y tomillo | D92: 44788 | E92: =IFERROR(__xludf.DUMMYFUNCTION("COUNTUNIQUEIFS($A$2:$A92,$B$2:$B92,B92)"),2.0) -> 2 | F92: =IF(E92=1, 0, D92 - INDEX($D$2:$D92,MATCH(1, ($B$2:$B92=B92)*($E$2:$E92=E92-1), 0))) -> 1 | G92: =IF(MINIFS(dynamic[orderDate], dynamic[customerID], B92) >= DATE(2024,4,30)-120, "New", IF(MAXIFS(dynamic[orderCount], dynamic[customerID], B92)<=2, IF((DATE(2024,4,30) - MAXIFS(dynamic[orderDate], dynamic[customerID], B92)) > 180, "Non-Returning", "Dormant"), IF(AND(MAX(dynamic[sinceLastOrder]) > 365, (DATE(2024,4,30) - MAXIFS(dynamic[orderDate], dynamic[customerID], B92)) > 180), "Dormant", "Regular"))) -> Regular | H92: 57 | I92: =VLOOKUP(dynamic[productID],products[],2,FALSE) -> Ravioli Angelo | J92: =VLOOKUP(dynamic[productID],products[],12,FALSE) -> Grains/Cereals | K92: =IF(VLOOKUP(dynamic[productID],products[],7,FALSE)=1,"Discontinued","Current") -> Current | L92: =VLOOKUP(dynamic[productID],products[],IF(YEAR(dynamic[orderDate])=2022,8,IF(YEAR(dynamic[orderDate])=2023,9,IF(YEAR(dynamic[orderDate])=2024,10,NA))),FALSE) -> 11.229508 | M92: 15.6 | N92: =(dynamic[orderPrice]-dynamic[productCost])/dynamic[productCost] -> 0.38919715 | O92: 2 | P92: 0 | Q92: =dynamic[orderPrice]*dynamic[orderQuantity] -> 31.2 | R92: =dynamic[orderTotal]*(1-dynamic[discountApllied]) -> 31.2 | S92: =dynamic[revenue]-(dynamic[productCost]*dynamic[orderQuantity]) -> 8.7409847 | T92: =IFERROR(dynamic[profit]/dynamic[revenue], 0) -> 0.28015977
A93: 10283 | B93: LILAS | C93: =VLOOKUP(dynamic[customerID],customers[],2,FALSE) -> LILA-Supermercado | D93: 44789 | E93: =IFERROR(__xludf.DUMMYFUNCTION("COUNTUNIQUEIFS($A$2:$A93,$B$2:$B93,B93)"),1.0) -> 1 | F93: =IF(E93=1, 0, D93 - INDEX($D$2:$D93,MATCH(1, ($B$2:$B93=B93)*($E$2:$E93=E93-1), 0))) -> 0 | G93: =IF(MINIFS(dynamic[orderDate], dynamic[customerID], B93) >= DATE(2024,4,30)-120, "New", IF(MAXIFS(dynamic[orderCount], dynamic[customerID], B93)<=2, IF((DATE(2024,4,30) - MAXIFS(dynamic[orderDate], dynamic[customerID], B93)) > 180, "Non-Returning", "Dormant"), IF(AND(MAX(dynamic[sinceLastOrder]) > 365, (DATE(2024,4,30) - MAXIFS(dynamic[orderDate], dynamic[customerID], B93)) > 180), "Dormant", "Regular"))) -> Regular | H93: 15 | I93: =VLOOKUP(dynamic[productID],products[],2,FALSE) -> Genen Shouyu | J93: =VLOOKUP(dynamic[productID],products[],12,FALSE) -> Condiments | K93: =IF(VLOOKUP(dynamic[productID],products[],7,FALSE)=1,"Discontinued","Current") -> Current | L93: =VLOOKUP(dynamic[productID],products[],IF(YEAR(dynamic[orderDate])=2022,8,IF(YEAR(dynamic[orderDate])=2023,9,IF(YEAR(dynamic[orderDate])=2024,10,NA))),FALSE) -> 8.7559169 | M93: 12.4 | N93: =(dynamic[orderPrice]-dynamic[productCost])/dynamic[productCost] -> 0.41618521 | O93: 20 | P93: 0 | Q93: =dynamic[orderPrice]*dynamic[orderQuantity] -> 248 | R93: =dynamic[orderTotal]*(1-dynamic[discountApllied]) -> 248 | S93: =dynamic[revenue]-(dynamic[productCost]*dynamic[orderQuantity]) -> 72.881663 | T93: =IFERROR(dynamic[profit]/dynamic[revenue], 0) -> 0.29387767
A94: 10283 | B94: LILAS | C94: =VLOOKUP(dynamic[customerID],customers[],2,FALSE) -> LILA-Supermercado | D94: 44789 | E94: =IFERROR(__xludf.DUMMYFUNCTION("COUNTUNIQUEIFS($A$2:$A94,$B$2:$B94,B94)"),1.0) -> 1 | F94: =IF(E94=1, 0, D94 - INDEX($D$2:$D94,MATCH(1, ($B$2:$B94=B94)*($E$2:$E94=E94-1), 0))) -> 0 | G94: =IF(MINIFS(dynamic[orderDate], dynamic[customerID], B94) >= DATE(2024,4,30)-120, "New", IF(MAXIFS(dynamic[orderCount], dynamic[customerID], B94)<=2, IF((DATE(2024,4,30) - MAXIFS(dynamic[orderDate], dynamic[customerID], B94)) > 180, "Non-Returning", "Dormant"), IF(AND(MAX(dynamic[sinceLastOrder]) > 365, (DATE(2024,4,30) - MAXIFS(dynamic[orderDate], dynamic[customerID], B94)) > 180), "Dormant", "Regular"))) -> Regular | H94: 19 | I94: =VLOOKUP(dynamic[productID],products[],2,FALSE) -> Teatime Chocolate Biscuits | J94: =VLOOKUP(dynamic[productID],products[],12,FALSE) -> Confections | K94: =IF(VLOOKUP(dynamic[productID],products[],7,FALSE)=1,"Discontinued","Current") -> Current | L94: =VLOOKUP(dynamic[productID],products[],IF(YEAR(dynamic[orderDate])=2022,8,IF(YEAR(dynamic[orderDate])=2023,9,IF(YEAR(dynamic[orderDate])=2024,10,NA))),FALSE) -> 5.5812009 | M94: 7.3 | N94: =(dynamic[orderPrice]-dynamic[productCost])/dynamic[productCost] -> 0.30796223 | O94: 18 | P94: 0 | Q94: =dynamic[orderPrice]*dynamic[orderQuantity] -> 131.4 | R94: =dynamic[orderTotal]*(1-dynamic[discountApllied]) -> 131.4 | S94: =dynamic[revenue]-(dynamic[productCost]*dynamic[orderQuantity]) -> 30.938383 | T94: =IFERROR(dynamic[profit]/dynamic[revenue], 0) -> 0.23545193
A95: 10283 | B95: LILAS | C95: =VLOOKUP(dynamic[customerID],customers[],2,FALSE) -> LILA-Supermercado | D95: 44789 | E95: =IFERROR(__xludf.DUMMYFUNCTION("COUNTUNIQUEIFS($A$2:$A95,$B$2:$B95,B95)"),1.0) -> 1 | F95: =IF(E95=1, 0, D95 - INDEX($D$2:$D95,MATCH(1, ($B$2:$B95=B95)*($E$2:$E95=E95-1), 0))) -> 0 | G95: =IF(MINIFS(dynamic[orderDate], dynamic[customerID], B95) >= DATE(2024,4,30)-120, "New", IF(MAXIFS(dynamic[orderCount], dynamic[customerID], B95)<=2, IF((DATE(2024,4,30) - MAXIFS(dynamic[orderDate], dynamic[customerID], B95)) > 180, "Non-Returning", "Dormant"), IF(AND(MAX(dynamic[sinceLastOrder]) > 365, (DATE(2024,4,30) - MAXIFS(dynamic[orderDate], dynamic[customerID], B95)) > 180), "Dormant", "Regular"))) -> Regular | H95: 60 | I95: =VLOOKUP(dynamic[productID],products[],2,FALSE) -> Camembert Pierrot | J95: =VLOOKUP(dynamic[productID],products[],12,FALSE) -> Dairy Products | K95: =IF(VLOOKUP(dynamic[productID],products[],7,FALSE)=1,"Discontinued","Current") -> Current | L95: =VLOOKUP(dynamic[productID],products[],IF(YEAR(dynamic[orderDate])=2022,8,IF(YEAR(dynamic[orderDate])=2023,9,IF(YEAR(dynamic[orderDate])=2024,10,NA))),FALSE) -> 17.665635 | M95: 27.2 | N95: =(dynamic[orderPrice]-dynamic[productCost])/dynamic[productCost] -> 0.53971256 | O95: 35 | P95: 0 | Q95: =dynamic[orderPrice]*dynamic[orderQuantity] -> 952 | R95: =dynamic[orderTotal]*(1-dynamic[discountApllied]) -> 952 | S95: =dynamic[revenue]-(dynamic[productCost]*dynamic[orderQuantity]) -> 333.70278 | T95: =IFERROR(dynamic[profit]/dynamic[revenue], 0) -> 0.35052813
A96: 10283 | B96: LILAS | C96: =VLOOKUP(dynamic[customerID],customers[],2,FALSE) -> LILA-Supermercado | D96: 44789 | E96: =IFERROR(__xludf.DUMMYFUNCTION("COUNTUNIQUEIFS($A$2:$A96,$B$2:$B96,B96)"),1.0) -> 1 | F96: =IF(E96=1, 0, D96 - INDEX($D$2:$D96,MATCH(1, ($B$2:$B96=B96)*($E$2:$E96=E96-1), 0))) -> 0 | G96: =IF(MINIFS(dynamic[orderDate], dynamic[customerID], B96) >= DATE(2024,4,30)-120, "New", IF(MAXIFS(dynamic[orderCount], dynamic[customerID], B96)<=2, IF((DATE(2024,4,30) - MAXIFS(dynamic[orderDate], dynamic[customerID], B96)) > 180, "Non-Returning", "Dormant"), IF(AND(MAX(dynamic[sinceLastOrder]) > 365, (DATE(2024,4,30) - MAXIFS(dynamic[orderDate], dynamic[customerID], B96)) > 180), "Dormant", "Regular"))) -> Regular | H96: 72 | I96: =VLOOKUP(dynamic[productID],products[],2,FALSE) -> Mozzarella di Giovanni | J96: =VLOOKUP(dynamic[productID],products[],12,FALSE) -> Dairy Products | K96: =IF(VLOOKUP(dynamic[productID],products[],7,FALSE)=1,"Discontinued","Current") -> Current | L96: =VLOOKUP(dynamic[productID],products[],IF(YEAR(dynamic[orderDate])=2022,8,IF(YEAR(dynamic[orderDate])=2023,9,IF(YEAR(dynamic[orderDate])=2024,10,NA))),FALSE) -> 19.208293 | M96: 27.8 | N96: =(dynamic[orderPrice]-dynamic[productCost])/dynamic[productCost] -> 0.44729152 | O96: 3 | P96: 0 | Q96: =dynamic[orderPrice]*dynamic[orderQuantity] -> 83.4 | R96: =dynamic[orderTotal]*(1-dynamic[discountApllied]) -> 83.4 | S96: =dynamic[revenue]-(dynamic[productCost]*dynamic[orderQuantity]) -> 25.77512 | T96: =IFERROR(dynamic[profit]/dynamic[revenue], 0) -> 0.3090542
A97: 10284 | B97: LEHMS | C97: =VLOOKUP(dynamic[customerID],customers[],2,FALSE) -> Lehmanns Marktstand | D97: 44792 | E97: =IFERROR(__xludf.DUMMYFUNCTION("COUNTUNIQUEIFS($A$2:$A97,$B$2:$B97,B97)"),2.0) -> 2 | F97: =IF(E97=1, 0, D97 - INDEX($D$2:$D97,MATCH(1, ($B$2:$B97=B97)*($E$2:$E97=E97-1), 0))) -> 6 | G97: =IF(MINIFS(dynamic[orderDate], dynamic[customerID], B97) >= DATE(2024,4,30)-120, "New", IF(MAXIFS(dynamic[orderCount], dynamic[customerID], B97)<=2, IF((DATE(2024,4,30) - MAXIFS(dynamic[orderDate], dynamic[customerID], B97)) > 180, "Non-Returning", "Dormant"), IF(AND(MAX(dynamic[sinceLastOrder]) > 365, (DATE(2024,4,30) - MAXIFS(dynamic[orderDate], dynamic[customerID], B97)) > 180), "Dormant", "Regular"))) -> Regular | H97: 27 | I97: =VLOOKUP(dynamic[productID],products[],2,FALSE) -> Schoggi Schokolade | J97: =VLOOKUP(dynamic[productID],products[],12,FALSE) -> Confections | K97: =IF(VLOOKUP(dynamic[productID],products[],7,FALSE)=1,"Discontinued","Current") -> Current | L97: =VLOOKUP(dynamic[productID],products[],IF(YEAR(dynamic[orderDate])=2022,8,IF(YEAR(dynamic[orderDate])=2023,9,IF(YEAR(dynamic[orderDate])=2024,10,NA))),FALSE) -> 23.205628 | M97: 35.1 | N97: =(dynamic[orderPrice]-dynamic[productCost])/dynamic[productCost] -> 0.51256408 | O97: 15 | P97: 0.25 | Q97: =dynamic[orderPrice]*dynamic[orderQuantity] -> 526.5 | R97: =dynamic[orderTotal]*(1-dynamic[discountApllied]) -> 394.875 | S97: =dynamic[revenue]-(dynamic[productCost]*dynamic[orderQuantity]) -> 46.790574 | T97: =IFERROR(dynamic[profit]/dynamic[revenue], 0) -> 0.11849465
A98: 10284 | B98: LEHMS | C98: =VLOOKUP(dynamic[customerID],customers[],2,FALSE) -> Lehmanns Marktstand | D98: 44792 | E98: =IFERROR(__xludf.DUMMYFUNCTION("COUNTUNIQUEIFS($A$2:$A98,$B$2:$B98,B98)"),2.0) -> 2 | F98: =IF(E98=1, 0, D98 - INDEX($D$2:$D98,MATCH(1, ($B$2:$B98=B98)*($E$2:$E98=E98-1), 0))) -> 6 | G98: =IF(MINIFS(dynamic[orderDate], dynamic[customerID], B98) >= DATE(2024,4,30)-120, "New", IF(MAXIFS(dynamic[orderCount], dynamic[customerID], B98)<=2, IF((DATE(2024,4,30) - MAXIFS(dynamic[orderDate], dynamic[customerID], B98)) > 180, "Non-Returning", "Dormant"), IF(AND(MAX(dynamic[sinceLastOrder]) > 365, (DATE(2024,4,30) - MAXIFS(dynamic[orderDate], dynamic[customerID], B98)) > 180), "Dormant", "Regular"))) -> Regular | H98: 44 | I98: =VLOOKUP(dynamic[productID],products[],2,FALSE) -> Gula Malacca | J98: =VLOOKUP(dynamic[productID],products[],12,FALSE) -> Condiments | K98: =IF(VLOOKUP(dynamic[productID],products[],7,FALSE)=1,"Discontinued","Current") -> Current | L98: =VLOOKUP(dynamic[productID],products[],IF(YEAR(dynamic[orderDate])=2022,8,IF(YEAR(dynamic[orderDate])=2023,9,IF(YEAR(dynamic[orderDate])=2024,10,NA))),FALSE) -> 10.651651 | M98: 15.5 | N98: =(dynamic[orderPrice]-dynamic[productCost])/dynamic[productCost] -> 0.45517341 | O98: 21 | P98: 0 | Q98: =dynamic[orderPrice]*dynamic[orderQuantity] -> 325.5 | R98: =dynamic[orderTotal]*(1-dynamic[discountApllied]) -> 325.5 | S98: =dynamic[revenue]-(dynamic[productCost]*dynamic[orderQuantity]) -> 101.81532 | T98: =IFERROR(dynamic[profit]/dynamic[revenue], 0) -> 0.31279668
A99: 10284 | B99: LEHMS | C99: =VLOOKUP(dynamic[customerID],customers[],2,FALSE) -> Lehmanns Marktstand | D99: 44792 | E99: =IFERROR(__xludf.DUMMYFUNCTION("COUNTUNIQUEIFS($A$2:$A99,$B$2:$B99,B99)"),2.0) -> 2 | F99: =IF(E99=1, 0, D99 - INDEX($D$2:$D99,MATCH(1, ($B$2:$B99=B99)*($E$2:$E99=E99-1), 0))) -> 6 | G99: =IF(MINIFS(dynamic[orderDate], dynamic[customerID], B99) >= DATE(2024,4,30)-120, "New", IF(MAXIFS(dynamic[orderCount], dynamic[customerID], B99)<=2, IF((DATE(2024,4,30) - MAXIFS(dynamic[orderDate], dynamic[customerID], B99)) > 180, "Non-Returning", "Dormant"), IF(AND(MAX(dynamic[sinceLastOrder]) > 365, (DATE(2024,4,30) - MAXIFS(dynamic[orderDate], dynamic[customerID], B99)) > 180), "Dormant", "Regular"))) -> Regular | H99: 60 | I99: =VLOOKUP(dynamic[productID],products[],2,FALSE) -> Camembert Pierrot | J99: =VLOOKUP(dynamic[productID],products[],12,FALSE) -> Dairy Products | K99: =IF(VLOOKUP(dynamic[productID],products[],7,FALSE)=1,"Discontinued","Current") -> Current | L99: =VLOOKUP(dynamic[productID],products[],IF(YEAR(dynamic[orderDate])=2022,8,IF(YEAR(dynamic[orderDate])=2023,9,IF(YEAR(dynamic[orderDate])=2024,10,NA))),FALSE) -> 17.665635 | M99: 27.2 | N99: =(dynamic[orderPrice]-dynamic[productCost])/dynamic[productCost] -> 0.53971256 | O99: 20 | P99: 0.25 | Q99: =dynamic[orderPrice]*dynamic[orderQuantity] -> 544 | R99: =dynamic[orderTotal]*(1-dynamic[discountApllied]) -> 408 | S99: =dynamic[revenue]-(dynamic[productCost]*dynamic[orderQuantity]) -> 54.687301 | T99: =IFERROR(dynamic[profit]/dynamic[revenue], 0) -> 0.1340375
A100: 10284 | B100: LEHMS | C100: =VLOOKUP(dynamic[customerID],customers[],2,FALSE) -> Lehmanns Marktstand | D100: 44792 | E100: =IFERROR(__xludf.DUMMYFUNCTION("COUNTUNIQUEIFS($A$2:$A100,$B$2:$B100,B100)"),2.0) -> 2 | F100: =IF(E100=1, 0, D100 - INDEX($D$2:$D100,MATCH(1, ($B$2:$B100=B100)*($E$2:$E100=E100-1), 0))) -> 6 | G100: =IF(MINIFS(dynamic[orderDate], dynamic[customerID], B100) >= DATE(2024,4,30)-120, "New", IF(MAXIFS(dynamic[orderCount], dynamic[customerID], B100)<=2, IF((DATE(2024,4,30) - MAXIFS(dynamic[orderDate], dynamic[customerID], B100)) > 180, "Non-Returning", "Dormant"), IF(AND(MAX(dynamic[sinceLastOrder]) > 365, (DATE(2024,4,30) - MAXIFS(dynamic[orderDate], dynamic[customerID], B100)) > 180), "Dormant", "Regular"))) -> Regular | H100: 67 | I100: =VLOOKUP(dynamic[productID],products[],2,FALSE) -> Laughing Lumberjack Lager | J100: =VLOOKUP(dynamic[productID],products[],12,FALSE) -> Beverages | K100: =IF(VLOOKUP(dynamic[productID],products[],7,FALSE)=1,"Discontinued","Current") -> Current | L100: =VLOOKUP(dynamic[productID],products[],IF(YEAR(dynamic[orderDate])=2022,8,IF(YEAR(dynamic[orderDate])=2023,9,IF(YEAR(dynamic[orderDate])=2024,10,NA))),FALSE) -> 6.3335786 | M100: 11.2 | N100: =(dynamic[orderPrice]-dynamic[productCost])/dynamic[productCost] -> 0.76835256 | O100: 5 | P100: 0.25 | Q100: =dynamic[orderPrice]*dynamic[orderQuantity] -> 56 | R100: =dynamic[orderTotal]*(1-dynamic[discountApllied]) -> 42 | S100: =dynamic[revenue]-(dynamic[productCost]*dynamic[orderQuantity]) -> 10.332107 | T100: =IFERROR(dynamic[profit]/dynamic[revenue], 0) -> 0.24600254
...

Sheet analysis-operations
A1: orderID | B1: orderDate | C1: requiredDate | D1: shippedDate | E1: arrivedDate | F1: productID | G1: productName | H1: productStatus | I1: unitsStocked | J1: unitsOrdered | K1: reorderLevel | L1: orderQuantity | M1: orderCount | N1: sinceLastOrder | O1: salesVelocity | P1: freightCost | Q1: shipVia | R1: shipDuration
A2: 10248 | B2: 44746 | C2: 44774 | D2: 44758 | E2: 44766 | F2: 11 | G2: =VLOOKUP(operations[productID],products[],2,FALSE) -> Queso Cabrales | H2: =IF(VLOOKUP(operations[productID],products[],7,FALSE)=1,"Discontinued","Current") -> Current | I2: =VLOOKUP(operations[productID],products[],4,FALSE) -> 22 | J2: =VLOOKUP(operations[productID],products[],5,FALSE) -> 30 | K2: =VLOOKUP(operations[productID],products[],6,FALSE) -> 30 | L2: {=INDEX('1 orders'!I2:I2156, MATCH(1, ('1 orders'!A2:A2156=A2)*('1 orders'!G2:G2156=F2), 0))} -> 12 | M2: =IFERROR(__xludf.DUMMYFUNCTION("COUNTUNIQUEIFS($A$2:$A2,$F$2:$F2,F2)"),1.0) -> 1 | N2: =IF(M2=1, 0, B2 - INDEX($B$2:$B2,MATCH(1, ($F$2:$F2=F2)*($M$2:$M2=M2-1), 0))) -> 0 | O2: =IF(operations[sinceLastOrder]=0,0,operations[orderQuantity] / operations[sinceLastOrder]) -> 0 | P2: 32.38 | Q2: Federal Shipping | R2: =operations[arrivedDate]-operations[shippedDate] -> 8
A3: 10248 | B3: 44746 | C3: 44774 | D3: 44758 | E3: 44766 | F3: 42 | G3: =VLOOKUP(operations[productID],products[],2,FALSE) -> Singaporean Hokkien Fried Mee | H3: =IF(VLOOKUP(operations[productID],products[],7,FALSE)=1,"Discontinued","Current") -> Discontinued | I3: =VLOOKUP(operations[productID],products[],4,FALSE) -> 26 | J3: =VLOOKUP(operations[productID],products[],5,FALSE) -> 0 | K3: =VLOOKUP(operations[productID],products[],6,FALSE) -> 0 | L3: {=INDEX('1 orders'!I3:I2156, MATCH(1, ('1 orders'!A3:A2156=A3)*('1 orders'!G3:G2156=F3), 0))} -> 10 | M3: =IFERROR(__xludf.DUMMYFUNCTION("COUNTUNIQUEIFS($A$2:$A3,$F$2:$F3,F3)"),1.0) -> 1 | N3: =IF(M3=1, 0, B3 - INDEX($B$2:$B3,MATCH(1, ($F$2:$F3=F3)*($M$2:$M3=M3-1), 0))) -> 0 | O3: =IF(operations[sinceLastOrder]=0,0,operations[orderQuantity] / operations[sinceLastOrder]) -> 0 | P3: 32.38 | Q3: Federal Shipping | R3: =operations[arrivedDate]-operations[shippedDate] -> 8
A4: 10248 | B4: 44746 | C4: 44774 | D4: 44758 | E4: 44766 | F4: 72 | G4: =VLOOKUP(operations[productID],products[],2,FALSE) -> Mozzarella di Giovanni | H4: =IF(VLOOKUP(operations[productID],products[],7,FALSE)=1,"Discontinued","Current") -> Current | I4: =VLOOKUP(operations[productID],products[],4,FALSE) -> 14 | J4: =VLOOKUP(operations[productID],products[],5,FALSE) -> 0 | K4: =VLOOKUP(operations[productID],products[],6,FALSE) -> 0 | L4: {=INDEX('1 orders'!I4:I2156, MATCH(1, ('1 orders'!A4:A2156=A4)*('1 orders'!G4:G2156=F4), 0))} -> 5 | M4: =IFERROR(__xludf.DUMMYFUNCTION("COUNTUNIQUEIFS($A$2:$A4,$F$2:$F4,F4)"),1.0) -> 1 | N4: =IF(M4=1, 0, B4 - INDEX($B$2:$B4,MATCH(1, ($F$2:$F4=F4)*($M$2:$M4=M4-1), 0))) -> 0 | O4: =IF(operations[sinceLastOrder]=0,0,operations[orderQuantity] / operations[sinceLastOrder]) -> 0 | P4: 32.38 | Q4: Federal Shipping | R4: =operations[arrivedDate]-operations[shippedDate] -> 8
A5: 10249 | B5: 44747 | C5: 44789 | D5: 44752 | E5: 44756 | F5: 14 | G5: =VLOOKUP(operations[productID],products[],2,FALSE) -> Tofu | H5: =IF(VLOOKUP(operations[productID],products[],7,FALSE)=1,"Discontinued","Current") -> Current | I5: =VLOOKUP(operations[productID],products[],4,FALSE) -> 35 | J5: =VLOOKUP(operations[productID],products[],5,FALSE) -> 0 | K5: =VLOOKUP(operations[productID],products[],6,FALSE) -> 0 | L5: {=INDEX('1 orders'!I5:I2156, MATCH(1, ('1 orders'!A5:A2156=A5)*('1 orders'!G5:G2156=F5), 0))} -> 9 | M5: =IFERROR(__xludf.DUMMYFUNCTION("COUNTUNIQUEIFS($A$2:$A5,$F$2:$F5,F5)"),1.0) -> 1 | N5: =IF(M5=1, 0, B5 - INDEX($B$2:$B5,MATCH(1, ($F$2:$F5=F5)*($M$2:$M5=M5-1), 0))) -> 0 | O5: =IF(operations[sinceLastOrder]=0,0,operations[orderQuantity] / operations[sinceLastOrder]) -> 0 | P5: 11.61 | Q5: Speedy Express | R5: =operations[arrivedDate]-operations[shippedDate] -> 4
A6: 10249 | B6: 44747 | C6: 44789 | D6: 44752 | E6: 44756 | F6: 51 | G6: =VLOOKUP(operations[productID],products[],2,FALSE) -> Manjimup Dried Apples | H6: =IF(VLOOKUP(operations[productID],products[],7,FALSE)=1,"Discontinued","Current") -> Current | I6: =VLOOKUP(operations[productID],products[],4,FALSE) -> 20 | J6: =VLOOKUP(operations[productID],products[],5,FALSE) -> 0 | K6: =VLOOKUP(operations[productID],products[],6,FALSE) -> 10 | L6: {=INDEX('1 orders'!I6:I2156, MATCH(1, ('1 orders'!A6:A2156=A6)*('1 orders'!G6:G2156=F6), 0))} -> 40 | M6: =IFERROR(__xludf.DUMMYFUNCTION("COUNTUNIQUEIFS($A$2:$A6,$F$2:$F6,F6)"),1.0) -> 1 | N6: =IF(M6=1, 0, B6 - INDEX($B$2:$B6,MATCH(1, ($F$2:$F6=F6)*($M$2:$M6=M6-1), 0))) -> 0 | O6: =IF(operations[sinceLastOrder]=0,0,operations[orderQuantity] / operations[sinceLastOrder]) -> 0 | P6: 11.61 | Q6: Speedy Express | R6: =operations[arrivedDate]-operations[shippedDate] -> 4
A7: 10250 | B7: 44750 | C7: 44778 | D7: 44754 | E7: 44771 | F7: 41 | G7: =VLOOKUP(operations[productID],products[],2,FALSE) -> Jack's New England Clam Chowder | H7: =IF(VLOOKUP(operations[productID],products[],7,FALSE)=1,"Discontinued","Current") -> Current | I7: =VLOOKUP(operations[productID],products[],4,FALSE) -> 85 | J7: =VLOOKUP(operations[productID],products[],5,FALSE) -> 0 | K7: =VLOOKUP(operations[productID],products[],6,FALSE) -> 10 | L7: {=INDEX('1 orders'!I7:I2156, MATCH(1, ('1 orders'!A7:A2156=A7)*('1 orders'!G7:G2156=F7), 0))} -> 10 | M7: =IFERROR(__xludf.DUMMYFUNCTION("COUNTUNIQUEIFS($A$2:$A7,$F$2:$F7,F7)"),1.0) -> 1 | N7: =IF(M7=1, 0, B7 - INDEX($B$2:$B7,MATCH(1, ($F$2:$F7=F7)*($M$2:$M7=M7-1), 0))) -> 0 | O7: =IF(operations[sinceLastOrder]=0,0,operations[orderQuantity] / operations[sinceLastOrder]) -> 0 | P7: 65.83 | Q7: United Package | R7: =operations[arrivedDate]-operations[shippedDate] -> 17
A8: 10250 | B8: 44750 | C8: 44778 | D8: 44754 | E8: 44771 | F8: 51 | G8: =VLOOKUP(operations[productID],products[],2,FALSE) -> Manjimup Dried Apples | H8: =IF(VLOOKUP(operations[productID],products[],7,FALSE)=1,"Discontinued","Current") -> Current | I8: =VLOOKUP(operations[productID],products[],4,FALSE) -> 20 | J8: =VLOOKUP(operations[productID],products[],5,FALSE) -> 0 | K8: =VLOOKUP(operations[productID],products[],6,FALSE) -> 10 | L8: {=INDEX('1 orders'!I8:I2156, MATCH(1, ('1 orders'!A8:A2156=A8)*('1 orders'!G8:G2156=F8), 0))} -> 35 | M8: =IFERROR(__xludf.DUMMYFUNCTION("COUNTUNIQUEIFS($A$2:$A8,$F$2:$F8,F8)"),2.0) -> 2 | N8: =IF(M8=1, 0, B8 - INDEX($B$2:$B8,MATCH(1, ($F$2:$F8=F8)*($M$2:$M8=M8-1), 0))) -> 3 | O8: =IF(operations[sinceLastOrder]=0,0,operations[orderQuantity] / operations[sinceLastOrder]) -> 11.666667 | P8: 65.83 | Q8: United Package | R8: =operations[arrivedDate]-operations[shippedDate] -> 17
A9: 10250 | B9: 44750 | C9: 44778 | D9: 44754 | E9: 44771 | F9: 65 | G9: =VLOOKUP(operations[productID],products[],2,FALSE) -> Louisiana Fiery Hot Pepper Sauce | H9: =IF(VLOOKUP(operations[productID],products[],7,FALSE)=1,"Discontinued","Current") -> Current | I9: =VLOOKUP(operations[productID],products[],4,FALSE) -> 76 | J9: =VLOOKUP(operations[productID],products[],5,FALSE) -> 0 | K9: =VLOOKUP(operations[productID],products[],6,FALSE) -> 0 | L9: {=INDEX('1 orders'!I9:I2156, MATCH(1, ('1 orders'!A9:A2156=A9)*('1 orders'!G9:G2156=F9), 0))} -> 15 | M9: =IFERROR(__xludf.DUMMYFUNCTION("COUNTUNIQUEIFS($A$2:$A9,$F$2:$F9,F9)"),1.0) -> 1 | N9: =IF(M9=1, 0, B9 - INDEX($B$2:$B9,MATCH(1, ($F$2:$F9=F9)*($M$2:$M9=M9-1), 0))) -> 0 | O9: =IF(operations[sinceLastOrder]=0,0,operations[orderQuantity] / operations[sinceLastOrder]) -> 0 | P9: 65.83 | Q9: United Package | R9: =operations[arrivedDate]-operations[shippedDate] -> 17
A10: 10251 | B10: 44750 | C10: 44778 | D10: 44757 | E10: 44761 | F10: 22 | G10: =VLOOKUP(operations[productID],products[],2,FALSE) -> Gustaf's Knäckebröd | H10: =IF(VLOOKUP(operations[productID],products[],7,FALSE)=1,"Discontinued","Current") -> Current | I10: =VLOOKUP(operations[productID],products[],4,FALSE) -> 104 | J10: =VLOOKUP(operations[productID],products[],5,FALSE) -> 0 | K10: =VLOOKUP(operations[productID],products[],6,FALSE) -> 25 | L10: {=INDEX('1 orders'!I10:I2156, MATCH(1, ('1 orders'!A10:A2156=A10)*('1 orders'!G10:G2156=F10), 0))} -> 6 | M10: =IFERROR(__xludf.DUMMYFUNCTION("COUNTUNIQUEIFS($A$2:$A10,$F$2:$F10,F10)"),1.0) -> 1 | N10: =IF(M10=1, 0, B10 - INDEX($B$2:$B10,MATCH(1, ($F$2:$F10=F10)*($M$2:$M10=M10-1), 0))) -> 0 | O10: =IF(operations[sinceLastOrder]=0,0,operations[orderQuantity] / operations[sinceLastOrder]) -> 0 | P10: 41.34 | Q10: Speedy Express | R10: =operations[arrivedDate]-operations[shippedDate] -> 4
A11: 10251 | B11: 44750 | C11: 44778 | D11: 44757 | E11: 44761 | F11: 57 | G11: =VLOOKUP(operations[productID],products[],2,FALSE) -> Ravioli Angelo | H11: =IF(VLOOKUP(operations[productID],products[],7,FALSE)=1,"Discontinued","Current") -> Current | I11: =VLOOKUP(operations[productID],products[],4,FALSE) -> 36 | J11: =VLOOKUP(operations[productID],products[],5,FALSE) -> 0 | K11: =VLOOKUP(operations[productID],products[],6,FALSE) -> 20 | L11: {=INDEX('1 orders'!I11:I2156, MATCH(1, ('1 orders'!A11:A2156=A11)*('1 orders'!G11:G2156=F11), 0))} -> 15 | M11: =IFERROR(__xludf.DUMMYFUNCTION("COUNTUNIQUEIFS($A$2:$A11,$F$2:$F11,F11)"),1.0) -> 1 | N11: =IF(M11=1, 0, B11 - INDEX($B$2:$B11,MATCH(1, ($F$2:$F11=F11)*($M$2:$M11=M11-1), 0))) -> 0 | O11: =IF(operations[sinceLastOrder]=0,0,operations[orderQuantity] / operations[sinceLastOrder]) -> 0 | P11: 41.34 | Q11: Speedy Express | R11: =operations[arrivedDate]-operations[shippedDate] -> 4
A12: 10251 | B12: 44750 | C12: 44778 | D12: 44757 | E12: 44761 | F12: 65 | G12: =VLOOKUP(operations[productID],products[],2,FALSE) -> Louisiana Fiery Hot Pepper Sauce | H12: =IF(VLOOKUP(operations[productID],products[],7,FALSE)=1,"Discontinued","Current") -> Current | I12: =VLOOKUP(operations[productID],products[],4,FALSE) -> 76 | J12: =VLOOKUP(operations[productID],products[],5,FALSE) -> 0 | K12: =VLOOKUP(operations[productID],products[],6,FALSE) -> 0 | L12: {=INDEX('1 orders'!I12:I2156, MATCH(1, ('1 orders'!A12:A2156=A12)*('1 orders'!G12:G2156=F12), 0))} -> 20 | M12: =IFERROR(__xludf.DUMMYFUNCTION("COUNTUNIQUEIFS($A$2:$A12,$F$2:$F12,F12)"),2.0) -> 2 | N12: =IF(M12=1, 0, B12 - INDEX($B$2:$B12,MATCH(1, ($F$2:$F12=F12)*($M$2:$M12=M12-1), 0))) -> 0 | O12: =IF(operations[sinceLastOrder]=0,0,operations[orderQuantity] / operations[sinceLastOrder]) -> 0 | P12: 41.34 | Q12: Speedy Express | R12: =operations[arrivedDate]-operations[shippedDate] -> 4
A13: 10252 | B13: 44751 | C13: 44779 | D13: 44753 | E13: 44766 | F13: 20 | G13: =VLOOKUP(operations[productID],products[],2,FALSE) -> Sir Rodney's Marmalade | H13: =IF(VLOOKUP(operations[productID],products[],7,FALSE)=1,"Discontinued","Current") -> Current | I13: =VLOOKUP(operations[productID],products[],4,FALSE) -> 40 | J13: =VLOOKUP(operations[productID],products[],5,FALSE) -> 0 | K13: =VLOOKUP(operations[productID],products[],6,FALSE) -> 0 | L13: {=INDEX('1 orders'!I13:I2156, MATCH(1, ('1 orders'!A13:A2156=A13)*('1 orders'!G13:G2156=F13), 0))} -> 40 | M13: =IFERROR(__xludf.DUMMYFUNCTION("COUNTUNIQUEIFS($A$2:$A13,$F$2:$F13,F13)"),1.0) -> 1 | N13: =IF(M13=1, 0, B13 - INDEX($B$2:$B13,MATCH(1, ($F$2:$F13=F13)*($M$2:$M13=M13-1), 0))) -> 0 | O13: =IF(operations[sinceLastOrder]=0,0,operations[orderQuantity] / operations[sinceLastOrder]) -> 0 | P13: 51.3 | Q13: United Package | R13: =operations[arrivedDate]-operations[shippedDate] -> 13
A14: 10252 | B14: 44751 | C14: 44779 | D14: 44753 | E14: 44766 | F14: 33 | G14: =VLOOKUP(operations[productID],products[],2,FALSE) -> Geitost | H14: =IF(VLOOKUP(operations[productID],products[],7,FALSE)=1,"Discontinued","Current") -> Current | I14: =VLOOKUP(operations[productID],products[],4,FALSE) -> 112 | J14: =VLOOKUP(operations[productID],products[],5,FALSE) -> 0 | K14: =VLOOKUP(operations[productID],products[],6,FALSE) -> 20 | L14: {=INDEX('1 orders'!I14:I2156, MATCH(1, ('1 orders'!A14:A2156=A14)*('1 orders'!G14:G2156=F14), 0))} -> 25 | M14: =IFERROR(__xludf.DUMMYFUNCTION("COUNTUNIQUEIFS($A$2:$A14,$F$2:$F14,F14)"),1.0) -> 1 | N14: =IF(M14=1, 0, B14 - INDEX($B$2:$B14,MATCH(1, ($F$2:$F14=F14)*($M$2:$M14=M14-1), 0))) -> 0 | O14: =IF(operations[sinceLastOrder]=0,0,operations[orderQuantity] / operations[sinceLastOrder]) -> 0 | P14: 51.3 | Q14: United Package | R14: =operations[arrivedDate]-operations[shippedDate] -> 13
A15: 10252 | B15: 44751 | C15: 44779 | D15: 44753 | E15: 44766 | F15: 60 | G15: =VLOOKUP(operations[productID],products[],2,FALSE) -> Camembert Pierrot | H15: =IF(VLOOKUP(operations[productID],products[],7,FALSE)=1,"Discontinued","Current") -> Current | I15: =VLOOKUP(operations[productID],products[],4,FALSE) -> 19 | J15: =VLOOKUP(operations[productID],products[],5,FALSE) -> 0 | K15: =VLOOKUP(operations[productID],products[],6,FALSE) -> 0 | L15: {=INDEX('1 orders'!I15:I2156, MATCH(1, ('1 orders'!A15:A2156=A15)*('1 orders'!G15:G2156=F15), 0))} -> 40 | M15: =IFERROR(__xludf.DUMMYFUNCTION("COUNTUNIQUEIFS($A$2:$A15,$F$2:$F15,F15)"),1.0) -> 1 | N15: =IF(M15=1, 0, B15 - INDEX($B$2:$B15,MATCH(1, ($F$2:$F15=F15)*($M$2:$M15=M15-1), 0))) -> 0 | O15: =IF(operations[sinceLastOrder]=0,0,operations[orderQuantity] / operations[sinceLastOrder]) -> 0 | P15: 51.3 | Q15: United Package | R15: =operations[arrivedDate]-operations[shippedDate] -> 13
